MCPatcher version is 2.1.0
OS: Linux 2.6.35.13-91.fc14.x86_64 amd64
JVM: Sun Microsystems Inc. 1.6.0_25 (64 bit)
Classpath: out/artifacts/mcpatcher/mcpatcher.jar
Minecraft version is 1.6.2 (md5 01330b1c930102a683a4dd8d792e632e)

Analyzing /home/prupe/.minecraft/bin/minecraft-1.6.2.jar (824 files)
  au.class matches Compass.class
  av.class matches TextureFX.class
   a matches onTick
  ce.class matches StillLava.class
  ct.class matches RenderBlocks.class
   a matches renderStandardBlockWithAmbientOcclusion
   b matches renderStandardBlockWithColorMultiplier
   AO faces (N S E W) = (17 18 15 16)
   non-AO multipliers (R G B) = (14 15 16)
  gc.class matches GLAllocation.class
   c matches createDirectByteBuffer
  h.class matches TexturePackBase.class
   a matches getInputStream
  hq.class matches Portal.class
  hu.class matches ColorizerWater.class
  hx.class matches ColorizerGrass.class
  ic.class matches FlowLava.class
  ih.class matches TexturePackList.class
  je.class matches ColorizerFoliage.class
  jf.class matches RenderEngine.class
  kq.class matches Watch.class
  kr.class matches GameSettings.class
  lj.class matches Material.class
  od.class matches FlowWater.class
  ow.class matches TexturePackDefault.class
  qv.class matches ItemRenderer.class
  ry.class matches Fire.class
  se.class matches FontRenderer.class
  se.class matches FontRenderer.class
   font registers = 5, 6
  un.class matches Block.class
  vk.class matches StillWater.class
  wg.class matches BlockGrass.class
   a matches getBlockTexture
  xg.class matches IBlockAccess.class
   f matches getBlockMaterial
  net/minecraft/client/Minecraft.class matches Minecraft.class

Analyzing /home/prupe/.minecraft/bin/minecraft-1.6.2.jar (second pass)
  RenderEngine (jf.class)
   field f matches imageData
   field g matches textureList
   method a matches registerTextureFX
   method b matches refreshTextures
   method a matches readTextureImage
   method a matches readTextureImageData
   method a matches setupTexture
  TextureFX (av.class)
   field a matches imageData
   field b matches tileNumber
   field e matches tileSize
   field f matches tileImage
  Compass (au.class)
  Fire (ry.class)
  StillLava (ce.class)
  FlowLava (ic.class)
  StillWater (vk.class)
  FlowWater (od.class)
  ItemRenderer (qv.class)
  Watch (kq.class)
  Portal (hq.class)
  Minecraft (net/minecraft/client/Minecraft.class)
   field D matches texturePackList
   field p matches renderEngine
   field z matches gameSettings
   field q matches fontRenderer
  GLAllocation (gc.class)
  TexturePackList (ih.class)
   field a matches selectedTexturePack
   field c matches defaultTexturePack
   field e matches minecraft
  TexturePackBase (h.class)
   field a matches texturePackFileName
  TexturePackDefault (ow.class)
  FontRenderer (se.class)
  GameSettings (kr.class)
  ColorizerWater (hu.class)
   field a matches colorBuffer
  ColorizerGrass (hx.class)
   field a matches colorBuffer
  ColorizerFoliage (je.class)
   field a matches colorBuffer
  FontRenderer (se.class)
  Material (lj.class)
   field b matches ground
  Block (un.class)
   method a matches getBlockTexture
  BlockGrass (wg.class)
  IBlockAccess (xg.class)
   method f matches getBlockMaterial
   method a matches getBlockId
   method e matches getBlockMetadata
  RenderBlocks (ct.class)
   field b matches blockAccess

3 available mods:
[YES] HD Textures 1.0 - Provides support for texture packs of 32x32, 64x64, 128x128, and 256x256.
[YES] HD Font 1.0 - Provides support for higher resolution fonts.
[YES] Better Grass 1.0 - Improves the look of the sides of grass blocks. Inspired by MrMessiah's mod.

#### Class map:
HD Textures
    class ColorizerFoliage (je.class)
        field colorBuffer -> a
    class ColorizerGrass (hx.class)
        field colorBuffer -> a
    class ColorizerWater (hu.class)
        field colorBuffer -> a
    class Compass (au.class)
    class Fire (ry.class)
    class FlowLava (ic.class)
    class FlowWater (od.class)
    class FontRenderer (se.class)
    class GLAllocation (gc.class)
        method createDirectByteBuffer -> c
    class GameSettings (kr.class)
    class ItemRenderer (qv.class)
    class Minecraft (net/minecraft/client/Minecraft.class)
        field fontRenderer -> q
        field gameSettings -> z
        field renderEngine -> p
        field texturePackList -> D
    class Portal (hq.class)
    class RenderEngine (jf.class)
        method readTextureImage -> a
        method readTextureImageData -> a
        method refreshTextures -> b
        method registerTextureFX -> a
        method setupTexture -> a
        field imageData -> f
        field textureList -> g
    class StillLava (ce.class)
    class StillWater (vk.class)
    class TextureFX (av.class)
        method onTick -> a
        field imageData -> a
        field tileImage -> f
        field tileNumber -> b
        field tileSize -> e
    class TexturePackBase (h.class)
        method getInputStream -> a
        field texturePackFileName -> a
    class TexturePackDefault (ow.class)
    class TexturePackList (ih.class)
        field defaultTexturePack -> c
        field minecraft -> e
        field selectedTexturePack -> a
    class Watch (kq.class)
    class com.pclewis.mcpatcher.mod.CustomAnimation extends TextureFX
        method onTick -> a
        field imageData -> a
        field tileImage -> f
        field tileNumber -> b
        field tileSize -> e
    class net.minecraft.client.Minecraft alias for Minecraft
    class net.minecraft.src.ColorizerFoliage alias for ColorizerFoliage
    class net.minecraft.src.ColorizerGrass alias for ColorizerGrass
    class net.minecraft.src.ColorizerWater alias for ColorizerWater
    class net.minecraft.src.Compass alias for Compass
    class net.minecraft.src.Fire alias for Fire
    class net.minecraft.src.FlowLava alias for FlowLava
    class net.minecraft.src.FlowWater alias for FlowWater
    class net.minecraft.src.FontRenderer alias for FontRenderer
    class net.minecraft.src.GLAllocation alias for GLAllocation
    class net.minecraft.src.GameSettings alias for GameSettings
    class net.minecraft.src.ItemRenderer alias for ItemRenderer
    class net.minecraft.src.Portal alias for Portal
    class net.minecraft.src.RenderEngine alias for RenderEngine
    class net.minecraft.src.StillLava alias for StillLava
    class net.minecraft.src.StillWater alias for StillWater
    class net.minecraft.src.TextureFX alias for TextureFX
    class net.minecraft.src.TexturePackBase alias for TexturePackBase
    class net.minecraft.src.TexturePackDefault alias for TexturePackDefault
    class net.minecraft.src.TexturePackList alias for TexturePackList
    class net.minecraft.src.Watch alias for Watch

HD Font
    class FontRenderer (se.class)
    class net.minecraft.src.FontRenderer alias for FontRenderer

Better Grass
    class Block (un.class)
        method getBlockTexture -> a
    class BlockGrass (wg.class)
        method getBlockTexture -> a
    class IBlockAccess (xg.class)
        method getBlockId -> a
        method getBlockMaterial -> f
        method getBlockMetadata -> e
    class Material (lj.class)
        field builtSnow -> u
        field ground -> b
        field snow -> t
    class RenderBlocks (ct.class)
        method renderStandardBlockWithAmbientOcclusion -> a
        method renderStandardBlockWithColorMultiplier -> b
        field blockAccess -> b
    class net.minecraft.src.Block alias for Block
    class net.minecraft.src.BlockGrass alias for BlockGrass
    class net.minecraft.src.IBlockAccess alias for IBlockAccess
    class net.minecraft.src.Material alias for Material
    class net.minecraft.src.RenderBlocks alias for RenderBlocks


Patching...
 applying Compass patch to au.class for mod HD Textures
    7.5D -> double_compassCenterMin a@464
     LDC2_W 0x00 0x24          GETSTATIC 0x00 0xa5
    7.5D -> double_compassCenterMin a@675
     LDC2_W 0x00 0x24          GETSTATIC 0x00 0xa5
    8.5D -> double_compassCenterMax a@447
     LDC2_W 0x00 0x26          GETSTATIC 0x00 0xa8
    8.5D -> double_compassCenterMax a@658
     LDC2_W 0x00 0x26          GETSTATIC 0x00 0xa8
    array size 256 -> int_numPixels <init>@12
     SIPUSH 0x01 0x00          GETSTATIC 0x00 0xab
     NEWARRAY 0x0a             NEWARRAY 0x0a
    * 16 -> int_size <init>@48
     BIPUSH 0x10               GETSTATIC 0x00 0xae
     IMUL                      IMUL
    * 16 -> int_size <init>@60
     BIPUSH 0x10               GETSTATIC 0x00 0xae
     IMUL                      IMUL
    * 16 -> int_size a@487
     BIPUSH 0x10               GETSTATIC 0x00 0xae
     IMUL                      IMUL
    * 16 -> int_size a@699
     BIPUSH 0x10               GETSTATIC 0x00 0xae
     IMUL                      IMUL
    while i < 256 -> int_numPixels a@3
     SIPUSH 0x01 0x00          GETSTATIC 0x00 0xab
     IF_ICMPGE 0x00 0xb9       IF_ICMPGE 0x00 0xb9
    -4 -> int_compassCrossMin a@437
     BIPUSH 0xfc               GETSTATIC 0x00 0xb1
    if i > 4 -> int_compassCrossMax a@444
     ICONST_4                  GETSTATIC 0x00 0xb4
     IF_ICMPGT 0x00 0xcc       IF_ICMPGT 0x00 0xcc
    -8 -> int_compassNeedleMin a@651
     BIPUSH 0xf8               GETSTATIC 0x00 0xb7
    if i > 16 -> int_compassNeedleMax a@658
     BIPUSH 0x10               GETSTATIC 0x00 0xba
     IF_ICMPGT 0x00 0xeb       IF_ICMPGT 0x00 0xeb
    getRGB(...16,16,...16) -> getRGB(...int_size,int_size,...int_size) <init>@70
     BIPUSH 0x10               GETSTATIC 0x00 0xae
     BIPUSH 0x10               GETSTATIC 0x00 0xae
     ALOAD_0                   ALOAD_0
     GETFIELD 0x00 0x2f        GETFIELD 0x00 0x2f
     ICONST_0                  ICONST_0
     BIPUSH 0x10               GETSTATIC 0x00 0xae
 applying GetResource patch to au.class for mod HD Textures
    ImageIO.read(getResource(...)) -> getResourceAsBufferedImage(...) <init>@30
     LDC 0x0e                  NOP
     LDC 0x02                  NOP
     INVOKEVIRTUAL 0x00 0x41   NOP
     INVOKESTATIC 0x00 0x46    NOP
                               NOP
                               LDC 0x02
                               INVOKESTATIC 0x00 0xc7
 applying TextureFX patch to av.class for mod HD Textures
    array size 1024 -> int_numBytes <init>@5
     SIPUSH 0x04 0x00          GETSTATIC 0x00 0x36
     NEWARRAY 0x08             NEWARRAY 0x08
 applying StillLava patch to ce.class for mod HD Textures
    array size 256 -> int_numPixels <init>@11
     SIPUSH 0x01 0x00          GETSTATIC 0x00 0x4a
     NEWARRAY 0x06             NEWARRAY 0x06
    array size 256 -> int_numPixels <init>@20
     SIPUSH 0x01 0x00          GETSTATIC 0x00 0x4a
     NEWARRAY 0x06             NEWARRAY 0x06
    array size 256 -> int_numPixels <init>@29
     SIPUSH 0x01 0x00          GETSTATIC 0x00 0x4a
     NEWARRAY 0x06             NEWARRAY 0x06
    array size 256 -> int_numPixels <init>@38
     SIPUSH 0x01 0x00          GETSTATIC 0x00 0x4a
     NEWARRAY 0x06             NEWARRAY 0x06
    while i < 256 -> int_numPixels a@367
     SIPUSH 0x01 0x00          GETSTATIC 0x00 0x4a
     IF_ICMPGE 0x00 0xc7       IF_ICMPGE 0x00 0xc7
    while i < 16 -> int_size a@3
     BIPUSH 0x10               GETSTATIC 0x00 0x4d
     IF_ICMPGE 0x01 0x55       IF_ICMPGE 0x01 0x55
    while i < 16 -> int_size a@12
     BIPUSH 0x10               GETSTATIC 0x00 0x4d
     IF_ICMPGE 0x01 0x47       IF_ICMPGE 0x01 0x47
    & 15 -> int_sizeMinus1 a@89
     BIPUSH 0x0f               GETSTATIC 0x00 0x50
     IAND                      IAND
    & 15 -> int_sizeMinus1 a@100
     BIPUSH 0x0f               GETSTATIC 0x00 0x50
     IAND                      IAND
    & 15 -> int_sizeMinus1 a@155
     BIPUSH 0x0f               GETSTATIC 0x00 0x50
     IAND                      IAND
    & 15 -> int_sizeMinus1 a@162
     BIPUSH 0x0f               GETSTATIC 0x00 0x50
     IAND                      IAND
    & 15 -> int_sizeMinus1 a@178
     BIPUSH 0x0f               GETSTATIC 0x00 0x50
     IAND                      IAND
    & 15 -> int_sizeMinus1 a@185
     BIPUSH 0x0f               GETSTATIC 0x00 0x50
     IAND                      IAND
    & 15 -> int_sizeMinus1 a@202
     BIPUSH 0x0f               GETSTATIC 0x00 0x50
     IAND                      IAND
    & 15 -> int_sizeMinus1 a@209
     BIPUSH 0x0f               GETSTATIC 0x00 0x50
     IAND                      IAND
    & 15 -> int_sizeMinus1 a@226
     BIPUSH 0x0f               GETSTATIC 0x00 0x50
     IAND                      IAND
    & 15 -> int_sizeMinus1 a@233
     BIPUSH 0x0f               GETSTATIC 0x00 0x50
     IAND                      IAND
    * 16 -> int_size a@115
     BIPUSH 0x10               GETSTATIC 0x00 0x4d
     IMUL                      IMUL
    * 16 -> int_size a@141
     BIPUSH 0x10               GETSTATIC 0x00 0x4d
     IMUL                      IMUL
    * 16 -> int_size a@168
     BIPUSH 0x10               GETSTATIC 0x00 0x4d
     IMUL                      IMUL
    * 16 -> int_size a@192
     BIPUSH 0x10               GETSTATIC 0x00 0x4d
     IMUL                      IMUL
    * 16 -> int_size a@217
     BIPUSH 0x10               GETSTATIC 0x00 0x4d
     IMUL                      IMUL
    * 16 -> int_size a@242
     BIPUSH 0x10               GETSTATIC 0x00 0x4d
     IMUL                      IMUL
    * 16 -> int_size a@263
     BIPUSH 0x10               GETSTATIC 0x00 0x4d
     IMUL                      IMUL
    * 16 -> int_size a@276
     BIPUSH 0x10               GETSTATIC 0x00 0x4d
     IMUL                      IMUL
    * 16 -> int_size a@293
     BIPUSH 0x10               GETSTATIC 0x00 0x4d
     IMUL                      IMUL
    * 16 -> int_size a@310
     BIPUSH 0x10               GETSTATIC 0x00 0x4d
     IMUL                      IMUL
    * 16 -> int_size a@323
     BIPUSH 0x10               GETSTATIC 0x00 0x4d
     IMUL                      IMUL
    * 16 -> int_size a@350
     BIPUSH 0x10               GETSTATIC 0x00 0x4d
     IMUL                      IMUL
 applying RenderBlocks patch to ct.class for mod Better Grass
    if (getBlockTexture == 0) useBiomeColor = true (AO) a@482
     label south -> instruction 571
     label north -> instruction 552
     label east -> instruction 514
     label west -> instruction 533
     branch offset IFNE east -> +6 @508
     branch offset IFNE west -> +6 @527
     branch offset IFNE north -> +6 @546
     branch offset IFNE south -> +6 @565
     ICONST_0                  ICONST_0
     DUP                       DUP
     ISTORE 0x12               ISTORE 0x12
     DUP                       DUP
     ISTORE 0x11               ISTORE 0x11
     DUP                       DUP
     ISTORE 0x10               ISTORE 0x10
     DUP                       DUP
     ISTORE 0x0f               ISTORE 0x0f
                               ALOAD_1
                               ALOAD_0
                               GETFIELD 0x00 0xa1
                               ILOAD_2
                               ILOAD_3
                               ILOAD 0x04
                               ICONST_2
                               INVOKEVIRTUAL 0x01 0x0d
                               IFNE 0x00 0x06
                               ICONST_1
                               ISTORE 0x0f
                               ALOAD_1
                               ALOAD_0
                               GETFIELD 0x00 0xa1
                               ILOAD_2
                               ILOAD_3
                               ILOAD 0x04
                               ICONST_3
                               INVOKEVIRTUAL 0x01 0x0d
                               IFNE 0x00 0x06
                               ICONST_1
                               ISTORE 0x10
                               ALOAD_1
                               ALOAD_0
                               GETFIELD 0x00 0xa1
                               ILOAD_2
                               ILOAD_3
                               ILOAD 0x04
                               ICONST_4
                               INVOKEVIRTUAL 0x01 0x0d
                               IFNE 0x00 0x06
                               ICONST_1
                               ISTORE 0x11
                               ALOAD_1
                               ALOAD_0
                               GETFIELD 0x00 0xa1
                               ILOAD_2
                               ILOAD_3
                               ILOAD 0x04
                               ICONST_5
                               INVOKEVIRTUAL 0x01 0x0d
                               IFNE 0x00 0x06
                               ICONST_1
                               ISTORE 0x12
    if (getBlockTexture == 0) useBiomeColor = true (AO) a@580
     label south -> instruction 669
     label north -> instruction 650
     label east -> instruction 612
     label west -> instruction 631
     branch offset IFNE east -> +6 @606
     branch offset IFNE west -> +6 @625
     branch offset IFNE north -> +6 @644
     branch offset IFNE south -> +6 @663
     ICONST_0                  ICONST_0
     DUP                       DUP
     ISTORE 0x12               ISTORE 0x12
     DUP                       DUP
     ISTORE 0x11               ISTORE 0x11
     DUP                       DUP
     ISTORE 0x10               ISTORE 0x10
     DUP                       DUP
     ISTORE 0x0f               ISTORE 0x0f
                               ALOAD_1
                               ALOAD_0
                               GETFIELD 0x00 0xa1
                               ILOAD_2
                               ILOAD_3
                               ILOAD 0x04
                               ICONST_2
                               INVOKEVIRTUAL 0x01 0x0d
                               IFNE 0x00 0x06
                               ICONST_1
                               ISTORE 0x0f
                               ALOAD_1
                               ALOAD_0
                               GETFIELD 0x00 0xa1
                               ILOAD_2
                               ILOAD_3
                               ILOAD 0x04
                               ICONST_3
                               INVOKEVIRTUAL 0x01 0x0d
                               IFNE 0x00 0x06
                               ICONST_1
                               ISTORE 0x10
                               ALOAD_1
                               ALOAD_0
                               GETFIELD 0x00 0xa1
                               ILOAD_2
                               ILOAD_3
                               ILOAD 0x04
                               ICONST_4
                               INVOKEVIRTUAL 0x01 0x0d
                               IFNE 0x00 0x06
                               ICONST_1
                               ISTORE 0x11
                               ALOAD_1
                               ALOAD_0
                               GETFIELD 0x00 0xa1
                               ILOAD_2
                               ILOAD_3
                               ILOAD 0x04
                               ICONST_5
                               INVOKEVIRTUAL 0x01 0x0d
                               IFNE 0x00 0x06
                               ICONST_1
                               ISTORE 0x12
    if (getBlockTexture == 0) useBiomeColor = true (non-AO) b@424
     label A -> instruction 466
     label B -> instruction 486
     branch offset IFNE A -> +26 @440
     branch offset GOTO B -> +23 @463
     ALOAD 0x08                ALOAD_1
     FLOAD 0x12                ALOAD_0
     FLOAD 0x1b                GETFIELD 0x00 0xa1
     FMUL                      ILOAD_2
     FLOAD 0x15                ILOAD_3
     FLOAD 0x1b                ILOAD 0x04
     FMUL                      ICONST_2
     FLOAD 0x18                INVOKEVIRTUAL 0x01 0x0d
     FLOAD 0x1b                DUP
     FMUL                      ISTORE 0x1c
     INVOKEVIRTUAL 0x00 0xfe   IFNE 0x00 0x1a
     ALOAD_1                   ALOAD 0x08
     ALOAD_0                   FLOAD 0x0e
     GETFIELD 0x00 0xa1        FLOAD 0x1b
     ILOAD_2                   FMUL
     ILOAD_3                   FLOAD 0x0f
     ILOAD 0x04                FLOAD 0x1b
     ICONST_2                  FMUL
     INVOKEVIRTUAL 0x01 0x0d   FLOAD 0x10
     ISTORE 0x1c               FLOAD 0x1b
                               FMUL
                               INVOKEVIRTUAL 0x00 0xfe
                               GOTO 0x00 0x17
                               ALOAD 0x08
                               FLOAD 0x12
                               FLOAD 0x1b
                               FMUL
                               FLOAD 0x15
                               FLOAD 0x1b
                               FMUL
                               FLOAD 0x18
                               FLOAD 0x1b
                               FMUL
                               INVOKEVIRTUAL 0x00 0xfe
    if (getBlockTexture == 0) useBiomeColor = true (non-AO) b@619
     label A -> instruction 661
     label B -> instruction 681
     branch offset IFNE A -> +26 @635
     branch offset GOTO B -> +23 @658
     ALOAD 0x08                ALOAD_1
     FLOAD 0x12                ALOAD_0
     FLOAD 0x1b                GETFIELD 0x00 0xa1
     FMUL                      ILOAD_2
     FLOAD 0x15                ILOAD_3
     FLOAD 0x1b                ILOAD 0x04
     FMUL                      ICONST_3
     FLOAD 0x18                INVOKEVIRTUAL 0x01 0x0d
     FLOAD 0x1b                DUP
     FMUL                      ISTORE 0x1c
     INVOKEVIRTUAL 0x00 0xfe   IFNE 0x00 0x1a
     ALOAD_1                   ALOAD 0x08
     ALOAD_0                   FLOAD 0x0e
     GETFIELD 0x00 0xa1        FLOAD 0x1b
     ILOAD_2                   FMUL
     ILOAD_3                   FLOAD 0x0f
     ILOAD 0x04                FLOAD 0x1b
     ICONST_3                  FMUL
     INVOKEVIRTUAL 0x01 0x0d   FLOAD 0x10
     ISTORE 0x1c               FLOAD 0x1b
                               FMUL
                               INVOKEVIRTUAL 0x00 0xfe
                               GOTO 0x00 0x17
                               ALOAD 0x08
                               FLOAD 0x12
                               FLOAD 0x1b
                               FMUL
                               FLOAD 0x15
                               FLOAD 0x1b
                               FMUL
                               FLOAD 0x18
                               FLOAD 0x1b
                               FMUL
                               INVOKEVIRTUAL 0x00 0xfe
    if (getBlockTexture == 0) useBiomeColor = true (non-AO) b@814
     label A -> instruction 856
     label B -> instruction 876
     branch offset IFNE A -> +26 @830
     branch offset GOTO B -> +23 @853
     ALOAD 0x08                ALOAD_1
     FLOAD 0x13                ALOAD_0
     FLOAD 0x1b                GETFIELD 0x00 0xa1
     FMUL                      ILOAD_2
     FLOAD 0x16                ILOAD_3
     FLOAD 0x1b                ILOAD 0x04
     FMUL                      ICONST_4
     FLOAD 0x19                INVOKEVIRTUAL 0x01 0x0d
     FLOAD 0x1b                DUP
     FMUL                      ISTORE 0x1c
     INVOKEVIRTUAL 0x00 0xfe   IFNE 0x00 0x1a
     ALOAD_1                   ALOAD 0x08
     ALOAD_0                   FLOAD 0x0e
     GETFIELD 0x00 0xa1        FLOAD 0x1b
     ILOAD_2                   FMUL
     ILOAD_3                   FLOAD 0x0f
     ILOAD 0x04                FLOAD 0x1b
     ICONST_4                  FMUL
     INVOKEVIRTUAL 0x01 0x0d   FLOAD 0x10
     ISTORE 0x1c               FLOAD 0x1b
                               FMUL
                               INVOKEVIRTUAL 0x00 0xfe
                               GOTO 0x00 0x17
                               ALOAD 0x08
                               FLOAD 0x13
                               FLOAD 0x1b
                               FMUL
                               FLOAD 0x16
                               FLOAD 0x1b
                               FMUL
                               FLOAD 0x19
                               FLOAD 0x1b
                               FMUL
                               INVOKEVIRTUAL 0x00 0xfe
    if (getBlockTexture == 0) useBiomeColor = true (non-AO) b@1009
     label A -> instruction 1051
     label B -> instruction 1071
     branch offset IFNE A -> +26 @1025
     branch offset GOTO B -> +23 @1048
     ALOAD 0x08                ALOAD_1
     FLOAD 0x13                ALOAD_0
     FLOAD 0x1b                GETFIELD 0x00 0xa1
     FMUL                      ILOAD_2
     FLOAD 0x16                ILOAD_3
     FLOAD 0x1b                ILOAD 0x04
     FMUL                      ICONST_5
     FLOAD 0x19                INVOKEVIRTUAL 0x01 0x0d
     FLOAD 0x1b                DUP
     FMUL                      ISTORE 0x1c
     INVOKEVIRTUAL 0x00 0xfe   IFNE 0x00 0x1a
     ALOAD_1                   ALOAD 0x08
     ALOAD_0                   FLOAD 0x0e
     GETFIELD 0x00 0xa1        FLOAD 0x1b
     ILOAD_2                   FMUL
     ILOAD_3                   FLOAD 0x0f
     ILOAD 0x04                FLOAD 0x1b
     ICONST_5                  FMUL
     INVOKEVIRTUAL 0x01 0x0d   FLOAD 0x10
     ISTORE 0x1c               FLOAD 0x1b
                               FMUL
                               INVOKEVIRTUAL 0x00 0xfe
                               GOTO 0x00 0x17
                               ALOAD 0x08
                               FLOAD 0x13
                               FLOAD 0x1b
                               FMUL
                               FLOAD 0x16
                               FLOAD 0x1b
                               FMUL
                               FLOAD 0x19
                               FLOAD 0x1b
                               FMUL
                               INVOKEVIRTUAL 0x00 0xfe
 applying GetResource patch to fw.class for mod HD Textures
    ImageIO.read(getResource(...)) -> getResourceAsBufferedImage(...) <init>@5
     LDC_W 0x00 0x02           NOP
     LDC 0x01                  NOP
     INVOKEVIRTUAL 0x00 0x14   NOP
     INVOKESTATIC 0x00 0x15    NOP
                               NOP
                               NOP
                               LDC 0x01
                               INVOKESTATIC 0x00 0x4b
 applying Portal patch to hq.class for mod HD Textures
    16.0F -> float_size <init>@98
     LDC 0x06                  GETSTATIC 0x00 0x50
    16.0F -> float_size <init>@112
     LDC 0x06                  GETSTATIC 0x00 0x50
    while i < 16 -> int_size <init>@50
     BIPUSH 0x10               GETSTATIC 0x00 0x53
     IF_ICMPGE 0x01 0x6c       IF_ICMPGE 0x01 0x6c
    while i < 16 -> int_size <init>@61
     BIPUSH 0x10               GETSTATIC 0x00 0x53
     IF_ICMPGE 0x01 0x5c       IF_ICMPGE 0x01 0x5c
    array size 32x1024 -> int_numBytes <init>@16
     BIPUSH 0x20               BIPUSH 0x20
     SIPUSH 0x04 0x00          GETSTATIC 0x00 0x56
     MULTIANEWARRAY 0x00 0x0d 0x02  MULTIANEWARRAY 0x00 0x0d 0x02
    * 16 -> int_size <init>@335
     BIPUSH 0x10               GETSTATIC 0x00 0x53
     IMUL                      IMUL
    * 8 -> int_sizeHalf <init>@81
     BIPUSH 0x08               GETSTATIC 0x00 0x59
     IMUL                      IMUL
    * 8 -> int_sizeHalf <init>@90
     BIPUSH 0x08               GETSTATIC 0x00 0x59
     IMUL                      IMUL
    while i < 256 -> int_numPixels a@26
     SIPUSH 0x01 0x00          GETSTATIC 0x00 0x5c
     IF_ICMPGE 0x00 0xb4       IF_ICMPGE 0x00 0xb4
 applying ColorizerWater patch to hu.class for mod HD Textures
    make field colorBuffer public
 applying ColorizerGrass patch to hx.class for mod HD Textures
    make field colorBuffer public
 applying FlowLava patch to ic.class for mod HD Textures
    array size 256 -> int_numPixels <init>@13
     SIPUSH 0x01 0x00          GETSTATIC 0x00 0x50
     NEWARRAY 0x06             NEWARRAY 0x06
    array size 256 -> int_numPixels <init>@22
     SIPUSH 0x01 0x00          GETSTATIC 0x00 0x50
     NEWARRAY 0x06             NEWARRAY 0x06
    array size 256 -> int_numPixels <init>@31
     SIPUSH 0x01 0x00          GETSTATIC 0x00 0x50
     NEWARRAY 0x06             NEWARRAY 0x06
    array size 256 -> int_numPixels <init>@40
     SIPUSH 0x01 0x00          GETSTATIC 0x00 0x50
     NEWARRAY 0x06             NEWARRAY 0x06
    while i < 256 -> int_numPixels a@377
     SIPUSH 0x01 0x00          GETSTATIC 0x00 0x50
     IF_ICMPGE 0x00 0xd5       IF_ICMPGE 0x00 0xd5
    while i < 16 -> int_size a@13
     BIPUSH 0x10               GETSTATIC 0x00 0x53
     IF_ICMPGE 0x01 0x55       IF_ICMPGE 0x01 0x55
    while i < 16 -> int_size a@22
     BIPUSH 0x10               GETSTATIC 0x00 0x53
     IF_ICMPGE 0x01 0x47       IF_ICMPGE 0x01 0x47
    & 255 -> int_numPixelsMinus1 a@400
     SIPUSH 0x00 0xff          GETSTATIC 0x00 0x56
     IAND                      IAND
    & 15 -> int_sizeMinus1 a@99
     BIPUSH 0x0f               GETSTATIC 0x00 0x59
     IAND                      IAND
    & 15 -> int_sizeMinus1 a@110
     BIPUSH 0x0f               GETSTATIC 0x00 0x59
     IAND                      IAND
    & 15 -> int_sizeMinus1 a@165
     BIPUSH 0x0f               GETSTATIC 0x00 0x59
     IAND                      IAND
    & 15 -> int_sizeMinus1 a@172
     BIPUSH 0x0f               GETSTATIC 0x00 0x59
     IAND                      IAND
    & 15 -> int_sizeMinus1 a@188
     BIPUSH 0x0f               GETSTATIC 0x00 0x59
     IAND                      IAND
    & 15 -> int_sizeMinus1 a@195
     BIPUSH 0x0f               GETSTATIC 0x00 0x59
     IAND                      IAND
    & 15 -> int_sizeMinus1 a@212
     BIPUSH 0x0f               GETSTATIC 0x00 0x59
     IAND                      IAND
    & 15 -> int_sizeMinus1 a@219
     BIPUSH 0x0f               GETSTATIC 0x00 0x59
     IAND                      IAND
    & 15 -> int_sizeMinus1 a@236
     BIPUSH 0x0f               GETSTATIC 0x00 0x59
     IAND                      IAND
    & 15 -> int_sizeMinus1 a@243
     BIPUSH 0x0f               GETSTATIC 0x00 0x59
     IAND                      IAND
    * 16 -> int_size a@125
     BIPUSH 0x10               GETSTATIC 0x00 0x53
     IMUL                      IMUL
    * 16 -> int_size a@151
     BIPUSH 0x10               GETSTATIC 0x00 0x53
     IMUL                      IMUL
    * 16 -> int_size a@178
     BIPUSH 0x10               GETSTATIC 0x00 0x53
     IMUL                      IMUL
    * 16 -> int_size a@202
     BIPUSH 0x10               GETSTATIC 0x00 0x53
     IMUL                      IMUL
    * 16 -> int_size a@227
     BIPUSH 0x10               GETSTATIC 0x00 0x53
     IMUL                      IMUL
    * 16 -> int_size a@252
     BIPUSH 0x10               GETSTATIC 0x00 0x53
     IMUL                      IMUL
    * 16 -> int_size a@273
     BIPUSH 0x10               GETSTATIC 0x00 0x53
     IMUL                      IMUL
    * 16 -> int_size a@286
     BIPUSH 0x10               GETSTATIC 0x00 0x53
     IMUL                      IMUL
    * 16 -> int_size a@303
     BIPUSH 0x10               GETSTATIC 0x00 0x53
     IMUL                      IMUL
    * 16 -> int_size a@320
     BIPUSH 0x10               GETSTATIC 0x00 0x53
     IMUL                      IMUL
    * 16 -> int_size a@333
     BIPUSH 0x10               GETSTATIC 0x00 0x53
     IMUL                      IMUL
    * 16 -> int_size a@360
     BIPUSH 0x10               GETSTATIC 0x00 0x53
     IMUL                      IMUL
    * 16 -> int_size a@418
     BIPUSH 0x10               GETSTATIC 0x00 0x53
     IMUL                      IMUL
 applying TexturePackList patch to ih.class for mod HD Textures
    TexturePackList.setTileSize(selectedTexturePack) on texture pack change a@54
     ALOAD_0                   ALOAD_0
     GETFIELD 0x00 0x16        GETFIELD 0x00 0x16
     INVOKEVIRTUAL 0x00 0x1f   INVOKEVIRTUAL 0x00 0x1f
     ICONST_1                  INVOKESTATIC 0x00 0xc7
                               POP
                               ALOAD_0
                               GETFIELD 0x00 0x1a
                               DUP
                               GETFIELD 0x00 0xcb
                               SWAP
                               INVOKEVIRTUAL 0x00 0xcf
                               INVOKESTATIC 0x00 0xd2
                               ICONST_1
 applying ColorizerFoliage patch to je.class for mod HD Textures
    make field colorBuffer public
 applying RenderEngine patch to jf.class for mod HD Textures
    (i % 16) * 16 + j * 16 -> (i % 16) * int_size + j * int_size a@116
     BIPUSH 0x10               BIPUSH 0x10
     IREM                      IREM
     BIPUSH 0x10               GETSTATIC 0x01 0x71
     IMUL                      IMUL
     ILOAD_3                   ILOAD_3
     BIPUSH 0x10               GETSTATIC 0x01 0x71
     IMUL                      IMUL
    (i / 16) * 16 + j * 16 -> (i / 16) * int_size + j * int_size a@133
     BIPUSH 0x10               BIPUSH 0x10
     IDIV                      IDIV
     BIPUSH 0x10               GETSTATIC 0x01 0x71
     IMUL                      IMUL
     ILOAD 0x04                ILOAD 0x04
     BIPUSH 0x10               GETSTATIC 0x01 0x71
     IMUL                      IMUL
    glTexSubImage2D(...,16,16) -> glTexSubImage2D(...,int_size,int_size) a@147
     BIPUSH 0x10               GETSTATIC 0x01 0x71
     BIPUSH 0x10               GETSTATIC 0x01 0x71
     SIPUSH 0x19 0x08          SIPUSH 0x19 0x08
     SIPUSH 0x14 0x01          SIPUSH 0x14 0x01
    glTexSubImage2D(...,16,16) -> glTexSubImage2D(...,int_size,int_size) a@534
     BIPUSH 0x10               GETSTATIC 0x01 0x71
     BIPUSH 0x10               GETSTATIC 0x01 0x71
     SIPUSH 0x19 0x08          SIPUSH 0x19 0x08
     SIPUSH 0x14 0x01          SIPUSH 0x14 0x01
    readTextureImage(getInputStream(...)) -> getResourceAsBufferedImage(...) a@46
     INVOKEVIRTUAL 0x00 0x44   SWAP
     INVOKESPECIAL 0x00 0x6c   POP
                               SWAP
                               POP
                               INVOKESTATIC 0x01 0x77
    readTextureImage(getInputStream(...)) -> getResourceAsBufferedImage(...) a@86
     INVOKEVIRTUAL 0x00 0x44   SWAP
     INVOKESPECIAL 0x00 0x6c   POP
                               SWAP
                               POP
                               INVOKESTATIC 0x01 0x77
    readTextureImage(getInputStream(...)) -> getResourceAsBufferedImage(...) a@128
     INVOKEVIRTUAL 0x00 0x44   SWAP
     INVOKESPECIAL 0x00 0x6c   POP
                               SWAP
                               POP
                               INVOKESTATIC 0x01 0x77
    readTextureImage(getInputStream(...)) -> getResourceAsBufferedImage(...) b@71
     INVOKEVIRTUAL 0x00 0x44   SWAP
     INVOKESPECIAL 0x00 0x6c   POP
                               SWAP
                               POP
                               INVOKESTATIC 0x01 0x77
    readTextureImage(getInputStream(...)) -> getResourceAsBufferedImage(...) b@111
     INVOKEVIRTUAL 0x00 0x44   SWAP
     INVOKESPECIAL 0x00 0x6c   POP
                               SWAP
                               POP
                               INVOKESTATIC 0x01 0x77
    readTextureImage(getInputStream(...)) -> getResourceAsBufferedImage(...) b@153
     INVOKEVIRTUAL 0x00 0x44   SWAP
     INVOKESPECIAL 0x00 0x6c   POP
                               SWAP
                               POP
                               INVOKESTATIC 0x01 0x77
    readTextureImage(getInputStream(...)) -> getResourceAsBufferedImage(...) b@160
     INVOKEVIRTUAL 0x00 0x44   SWAP
     INVOKESPECIAL 0x00 0x6c   POP
                               SWAP
                               POP
                               INVOKESTATIC 0x01 0x77
    readTextureImage(getInputStream(...)) -> getResourceAsBufferedImage(...) b@197
     INVOKEVIRTUAL 0x00 0x44   SWAP
     INVOKESPECIAL 0x00 0x6c   POP
                               SWAP
                               POP
                               INVOKESTATIC 0x01 0x77
    readTextureImage(getInputStream(...)) -> getResourceAsBufferedImage(...) b@231
     INVOKEVIRTUAL 0x00 0x44   SWAP
     INVOKESPECIAL 0x00 0x6c   POP
                               SWAP
                               POP
                               INVOKESTATIC 0x01 0x77
    readTextureImage(getInputStream(...)) -> getResourceAsBufferedImage(...) b@246
     INVOKEVIRTUAL 0x00 0x44   SWAP
     INVOKESPECIAL 0x00 0x6c   POP
                               SWAP
                               POP
                               INVOKESTATIC 0x01 0x77
    readTextureImage(getInputStream(...)) -> getResourceAsBufferedImage(...) b@351
     INVOKEVIRTUAL 0x00 0x44   SWAP
     INVOKESPECIAL 0x00 0x6c   POP
                               SWAP
                               POP
                               INVOKESTATIC 0x01 0x77
    readTextureImage(getInputStream(...)) -> getResourceAsBufferedImage(...) b@388
     INVOKEVIRTUAL 0x00 0x44   SWAP
     INVOKESPECIAL 0x00 0x6c   POP
                               SWAP
                               POP
                               INVOKESTATIC 0x01 0x77
    readTextureImage(getInputStream(...)) -> getResourceAsBufferedImage(...) b@422
     INVOKEVIRTUAL 0x00 0x44   SWAP
     INVOKESPECIAL 0x00 0x6c   POP
                               SWAP
                               POP
                               INVOKESTATIC 0x01 0x77
    readTextureImage(getInputStream(...)) -> getResourceAsBufferedImage(...) b@437
     INVOKEVIRTUAL 0x00 0x44   SWAP
     INVOKESPECIAL 0x00 0x6c   POP
                               SWAP
                               POP
                               INVOKESTATIC 0x01 0x77
    getInputStream(...), readTextureImage -> getResourceAsBufferedImage(...) b@172
     ALOAD_2                   NOP
     ALOAD_1                   NOP
     INVOKEVIRTUAL 0x00 0x44   NOP
     ASTORE 0x04               NOP
     ALOAD 0x04                NOP
     IFNONNULL 0x00 0x0f       NOP
     ALOAD_0                   NOP
     ALOAD_0                   NOP
     GETFIELD 0x00 0x3c        NOP
     ILOAD_3                   NOP
     INVOKEVIRTUAL 0x00 0x6a   NOP
     GOTO 0x00 0x0e            NOP
     ALOAD_0                   NOP
     ALOAD_0                   NOP
     ALOAD 0x04                NOP
     INVOKESPECIAL 0x00 0x6c   NOP
                               NOP
                               NOP
                               NOP
                               NOP
                               NOP
                               NOP
                               NOP
                               NOP
                               NOP
                               NOP
                               ALOAD_0
                               ALOAD_1
                               INVOKESTATIC 0x01 0x77
    imageData.clear(), .put(), .limit() -> imageData = TextureUtils.getByteBuffer() a@397
     ALOAD_0                   NOP
     GETFIELD 0x00 0x35        NOP
     INVOKEVIRTUAL 0x00 0x57   NOP
     POP                       NOP
     ALOAD_0                   NOP
     GETFIELD 0x00 0x35        NOP
     ALOAD 0x06                NOP
     INVOKEVIRTUAL 0x00 0x5a   NOP
     POP                       NOP
     ALOAD_0                   NOP
     GETFIELD 0x00 0x35        NOP
     ICONST_0                  NOP
     INVOKEVIRTUAL 0x00 0x59   NOP
     ALOAD 0x06                NOP
     ARRAYLENGTH               NOP
     INVOKEVIRTUAL 0x00 0x56   NOP
     POP                       NOP
                               NOP
                               NOP
                               NOP
                               ALOAD_0
                               ALOAD_0
                               GETFIELD 0x00 0x35
                               ALOAD 0x06
                               INVOKESTATIC 0x01 0x7b
                               PUTFIELD 0x00 0x35
    imageData.clear(), .put(), .limit() -> imageData = TextureUtils.getByteBuffer() a@359
     ALOAD_0                   NOP
     GETFIELD 0x00 0x35        NOP
     INVOKEVIRTUAL 0x00 0x57   NOP
     POP                       NOP
     ALOAD_0                   NOP
     GETFIELD 0x00 0x35        NOP
     ALOAD 0x05                NOP
     INVOKEVIRTUAL 0x00 0x5a   NOP
     POP                       NOP
     ALOAD_0                   NOP
     GETFIELD 0x00 0x35        NOP
     ICONST_0                  NOP
     INVOKEVIRTUAL 0x00 0x59   NOP
     ALOAD 0x05                NOP
     ARRAYLENGTH               NOP
     INVOKEVIRTUAL 0x00 0x56   NOP
     POP                       NOP
                               NOP
                               NOP
                               NOP
                               ALOAD_0
                               ALOAD_0
                               GETFIELD 0x00 0x35
                               ALOAD 0x05
                               INVOKESTATIC 0x01 0x7b
                               PUTFIELD 0x00 0x35
    imageData.clear(), .put(), .limit() -> imageData = TextureUtils.getByteBuffer() a@44
     ALOAD_0                   NOP
     GETFIELD 0x00 0x35        NOP
     INVOKEVIRTUAL 0x00 0x57   NOP
     POP                       NOP
     ALOAD_0                   NOP
     GETFIELD 0x00 0x35        NOP
     ALOAD_2                   NOP
     GETFIELD 0x00 0x24        NOP
     INVOKEVIRTUAL 0x00 0x5a   NOP
     POP                       NOP
     ALOAD_0                   NOP
     GETFIELD 0x00 0x35        NOP
     ICONST_0                  NOP
     INVOKEVIRTUAL 0x00 0x59   NOP
     ALOAD_2                   NOP
     GETFIELD 0x00 0x24        NOP
     ARRAYLENGTH               NOP
     INVOKEVIRTUAL 0x00 0x56   NOP
     POP                       NOP
                               NOP
                               NOP
                               NOP
                               ALOAD_0
                               ALOAD_0
                               GETFIELD 0x00 0x35
                               ALOAD_2
                               GETFIELD 0x00 0x24
                               INVOKESTATIC 0x01 0x7b
                               PUTFIELD 0x00 0x35
    imageData.clear(), .put(), .limit() -> imageData = TextureUtils.getByteBuffer() a@481
     ALOAD_0                   NOP
     GETFIELD 0x00 0x35        NOP
     INVOKEVIRTUAL 0x00 0x57   NOP
     POP                       NOP
     ALOAD_0                   NOP
     GETFIELD 0x00 0x35        NOP
     ALOAD_2                   NOP
     GETFIELD 0x00 0x24        NOP
     INVOKEVIRTUAL 0x00 0x5a   NOP
     POP                       NOP
     ALOAD_0                   NOP
     GETFIELD 0x00 0x35        NOP
     ICONST_0                  NOP
     INVOKEVIRTUAL 0x00 0x59   NOP
     ALOAD_2                   NOP
     GETFIELD 0x00 0x24        NOP
     ARRAYLENGTH               NOP
     INVOKEVIRTUAL 0x00 0x56   NOP
     POP                       NOP
                               NOP
                               NOP
                               NOP
                               ALOAD_0
                               ALOAD_0
                               GETFIELD 0x00 0x35
                               ALOAD_2
                               GETFIELD 0x00 0x24
                               INVOKESTATIC 0x01 0x7b
                               PUTFIELD 0x00 0x35
    call TextureUtils.registerTextureFX a@0
     ALOAD_0                   NOP
     GETFIELD 0x00 0x36        NOP
     ALOAD_1                   NOP
     INVOKEINTERFACE 0x00 0x79 0x02 0x00  NOP
     POP                       NOP
     ALOAD_1                   NOP
     INVOKEVIRTUAL 0x00 0x3e   NOP
                               ALOAD_0
                               GETFIELD 0x00 0x36
                               ALOAD_1
                               INVOKESTATIC 0x01 0x7f
    1048576 -> int_glBufferSize <init>@46
     LDC 0x02                  GETSTATIC 0x01 0x82
    insert method setTileSize (Lnet/minecraft/client/Minecraft;)V stack size 10, local vars 5
 applying Watch patch to kq.class for mod HD Textures
    16.0D -> double_size a@332
     LDC2_W 0x00 0x23          GETSTATIC 0x00 0x8f
    16.0D -> double_size a@354
     LDC2_W 0x00 0x23          GETSTATIC 0x00 0x8f
    15.0D -> double_sizeMinus1 a@286
     LDC2_W 0x00 0x21          GETSTATIC 0x00 0x92
    15.0D -> double_sizeMinus1 a@303
     LDC2_W 0x00 0x21          GETSTATIC 0x00 0x92
    getRGB(...16,16,...16) -> getRGB(...int_size,int_size,...int_size) <init>@77
     BIPUSH 0x10               GETSTATIC 0x00 0x95
     BIPUSH 0x10               GETSTATIC 0x00 0x95
     ALOAD_0                   ALOAD_0
     GETFIELD 0x00 0x2c        GETFIELD 0x00 0x2c
     ICONST_0                  ICONST_0
     BIPUSH 0x10               GETSTATIC 0x00 0x95
    getRGB(...16,16,...16) -> getRGB(...int_size,int_size,...int_size) <init>@109
     BIPUSH 0x10               GETSTATIC 0x00 0x95
     BIPUSH 0x10               GETSTATIC 0x00 0x95
     ALOAD_0                   ALOAD_0
     GETFIELD 0x00 0x2d        GETFIELD 0x00 0x2d
     ICONST_0                  ICONST_0
     BIPUSH 0x10               GETSTATIC 0x00 0x95
    array size 256 -> int_numPixels <init>@12
     SIPUSH 0x01 0x00          GETSTATIC 0x00 0x98
     NEWARRAY 0x0a             NEWARRAY 0x0a
    array size 256 -> int_numPixels <init>@21
     SIPUSH 0x01 0x00          GETSTATIC 0x00 0x98
     NEWARRAY 0x0a             NEWARRAY 0x0a
    * 16 -> int_size <init>@57
     BIPUSH 0x10               GETSTATIC 0x00 0x95
     IMUL                      IMUL
    * 16 -> int_size <init>@69
     BIPUSH 0x10               GETSTATIC 0x00 0x95
     IMUL                      IMUL
    * 16 -> int_size a@371
     BIPUSH 0x10               GETSTATIC 0x00 0x95
     IMUL                      IMUL
    while i < 256 -> int_numPixels a@194
     SIPUSH 0x01 0x00          GETSTATIC 0x00 0x98
     IF_ICMPGE 0x01 0x90       IF_ICMPGE 0x01 0x90
    & 15 -> int_sizeMinus1 a@363
     BIPUSH 0x0f               GETSTATIC 0x00 0x9b
     IAND                      IAND
    & 15 -> int_sizeMinus1 a@369
     BIPUSH 0x0f               GETSTATIC 0x00 0x9b
     IAND                      IAND
    % 16 -> int_size a@282
     BIPUSH 0x10               GETSTATIC 0x00 0x95
     IREM                      IREM
    / 16 -> int_size a@300
     BIPUSH 0x10               GETSTATIC 0x00 0x95
     IDIV                      IDIV
     I2D                       I2D
 applying GetResource patch to kq.class for mod HD Textures
    ImageIO.read(getResource(...)) -> getResourceAsBufferedImage(...) <init>@39
     LDC 0x0d                  NOP
     LDC 0x02                  NOP
     INVOKEVIRTUAL 0x00 0x38   NOP
     INVOKESTATIC 0x00 0x3c    NOP
                               NOP
                               LDC 0x02
                               INVOKESTATIC 0x00 0xa8
    ImageIO.read(getResource(...)) -> getResourceAsBufferedImage(...) <init>@97
     LDC 0x0d                  NOP
     LDC 0x03                  NOP
     INVOKEVIRTUAL 0x00 0x38   NOP
     INVOKESTATIC 0x00 0x3c    NOP
                               NOP
                               LDC 0x03
                               INVOKESTATIC 0x00 0xa8
 applying FlowWater patch to od.class for mod HD Textures
    array size 256 -> int_numPixels <init>@13
     SIPUSH 0x01 0x00          GETSTATIC 0x00 0x47
     NEWARRAY 0x06             NEWARRAY 0x06
    array size 256 -> int_numPixels <init>@22
     SIPUSH 0x01 0x00          GETSTATIC 0x00 0x47
     NEWARRAY 0x06             NEWARRAY 0x06
    array size 256 -> int_numPixels <init>@31
     SIPUSH 0x01 0x00          GETSTATIC 0x00 0x47
     NEWARRAY 0x06             NEWARRAY 0x06
    array size 256 -> int_numPixels <init>@40
     SIPUSH 0x01 0x00          GETSTATIC 0x00 0x47
     NEWARRAY 0x06             NEWARRAY 0x06
    while i < 256 -> int_numPixels a@260
     SIPUSH 0x01 0x00          GETSTATIC 0x00 0x47
     IF_ICMPGE 0x00 0xd4       IF_ICMPGE 0x00 0xd4
    while i < 16 -> int_size a@13
     BIPUSH 0x10               GETSTATIC 0x00 0x4a
     IF_ICMPGE 0x00 0x65       IF_ICMPGE 0x00 0x65
    while i < 16 -> int_size a@22
     BIPUSH 0x10               GETSTATIC 0x00 0x4a
     IF_ICMPGE 0x00 0x57       IF_ICMPGE 0x00 0x57
    while i < 16 -> int_size a@121
     BIPUSH 0x10               GETSTATIC 0x00 0x4a
     IF_ICMPGE 0x00 0x76       IF_ICMPGE 0x00 0x76
    while i < 16 -> int_size a@130
     BIPUSH 0x10               GETSTATIC 0x00 0x4a
     IF_ICMPGE 0x00 0x68       IF_ICMPGE 0x00 0x68
    & 255 -> int_numPixelsMinus1 a@283
     SIPUSH 0x00 0xff          GETSTATIC 0x00 0x4d
     IAND                      IAND
    & 15 -> int_sizeMinus1 a@42
     BIPUSH 0x0f               GETSTATIC 0x00 0x50
     IAND                      IAND
    & 15 -> int_sizeMinus1 a@50
     BIPUSH 0x0f               GETSTATIC 0x00 0x50
     IAND                      IAND
    * 16 -> int_size a@65
     BIPUSH 0x10               GETSTATIC 0x00 0x4a
     IMUL                      IMUL
    * 16 -> int_size a@85
     BIPUSH 0x10               GETSTATIC 0x00 0x4a
     IMUL                      IMUL
    * 16 -> int_size a@100
     BIPUSH 0x10               GETSTATIC 0x00 0x4a
     IMUL                      IMUL
    * 16 -> int_size a@147
     BIPUSH 0x10               GETSTATIC 0x00 0x4a
     IMUL                      IMUL
    * 16 -> int_size a@160
     BIPUSH 0x10               GETSTATIC 0x00 0x4a
     IMUL                      IMUL
    * 16 -> int_size a@177
     BIPUSH 0x10               GETSTATIC 0x00 0x4a
     IMUL                      IMUL
    * 16 -> int_size a@194
     BIPUSH 0x10               GETSTATIC 0x00 0x4a
     IMUL                      IMUL
    * 16 -> int_size a@207
     BIPUSH 0x10               GETSTATIC 0x00 0x4a
     IMUL                      IMUL
    * 16 -> int_size a@234
     BIPUSH 0x10               GETSTATIC 0x00 0x4a
     IMUL                      IMUL
    * 16 -> int_size a@290
     BIPUSH 0x10               GETSTATIC 0x00 0x4a
     IMUL                      IMUL
 applying GetResource patch to ow.class for mod HD Textures
    ImageIO.read(getResource(...)) -> getResourceAsBufferedImage(...) <init>@22
     LDC 0x0c                  NOP
     LDC 0x02                  NOP
     INVOKEVIRTUAL 0x00 0x14   NOP
     INVOKESTATIC 0x00 0x15    NOP
                               NOP
                               LDC 0x02
                               INVOKESTATIC 0x00 0x5b
 applying ItemRenderer patch to qv.class for mod HD Textures
    16.0F -> float_size a@446
     LDC 0x29                  GETSTATIC 0x01 0x7f
    16.0F -> float_size a@577
     LDC 0x29                  GETSTATIC 0x01 0x7f
    16.0F -> float_size a@711
     LDC 0x29                  GETSTATIC 0x01 0x7f
    16.0F -> float_size a@850
     LDC 0x29                  GETSTATIC 0x01 0x7f
    while i < 16 -> int_size a@438
     BIPUSH 0x10               GETSTATIC 0x01 0x82
     IF_ICMPGE 0x00 0x6d       IF_ICMPGE 0x00 0x6d
    while i < 16 -> int_size a@570
     BIPUSH 0x10               GETSTATIC 0x01 0x82
     IF_ICMPGE 0x00 0x70       IF_ICMPGE 0x00 0x70
    while i < 16 -> int_size a@705
     BIPUSH 0x10               GETSTATIC 0x01 0x82
     IF_ICMPGE 0x00 0x74       IF_ICMPGE 0x00 0x74
    while i < 16 -> int_size a@845
     BIPUSH 0x10               GETSTATIC 0x01 0x82
     IF_ICMPGE 0x00 0x71       IF_ICMPGE 0x00 0x71
    0.001953125F -> float_texNudge a@464
     LDC 0x0f                  GETSTATIC 0x01 0x85
    0.001953125F -> float_texNudge a@597
     LDC 0x0f                  GETSTATIC 0x01 0x85
    0.001953125F -> float_texNudge a@733
     LDC 0x0f                  GETSTATIC 0x01 0x85
    0.001953125F -> float_texNudge a@874
     LDC 0x0f                  GETSTATIC 0x01 0x85
 applying Fire patch to ry.class for mod HD Textures
    1.06F -> float_flameNudge a@143
     LDC 0x02                  GETSTATIC 0x00 0x3f
    array size 320 -> int_flameArraySize <init>@16
     SIPUSH 0x01 0x40          GETSTATIC 0x00 0x42
     NEWARRAY 0x06             NEWARRAY 0x06
    array size 320 -> int_flameArraySize <init>@25
     SIPUSH 0x01 0x40          GETSTATIC 0x00 0x42
     NEWARRAY 0x06             NEWARRAY 0x06
    while i < 256 -> int_numPixels a@227
     SIPUSH 0x01 0x00          GETSTATIC 0x00 0x45
     IF_ICMPGE 0x00 0xf5       IF_ICMPGE 0x00 0xf5
    while i < 20 -> int_flameHeight a@11
     BIPUSH 0x14               GETSTATIC 0x00 0x48
     IF_ICMPGE 0x00 0xbb       IF_ICMPGE 0x00 0xbb
    while i < 20 -> int_flameHeight a@92
     BIPUSH 0x14               GETSTATIC 0x00 0x48
     IF_ICMPGE 0x00 0x15       IF_ICMPGE 0x00 0x15
    while i < 16 -> int_size a@3
     BIPUSH 0x10               GETSTATIC 0x00 0x4b
     IF_ICMPGE 0x00 0xcb       IF_ICMPGE 0x00 0xcb
    while i < 16 -> int_size a@86
     BIPUSH 0x10               GETSTATIC 0x00 0x4b
     IF_ICMPGE 0x00 0x1d       IF_ICMPGE 0x00 0x1d
    * 16 -> int_size a@32
     BIPUSH 0x10               GETSTATIC 0x00 0x4b
     IMUL                      IMUL
    * 16 -> int_size a@111
     BIPUSH 0x10               GETSTATIC 0x00 0x4b
     IMUL                      IMUL
    * 16 -> int_size a@141
     BIPUSH 0x10               GETSTATIC 0x00 0x4b
     IMUL                      IMUL
    * 16 -> int_size a@168
     BIPUSH 0x10               GETSTATIC 0x00 0x4b
     IMUL                      IMUL
    % 20 -> int_flameHeight a@29
     BIPUSH 0x14               GETSTATIC 0x00 0x48
     IREM                      IREM
    if i < 19 -> int_flameHeightMinus1 a@158
     BIPUSH 0x13               GETSTATIC 0x00 0x4e
     IF_ICMPLT 0x00 0x2b       IF_ICMPLT 0x00 0x2b
 applying FontRenderer patch to se.class for mod HD Textures
    insert method initialize ()V stack size 11, local vars 18
 applying GetResource patch to se.class for mod HD Textures
    ImageIO.read(getResource(...)) -> getResourceAsBufferedImage(...) <init>@28
     LDC 0x14                  NOP
     ALOAD_2                   NOP
     INVOKEVIRTUAL 0x00 0x25   NOP
     INVOKESTATIC 0x00 0x37    NOP
                               NOP
                               ALOAD_2
                               INVOKESTATIC 0x00 0xdf
    ImageIO.read(getResource(...)) -> getResourceAsBufferedImage(...) initialize@28
     LDC 0x14                  NOP
     ALOAD_2                   NOP
     INVOKEVIRTUAL 0x00 0x25   NOP
     INVOKESTATIC 0x00 0x37    NOP
                               NOP
                               ALOAD_2
                               INVOKESTATIC 0x00 0xdf
 applying FontRenderer patch to se.class for mod HD Font
    font width 7 -> i / 16 - 1 <init>@119
     BIPUSH 0x07               ILOAD 0x05
     ISTORE 0x0b               BIPUSH 0x10
                               IDIV
                               ICONST_1
                               ISUB
                               ISTORE 0x0b
    font width 7 -> i / 16 - 1 initialize@119
     BIPUSH 0x07               ILOAD 0x05
     ISTORE 0x0b               BIPUSH 0x10
                               IDIV
                               ICONST_1
                               ISUB
                               ISTORE 0x0b
    font width 8 -> i / 16 <init>@135
     BIPUSH 0x08               ILOAD 0x05
                               BIPUSH 0x10
                               IDIV
    font width 8 -> i / 16 <init>@154
     BIPUSH 0x08               ILOAD 0x05
                               BIPUSH 0x10
                               IDIV
    font width 8 -> i / 16 <init>@169
     BIPUSH 0x08               ILOAD 0x05
                               BIPUSH 0x10
                               IDIV
    font width 8 -> i / 16 a@262
     BIPUSH 0x08               ILOAD 0x05
                               BIPUSH 0x10
                               IDIV
    font width 8 -> i / 16 initialize@135
     BIPUSH 0x08               ILOAD 0x05
                               BIPUSH 0x10
                               IDIV
    font width 8 -> i / 16 initialize@154
     BIPUSH 0x08               ILOAD 0x05
                               BIPUSH 0x10
                               IDIV
    font width 8 -> i / 16 initialize@169
     BIPUSH 0x08               ILOAD 0x05
                               BIPUSH 0x10
                               IDIV
    font whitespace width 2 -> i / 64 <init>@232
     ICONST_2                  ILOAD 0x05
     ISTORE 0x0b               BIPUSH 0x40
                               IDIV
                               ISTORE 0x0b
    font whitespace width 2 -> i / 64 initialize@232
     ICONST_2                  ILOAD 0x05
     ISTORE 0x0b               BIPUSH 0x40
                               IDIV
                               ISTORE 0x0b
    font charWidth computation: j + 2 -> (128 * j + 256) / i <init>@245
     ILOAD 0x0b                SIPUSH 0x00 0x80
     ICONST_2                  ILOAD 0x0b
     IADD                      IMUL
     IASTORE                   SIPUSH 0x01 0x00
                               IADD
                               ILOAD 0x05
                               IDIV
                               IASTORE
    font charWidth computation: j + 2 -> (128 * j + 256) / i initialize@245
     ILOAD 0x0b                SIPUSH 0x00 0x80
     ICONST_2                  ILOAD 0x0b
     IADD                      IMUL
     IASTORE                   SIPUSH 0x01 0x00
                               IADD
                               ILOAD 0x05
                               IDIV
                               IASTORE
 applying GetResource patch to uh.class for mod HD Textures
    ImageIO.read(getResource(...)) -> getResourceAsBufferedImage(...) <init>@66
     LDC 0x16                  NOP
     LDC 0x0b                  NOP
     INVOKEVIRTUAL 0x00 0x30   NOP
     INVOKESTATIC 0x00 0x33    NOP
                               NOP
                               LDC 0x0b
                               INVOKESTATIC 0x00 0x99
 applying GetResource patch to vh.class for mod HD Textures
 applying StillWater patch to vk.class for mod HD Textures
    array size 256 -> int_numPixels <init>@11
     SIPUSH 0x01 0x00          GETSTATIC 0x00 0x44
     NEWARRAY 0x06             NEWARRAY 0x06
    array size 256 -> int_numPixels <init>@20
     SIPUSH 0x01 0x00          GETSTATIC 0x00 0x44
     NEWARRAY 0x06             NEWARRAY 0x06
    array size 256 -> int_numPixels <init>@29
     SIPUSH 0x01 0x00          GETSTATIC 0x00 0x44
     NEWARRAY 0x06             NEWARRAY 0x06
    array size 256 -> int_numPixels <init>@38
     SIPUSH 0x01 0x00          GETSTATIC 0x00 0x44
     NEWARRAY 0x06             NEWARRAY 0x06
    while i < 256 -> int_numPixels a@262
     SIPUSH 0x01 0x00          GETSTATIC 0x00 0x44
     IF_ICMPGE 0x00 0xc8       IF_ICMPGE 0x00 0xc8
    while i < 16 -> int_size a@13
     BIPUSH 0x10               GETSTATIC 0x00 0x47
     IF_ICMPGE 0x00 0x67       IF_ICMPGE 0x00 0x67
    while i < 16 -> int_size a@22
     BIPUSH 0x10               GETSTATIC 0x00 0x47
     IF_ICMPGE 0x00 0x59       IF_ICMPGE 0x00 0x59
    while i < 16 -> int_size a@123
     BIPUSH 0x10               GETSTATIC 0x00 0x47
     IF_ICMPGE 0x00 0x76       IF_ICMPGE 0x00 0x76
    while i < 16 -> int_size a@132
     BIPUSH 0x10               GETSTATIC 0x00 0x47
     IF_ICMPGE 0x00 0x68       IF_ICMPGE 0x00 0x68
    & 15 -> int_sizeMinus1 a@45
     BIPUSH 0x0f               GETSTATIC 0x00 0x4a
     IAND                      IAND
    & 15 -> int_sizeMinus1 a@52
     BIPUSH 0x0f               GETSTATIC 0x00 0x4a
     IAND                      IAND
    * 16 -> int_size a@67
     BIPUSH 0x10               GETSTATIC 0x00 0x47
     IMUL                      IMUL
    * 16 -> int_size a@87
     BIPUSH 0x10               GETSTATIC 0x00 0x47
     IMUL                      IMUL
    * 16 -> int_size a@102
     BIPUSH 0x10               GETSTATIC 0x00 0x47
     IMUL                      IMUL
    * 16 -> int_size a@149
     BIPUSH 0x10               GETSTATIC 0x00 0x47
     IMUL                      IMUL
    * 16 -> int_size a@162
     BIPUSH 0x10               GETSTATIC 0x00 0x47
     IMUL                      IMUL
    * 16 -> int_size a@179
     BIPUSH 0x10               GETSTATIC 0x00 0x47
     IMUL                      IMUL
    * 16 -> int_size a@196
     BIPUSH 0x10               GETSTATIC 0x00 0x47
     IMUL                      IMUL
    * 16 -> int_size a@209
     BIPUSH 0x10               GETSTATIC 0x00 0x47
     IMUL                      IMUL
    * 16 -> int_size a@236
     BIPUSH 0x10               GETSTATIC 0x00 0x47
     IMUL                      IMUL
 applying BlockGrass patch to wg.class for mod Better Grass
    insert field grassMatrix [[I
    initialize grassMatrix <init>@19
     label A -> instruction 67
     branch offset IF_ACMPNE A -> +44 @23
                               GETSTATIC 0x00 0x67
                               ACONST_NULL
                               IF_ACMPNE 0x00 0x2c
                               ICONST_4
                               ICONST_2
                               MULTIANEWARRAY 0x00 0x68 0x02
                               PUTSTATIC 0x00 0x67
                               GETSTATIC 0x00 0x67
                               ICONST_0
                               AALOAD
                               ICONST_1
                               ICONST_M1
                               IASTORE
                               GETSTATIC 0x00 0x67
                               ICONST_1
                               AALOAD
                               ICONST_1
                               ICONST_1
                               IASTORE
                               GETSTATIC 0x00 0x67
                               ICONST_2
                               AALOAD
                               ICONST_0
                               ICONST_M1
                               IASTORE
                               GETSTATIC 0x00 0x67
                               ICONST_3
                               AALOAD
                               ICONST_0
                               ICONST_1
                               IASTORE
    check surrounding blocks in getBlockTexture a@29
     label A -> instruction 89
     label B -> instruction 87
     label C -> instruction 141
     branch offset IF_ACMPEQ A -> +52 @37
     branch offset IF_ACMPEQ A -> +44 @45
     branch offset IF_ICMPEQ B -> +5 @82
     branch offset IF_ACMPEQ C -> +14 @127
     branch offset IF_ACMPEQ C -> +6 @135
     ALOAD 0x06                IINC 0x05 0xfe
     GETSTATIC 0x00 0x0b       ALOAD 0x06
     IF_ACMPEQ 0x00 0x0b       GETSTATIC 0x00 0x0b
     ALOAD 0x06                IF_ACMPEQ 0x00 0x34
     GETSTATIC 0x00 0x0c       ALOAD 0x06
     IF_ACMPNE 0x00 0x06       GETSTATIC 0x00 0x0c
     BIPUSH 0x44               IF_ACMPEQ 0x00 0x2c
     IRETURN                   ALOAD 0x01
     ICONST_3                  ILOAD 0x02
                               GETSTATIC 0x00 0x67
                               ILOAD 0x05
                               AALOAD
                               ICONST_0
                               IALOAD
                               IADD
                               ILOAD 0x03
                               ICONST_1
                               ISUB
                               ILOAD 0x04
                               GETSTATIC 0x00 0x67
                               ILOAD 0x05
                               AALOAD
                               ICONST_1
                               IALOAD
                               IADD
                               INVOKEINTERFACE 0x00 0x6a 0x04 0x00
                               ICONST_2
                               IF_ICMPEQ 0x00 0x05
                               ICONST_3
                               IRETURN
                               ICONST_0
                               IRETURN
                               ALOAD 0x01
                               ILOAD 0x02
                               GETSTATIC 0x00 0x67
                               ILOAD 0x05
                               AALOAD
                               ICONST_0
                               IALOAD
                               IADD
                               ILOAD 0x03
                               ILOAD 0x04
                               GETSTATIC 0x00 0x67
                               ILOAD 0x05
                               AALOAD
                               ICONST_1
                               IALOAD
                               IADD
                               INVOKEINTERFACE 0x00 0x1f 0x04 0x00
                               ASTORE 0x06
                               ALOAD 0x06
                               GETSTATIC 0x00 0x0b
                               IF_ACMPEQ 0x00 0x0e
                               ALOAD 0x06
                               GETSTATIC 0x00 0x0c
                               IF_ACMPEQ 0x00 0x06
                               BIPUSH 0x44
                               IRETURN
                               BIPUSH 0x42
   increasing stack size from 4 to 6
 applying Minecraft patch to net/minecraft/client/Minecraft.class for mod HD Textures
    TextureUtils.setMinecraft(this) on startup a@206
     ALOAD_0                   ALOAD_0
     NEW 0x00 0x6f             NEW 0x00 0x6f
     DUP                       DUP
     ALOAD_0                   ALOAD_0
     ALOAD_0                   ALOAD_0
     GETFIELD 0x01 0x25        GETFIELD 0x01 0x25
     INVOKESPECIAL 0x01 0xb1   INVOKESPECIAL 0x01 0xb1
     PUTFIELD 0x01 0x0f        PUTFIELD 0x01 0x0f
                               ALOAD_0
                               INVOKESTATIC 0x06 0x18
    TextureUtils.setTileSize(), renderEngine.setTileSize() on startup a@226
     ALOAD_0                   ALOAD_0
     NEW 0x00 0x8a             NEW 0x00 0x8a
     DUP                       DUP
     ALOAD_0                   ALOAD_0
     GETFIELD 0x01 0x0f        GETFIELD 0x01 0x0f
     ALOAD_0                   ALOAD_0
     GETFIELD 0x01 0x47        GETFIELD 0x01 0x47
     INVOKESPECIAL 0x01 0xef   INVOKESPECIAL 0x01 0xef
     PUTFIELD 0x01 0x3d        PUTFIELD 0x01 0x3d
                               INVOKESTATIC 0x06 0x1b
                               POP
                               ALOAD_0
                               GETFIELD 0x01 0x3d
                               ALOAD_0
                               INVOKEVIRTUAL 0x06 0x1d
    remove registerTextureFX call a@507
     ALOAD_0                   NOP
     GETFIELD 0x01 0x3d        NOP
     ALOAD_0                   NOP
     GETFIELD 0x01 0x2b        NOP
     INVOKEVIRTUAL 0x01 0xf1   NOP
                               NOP
                               NOP
                               NOP
                               NOP
                               NOP
                               NOP
    remove registerTextureFX call a@518
     ALOAD_0                   NOP
     GETFIELD 0x01 0x3d        NOP
     ALOAD_0                   NOP
     GETFIELD 0x01 0x2a        NOP
     INVOKEVIRTUAL 0x01 0xf1   NOP
                               NOP
                               NOP
                               NOP
                               NOP
                               NOP
                               NOP
    remove registerTextureFX call a@529
     ALOAD_0                   NOP
     GETFIELD 0x01 0x3d        NOP
     NEW 0x00 0x6a             NOP
     DUP                       NOP
     INVOKESPECIAL 0x01 0xad   NOP
     INVOKEVIRTUAL 0x01 0xf1   NOP
                               NOP
                               NOP
                               NOP
                               NOP
                               NOP
                               NOP
                               NOP
                               NOP
    remove registerTextureFX call a@543
     ALOAD_0                   NOP
     GETFIELD 0x01 0x3d        NOP
     NEW 0x00 0x50             NOP
     DUP                       NOP
     ALOAD_0                   NOP
     INVOKESPECIAL 0x01 0x67   NOP
     INVOKEVIRTUAL 0x01 0xf1   NOP
                               NOP
                               NOP
                               NOP
                               NOP
                               NOP
                               NOP
                               NOP
                               NOP
    remove registerTextureFX call a@558
     ALOAD_0                   NOP
     GETFIELD 0x01 0x3d        NOP
     NEW 0x00 0x92             NOP
     DUP                       NOP
     ALOAD_0                   NOP
     INVOKESPECIAL 0x01 0xfb   NOP
     INVOKEVIRTUAL 0x01 0xf1   NOP
                               NOP
                               NOP
                               NOP
                               NOP
                               NOP
                               NOP
                               NOP
                               NOP
    remove registerTextureFX call a@573
     ALOAD_0                   NOP
     GETFIELD 0x01 0x3d        NOP
     NEW 0x00 0x9f             NOP
     DUP                       NOP
     INVOKESPECIAL 0x02 0x47   NOP
     INVOKEVIRTUAL 0x01 0xf1   NOP
                               NOP
                               NOP
                               NOP
                               NOP
                               NOP
                               NOP
                               NOP
                               NOP
    remove registerTextureFX call a@587
     ALOAD_0                   NOP
     GETFIELD 0x01 0x3d        NOP
     NEW 0x00 0x6e             NOP
     DUP                       NOP
     INVOKESPECIAL 0x01 0xb0   NOP
     INVOKEVIRTUAL 0x01 0xf1   NOP
                               NOP
                               NOP
                               NOP
                               NOP
                               NOP
                               NOP
                               NOP
                               NOP
    remove registerTextureFX call a@601
     ALOAD_0                   NOP
     GETFIELD 0x01 0x3d        NOP
     NEW 0x00 0xb1             NOP
     DUP                       NOP
     ICONST_0                  NOP
     INVOKESPECIAL 0x02 0x88   NOP
     INVOKEVIRTUAL 0x01 0xf1   NOP
                               NOP
                               NOP
                               NOP
                               NOP
                               NOP
                               NOP
                               NOP
                               NOP
    remove registerTextureFX call a@616
     ALOAD_0                   NOP
     GETFIELD 0x01 0x3d        NOP
     NEW 0x00 0xb1             NOP
     DUP                       NOP
     ICONST_1                  NOP
     INVOKESPECIAL 0x02 0x88   NOP
     INVOKEVIRTUAL 0x01 0xf1   NOP
                               NOP
                               NOP
                               NOP
                               NOP
                               NOP
                               NOP
                               NOP
                               NOP
  adding com/pclewis/mcpatcher/MCPatcherUtils.class for __Base
  adding com/pclewis/mcpatcher/Config.class for __Base
  adding com/pclewis/mcpatcher/mod/TileSize.class for HD Textures
  adding com/pclewis/mcpatcher/mod/TextureUtils.class for HD Textures
   method signature (Ljava/lang/Class;)Lnet/minecraft/src/TextureFX; -> (Ljava/lang/Class;)Lav;
   method signature (Ljava/util/List;Lnet/minecraft/src/TextureFX;)V -> (Ljava/util/List;Lav;)V
   method signature ()Lnet/minecraft/src/TexturePackBase; -> ()Lh;
   method signature (Lnet/minecraft/src/TexturePackBase;)Ljava/lang/String; -> (Lh;)Ljava/lang/String;
   method signature (Lnet/minecraft/src/TexturePackBase;Ljava/lang/String;)Ljava/io/InputStream; -> (Lh;Ljava/lang/String;)Ljava/io/InputStream;
   method signature (Lnet/minecraft/src/TexturePackBase;Ljava/lang/String;)Ljava/awt/image/BufferedImage; -> (Lh;Ljava/lang/String;)Ljava/awt/image/BufferedImage;
   method signature (Lnet/minecraft/src/TexturePackBase;)I -> (Lh;)I
   method signature (Lnet/minecraft/src/TexturePackBase;Ljava/lang/String;)Z -> (Lh;Ljava/lang/String;)Z
   field signature Lnet/minecraft/src/TexturePackBase; -> Lh;
    method ref com.pclewis.mcpatcher.mod.TextureUtils.getSelectedTexturePack ()Lnet/minecraft/src/TexturePackBase; -> com.pclewis.mcpatcher.mod.TextureUtils.getSelectedTexturePack ()Lh; setTileSize@8
     INVOKESTATIC 0x00 0x04    INVOKESTATIC 0x02 0x7a
    method ref com.pclewis.mcpatcher.mod.TextureUtils.getSelectedTexturePack ()Lnet/minecraft/src/TexturePackBase; -> com.pclewis.mcpatcher.mod.TextureUtils.getSelectedTexturePack ()Lh; refreshTextureFX@49
     INVOKESTATIC 0x00 0x04    INVOKESTATIC 0x02 0x7a
    method ref com.pclewis.mcpatcher.mod.TextureUtils.getSelectedTexturePack ()Lnet/minecraft/src/TexturePackBase; -> com.pclewis.mcpatcher.mod.TextureUtils.getSelectedTexturePack ()Lh; getResourceAsStream@0
     INVOKESTATIC 0x00 0x04    INVOKESTATIC 0x02 0x7a
    method ref com.pclewis.mcpatcher.mod.TextureUtils.getSelectedTexturePack ()Lnet/minecraft/src/TexturePackBase; -> com.pclewis.mcpatcher.mod.TextureUtils.getSelectedTexturePack ()Lh; getResourceAsBufferedImage@0
     INVOKESTATIC 0x00 0x04    INVOKESTATIC 0x02 0x7a
    method ref com.pclewis.mcpatcher.mod.TextureUtils.getSelectedTexturePack ()Lnet/minecraft/src/TexturePackBase; -> com.pclewis.mcpatcher.mod.TextureUtils.getSelectedTexturePack ()Lh; getTileSize@0
     INVOKESTATIC 0x00 0x04    INVOKESTATIC 0x02 0x7a
    method ref com.pclewis.mcpatcher.mod.TextureUtils.getSelectedTexturePack ()Lnet/minecraft/src/TexturePackBase; -> com.pclewis.mcpatcher.mod.TextureUtils.getSelectedTexturePack ()Lh; hasResource@0
     INVOKESTATIC 0x00 0x04    INVOKESTATIC 0x02 0x7a
    method ref com.pclewis.mcpatcher.mod.TextureUtils.getTexturePackName (Lnet/minecraft/src/TexturePackBase;)Ljava/lang/String; -> com.pclewis.mcpatcher.mod.TextureUtils.getTexturePackName (Lh;)Ljava/lang/String; setTileSize@11
     INVOKESTATIC 0x00 0x05    INVOKESTATIC 0x02 0x7c
    method ref com.pclewis.mcpatcher.mod.TextureUtils.getTexturePackName (Lnet/minecraft/src/TexturePackBase;)Ljava/lang/String; -> com.pclewis.mcpatcher.mod.TextureUtils.getTexturePackName (Lh;)Ljava/lang/String; getResourceAsBufferedImage@191
     INVOKESTATIC 0x00 0x05    INVOKESTATIC 0x02 0x7c
    field ref net.minecraft.client.Minecraft.fontRenderer Lnet/minecraft/src/FontRenderer; -> net/minecraft/client/Minecraft.q Lse; setFontRenderer@12
     GETFIELD 0x00 0x0f        GETFIELD 0x02 0x80
    field ref net.minecraft.client.Minecraft.gameSettings Lnet/minecraft/src/GameSettings; -> net/minecraft/client/Minecraft.z Lkr; setFontRenderer@18
     GETFIELD 0x00 0x10        GETFIELD 0x02 0x84
    field ref net.minecraft.client.Minecraft.renderEngine Lnet/minecraft/src/RenderEngine; -> net/minecraft/client/Minecraft.p Ljf; setFontRenderer@26
     GETFIELD 0x00 0x12        GETFIELD 0x02 0x88
    method ref net.minecraft.src.FontRenderer.initialize (Lnet/minecraft/src/GameSettings;Ljava/lang/String;Lnet/minecraft/src/RenderEngine;)V -> se.initialize (Lkr;Ljava/lang/String;Ljf;)V setFontRenderer@29
     INVOKEVIRTUAL 0x00 0x13   INVOKEVIRTUAL 0x02 0x8d
    method ref com.pclewis.mcpatcher.mod.TextureUtils.newTextureFX (Ljava/lang/Class;)Lnet/minecraft/src/TextureFX; -> com.pclewis.mcpatcher.mod.TextureUtils.newTextureFX (Ljava/lang/Class;)Lav; registerTextureFX@16
     INVOKESTATIC 0x00 0x21    INVOKESTATIC 0x02 0x8f
    method ref com.pclewis.mcpatcher.mod.TextureUtils.newTextureFX (Ljava/lang/Class;)Lnet/minecraft/src/TextureFX; -> com.pclewis.mcpatcher.mod.TextureUtils.newTextureFX (Ljava/lang/Class;)Lav; refreshTextureFX@459
     INVOKESTATIC 0x00 0x21    INVOKESTATIC 0x02 0x8f
    method ref net.minecraft.src.TextureFX.onTick ()V -> av.a ()V registerTextureFX@29
     INVOKEVIRTUAL 0x00 0x23   INVOKEVIRTUAL 0x02 0x94
    method ref net.minecraft.src.TextureFX.onTick ()V -> av.a ()V refreshTextureFX@536
     INVOKEVIRTUAL 0x00 0x23   INVOKEVIRTUAL 0x02 0x94
    method ref net.minecraft.src.Compass.<init> (Lnet/minecraft/client/Minecraft;)V -> au.<init> (Lnet/minecraft/client/Minecraft;)V refreshTextureFX@23
     INVOKESPECIAL 0x00 0x2d   INVOKESPECIAL 0x02 0x98
    method ref net.minecraft.src.Watch.<init> (Lnet/minecraft/client/Minecraft;)V -> kq.<init> (Lnet/minecraft/client/Minecraft;)V refreshTextureFX@40
     INVOKESPECIAL 0x00 0x2f   INVOKESPECIAL 0x02 0x9b
    method ref com.pclewis.mcpatcher.mod.CustomAnimation.<init> (IIILjava/lang/String;II)V -> com/pclewis/mcpatcher/mod/CustomAnimation.<init> (IIILjava/lang/String;II)V refreshTextureFX@94
     INVOKESPECIAL 0x00 0x34   INVOKESPECIAL 0x00 0x34
    method ref com.pclewis.mcpatcher.mod.CustomAnimation.<init> (IIILjava/lang/String;II)V -> com/pclewis/mcpatcher/mod/CustomAnimation.<init> (IIILjava/lang/String;II)V refreshTextureFX@118
     INVOKESPECIAL 0x00 0x34   INVOKESPECIAL 0x00 0x34
    method ref com.pclewis.mcpatcher.mod.CustomAnimation.<init> (IIILjava/lang/String;II)V -> com/pclewis/mcpatcher/mod/CustomAnimation.<init> (IIILjava/lang/String;II)V refreshTextureFX@188
     INVOKESPECIAL 0x00 0x34   INVOKESPECIAL 0x00 0x34
    method ref com.pclewis.mcpatcher.mod.CustomAnimation.<init> (IIILjava/lang/String;II)V -> com/pclewis/mcpatcher/mod/CustomAnimation.<init> (IIILjava/lang/String;II)V refreshTextureFX@211
     INVOKESPECIAL 0x00 0x34   INVOKESPECIAL 0x00 0x34
    method ref com.pclewis.mcpatcher.mod.CustomAnimation.<init> (IIILjava/lang/String;II)V -> com/pclewis/mcpatcher/mod/CustomAnimation.<init> (IIILjava/lang/String;II)V refreshTextureFX@296
     INVOKESPECIAL 0x00 0x34   INVOKESPECIAL 0x00 0x34
    method ref com.pclewis.mcpatcher.mod.CustomAnimation.<init> (IIILjava/lang/String;II)V -> com/pclewis/mcpatcher/mod/CustomAnimation.<init> (IIILjava/lang/String;II)V refreshTextureFX@318
     INVOKESPECIAL 0x00 0x34   INVOKESPECIAL 0x00 0x34
    method ref com.pclewis.mcpatcher.mod.CustomAnimation.<init> (IIILjava/lang/String;II)V -> com/pclewis/mcpatcher/mod/CustomAnimation.<init> (IIILjava/lang/String;II)V refreshTextureFX@397
     INVOKESPECIAL 0x00 0x34   INVOKESPECIAL 0x00 0x34
    method ref net.minecraft.src.StillLava.<init> ()V -> ce.<init> ()V refreshTextureFX@141
     INVOKESPECIAL 0x00 0x38   INVOKESPECIAL 0x02 0x9f
    method ref net.minecraft.src.FlowLava.<init> ()V -> ic.<init> ()V refreshTextureFX@155
     INVOKESPECIAL 0x00 0x3a   INVOKESPECIAL 0x02 0xa2
    method ref net.minecraft.src.StillWater.<init> ()V -> vk.<init> ()V refreshTextureFX@234
     INVOKESPECIAL 0x00 0x40   INVOKESPECIAL 0x02 0xa5
    method ref net.minecraft.src.FlowWater.<init> ()V -> od.<init> ()V refreshTextureFX@248
     INVOKESPECIAL 0x00 0x42   INVOKESPECIAL 0x02 0xa8
    method ref net.minecraft.src.Fire.<init> (I)V -> ry.<init> (I)V refreshTextureFX@342
     INVOKESPECIAL 0x00 0x4b   INVOKESPECIAL 0x02 0xac
    method ref net.minecraft.src.Fire.<init> (I)V -> ry.<init> (I)V refreshTextureFX@357
     INVOKESPECIAL 0x00 0x4b   INVOKESPECIAL 0x02 0xac
    method ref net.minecraft.src.Portal.<init> ()V -> hq.<init> ()V refreshTextureFX@420
     INVOKESPECIAL 0x00 0x51   INVOKESPECIAL 0x02 0xaf
    field ref net.minecraft.src.ColorizerWater.colorBuffer [I -> hu.a [I refreshTextureFX@542
     GETSTATIC 0x00 0x58       GETSTATIC 0x02 0xb3
    field ref net.minecraft.src.ColorizerGrass.colorBuffer [I -> hx.a [I refreshTextureFX@550
     GETSTATIC 0x00 0x5b       GETSTATIC 0x02 0xb6
    field ref net.minecraft.src.ColorizerFoliage.colorBuffer [I -> je.a [I refreshTextureFX@558
     GETSTATIC 0x00 0x5d       GETSTATIC 0x02 0xb9
    field ref net.minecraft.client.Minecraft.texturePackList Lnet/minecraft/src/TexturePackList; -> net/minecraft/client/Minecraft.D Lih; getSelectedTexturePack@13
     GETFIELD 0x00 0x60        GETFIELD 0x02 0xbd
    field ref net.minecraft.client.Minecraft.texturePackList Lnet/minecraft/src/TexturePackList; -> net/minecraft/client/Minecraft.D Lih; getSelectedTexturePack@26
     GETFIELD 0x00 0x60        GETFIELD 0x02 0xbd
    field ref net.minecraft.src.TexturePackList.selectedTexturePack Lnet/minecraft/src/TexturePackBase; -> ih.a Lh; getSelectedTexturePack@29
     GETFIELD 0x00 0x61        GETFIELD 0x02 0xc1
    field ref net.minecraft.src.TexturePackBase.texturePackFileName Ljava/lang/String; -> h.a Ljava/lang/String; getTexturePackName@10
     GETFIELD 0x00 0x63        GETFIELD 0x02 0xc5
    method ref net.minecraft.src.GLAllocation.createDirectByteBuffer (I)Ljava/nio/ByteBuffer; -> gc.c (I)Ljava/nio/ByteBuffer; getByteBuffer@49
     INVOKESTATIC 0x00 0x67    INVOKESTATIC 0x02 0xc9
    method ref net.minecraft.src.TexturePackBase.getInputStream (Ljava/lang/String;)Ljava/io/InputStream; -> h.a (Ljava/lang/String;)Ljava/io/InputStream; getResourceAsStream@8
     INVOKEVIRTUAL 0x00 0x6c   INVOKEVIRTUAL 0x02 0xcb
    method ref com.pclewis.mcpatcher.mod.TextureUtils.getResourceAsStream (Lnet/minecraft/src/TexturePackBase;Ljava/lang/String;)Ljava/io/InputStream; -> com.pclewis.mcpatcher.mod.TextureUtils.getResourceAsStream (Lh;Ljava/lang/String;)Ljava/io/InputStream; getResourceAsStream@4
     INVOKESTATIC 0x00 0x78    INVOKESTATIC 0x02 0xcd
    method ref com.pclewis.mcpatcher.mod.TextureUtils.getResourceAsStream (Lnet/minecraft/src/TexturePackBase;Ljava/lang/String;)Ljava/io/InputStream; -> com.pclewis.mcpatcher.mod.TextureUtils.getResourceAsStream (Lh;Ljava/lang/String;)Ljava/io/InputStream; getResourceAsBufferedImage@40
     INVOKESTATIC 0x00 0x78    INVOKESTATIC 0x02 0xcd
    method ref com.pclewis.mcpatcher.mod.TextureUtils.getResourceAsStream (Lnet/minecraft/src/TexturePackBase;Ljava/lang/String;)Ljava/io/InputStream; -> com.pclewis.mcpatcher.mod.TextureUtils.getResourceAsStream (Lh;Ljava/lang/String;)Ljava/io/InputStream; getTileSize@43
     INVOKESTATIC 0x00 0x78    INVOKESTATIC 0x02 0xcd
    method ref com.pclewis.mcpatcher.mod.TextureUtils.getResourceAsStream (Lnet/minecraft/src/TexturePackBase;Ljava/lang/String;)Ljava/io/InputStream; -> com.pclewis.mcpatcher.mod.TextureUtils.getResourceAsStream (Lh;Ljava/lang/String;)Ljava/io/InputStream; hasResource@2
     INVOKESTATIC 0x00 0x78    INVOKESTATIC 0x02 0xcd
    field ref com.pclewis.mcpatcher.mod.TextureUtils.lastTexturePack Lnet/minecraft/src/TexturePackBase; -> com.pclewis.mcpatcher.mod.TextureUtils.lastTexturePack Lh; getResourceAsBufferedImage@11
     GETSTATIC 0x00 0x7a       GETSTATIC 0x02 0xcf
    field ref com.pclewis.mcpatcher.mod.TextureUtils.lastTexturePack Lnet/minecraft/src/TexturePackBase; -> com.pclewis.mcpatcher.mod.TextureUtils.lastTexturePack Lh; getResourceAsBufferedImage@116
     GETSTATIC 0x00 0x7a       GETSTATIC 0x02 0xcf
    field ref com.pclewis.mcpatcher.mod.TextureUtils.lastTexturePack Lnet/minecraft/src/TexturePackBase; -> com.pclewis.mcpatcher.mod.TextureUtils.lastTexturePack Lh; getResourceAsBufferedImage@256
     PUTSTATIC 0x00 0x7a       PUTSTATIC 0x02 0xcf
    field ref com.pclewis.mcpatcher.mod.TextureUtils.lastTexturePack Lnet/minecraft/src/TexturePackBase; -> com.pclewis.mcpatcher.mod.TextureUtils.lastTexturePack Lh; <clinit>@11
     PUTSTATIC 0x00 0x7a       PUTSTATIC 0x02 0xcf
    method ref com.pclewis.mcpatcher.mod.TextureUtils.getResourceAsBufferedImage (Lnet/minecraft/src/TexturePackBase;Ljava/lang/String;)Ljava/awt/image/BufferedImage; -> com.pclewis.mcpatcher.mod.TextureUtils.getResourceAsBufferedImage (Lh;Ljava/lang/String;)Ljava/awt/image/BufferedImage; getResourceAsBufferedImage@4
     INVOKESTATIC 0x00 0x93    INVOKESTATIC 0x02 0xd1
    method ref com.pclewis.mcpatcher.mod.TextureUtils.getTileSize (Lnet/minecraft/src/TexturePackBase;)I -> com.pclewis.mcpatcher.mod.TextureUtils.getTileSize (Lh;)I getTileSize@3
     INVOKESTATIC 0x00 0x9c    INVOKESTATIC 0x02 0xd3
    method ref com.pclewis.mcpatcher.mod.TextureUtils.hasResource (Lnet/minecraft/src/TexturePackBase;Ljava/lang/String;)Z -> com.pclewis.mcpatcher.mod.TextureUtils.hasResource (Lh;Ljava/lang/String;)Z hasResource@4
     INVOKESTATIC 0x00 0x9d    INVOKESTATIC 0x02 0xd5
   string replace net/minecraft/src/StillWater -> vk @3364
   string replace net/minecraft/src/TexturePackDefault -> ow @2972
   string replace net/minecraft/src/Watch -> kq @2920
   string replace net/minecraft/src/Compass -> au @2813
   string replace net/minecraft/src/Portal -> hq @3683
   string replace net/minecraft/src/FlowWater -> od @3307
   string replace net/minecraft/src/StillLava -> ce @3104
   string replace net/minecraft/src/TextureFX -> av @1642
   string replace net/minecraft/src/FlowLava -> ic @3105
   string replace net/minecraft/src/Fire -> ry @3435
  adding com/pclewis/mcpatcher/mod/CustomAnimation.class for HD Textures
   method onTick -> a
    method ref net.minecraft.src.TextureFX.<init> (I)V -> av.<init> (I)V <init>@2
     INVOKESPECIAL 0x00 0x01   INVOKESPECIAL 0x00 0xaa
    field ref com.pclewis.mcpatcher.mod.CustomAnimation.minScrollDelay I -> com/pclewis/mcpatcher/mod/CustomAnimation.minScrollDelay I <init>@7
     PUTFIELD 0x00 0x02        PUTFIELD 0x00 0x02
    field ref com.pclewis.mcpatcher.mod.CustomAnimation.minScrollDelay I -> com/pclewis/mcpatcher/mod/CustomAnimation.minScrollDelay I <init>@38
     PUTFIELD 0x00 0x02        PUTFIELD 0x00 0x02
    field ref com.pclewis.mcpatcher.mod.CustomAnimation.minScrollDelay I -> com/pclewis/mcpatcher/mod/CustomAnimation.minScrollDelay I a@112
     GETFIELD 0x00 0x02        GETFIELD 0x00 0x02
    field ref com.pclewis.mcpatcher.mod.CustomAnimation.minScrollDelay I -> com/pclewis/mcpatcher/mod/CustomAnimation.minScrollDelay I a@122
     GETFIELD 0x00 0x02        GETFIELD 0x00 0x02
    field ref com.pclewis.mcpatcher.mod.CustomAnimation.maxScrollDelay I -> com/pclewis/mcpatcher/mod/CustomAnimation.maxScrollDelay I <init>@12
     PUTFIELD 0x00 0x03        PUTFIELD 0x00 0x03
    field ref com.pclewis.mcpatcher.mod.CustomAnimation.maxScrollDelay I -> com/pclewis/mcpatcher/mod/CustomAnimation.maxScrollDelay I <init>@44
     PUTFIELD 0x00 0x03        PUTFIELD 0x00 0x03
    field ref com.pclewis.mcpatcher.mod.CustomAnimation.maxScrollDelay I -> com/pclewis/mcpatcher/mod/CustomAnimation.maxScrollDelay I a@76
     GETFIELD 0x00 0x03        GETFIELD 0x00 0x03
    field ref com.pclewis.mcpatcher.mod.CustomAnimation.maxScrollDelay I -> com/pclewis/mcpatcher/mod/CustomAnimation.maxScrollDelay I a@97
     GETFIELD 0x00 0x03        GETFIELD 0x00 0x03
    field ref com.pclewis.mcpatcher.mod.CustomAnimation.maxScrollDelay I -> com/pclewis/mcpatcher/mod/CustomAnimation.maxScrollDelay I a@108
     GETFIELD 0x00 0x03        GETFIELD 0x00 0x03
    field ref com.pclewis.mcpatcher.mod.CustomAnimation.timer I -> com/pclewis/mcpatcher/mod/CustomAnimation.timer I <init>@17
     PUTFIELD 0x00 0x04        PUTFIELD 0x00 0x04
    field ref com.pclewis.mcpatcher.mod.CustomAnimation.timer I -> com/pclewis/mcpatcher/mod/CustomAnimation.timer I a@84
     GETFIELD 0x00 0x04        GETFIELD 0x00 0x04
    field ref com.pclewis.mcpatcher.mod.CustomAnimation.timer I -> com/pclewis/mcpatcher/mod/CustomAnimation.timer I a@90
     PUTFIELD 0x00 0x04        PUTFIELD 0x00 0x04
    field ref com.pclewis.mcpatcher.mod.CustomAnimation.timer I -> com/pclewis/mcpatcher/mod/CustomAnimation.timer I a@126
     PUTFIELD 0x00 0x04        PUTFIELD 0x00 0x04
    field ref com.pclewis.mcpatcher.mod.CustomAnimation.tileNumber I -> com/pclewis/mcpatcher/mod/CustomAnimation.b I <init>@22
     PUTFIELD 0x00 0x05        PUTFIELD 0x00 0xad
    field ref com.pclewis.mcpatcher.mod.CustomAnimation.tileNumber I -> com/pclewis/mcpatcher/mod/CustomAnimation.b I <init>@161
     GETFIELD 0x00 0x05        GETFIELD 0x00 0xad
    field ref com.pclewis.mcpatcher.mod.CustomAnimation.tileImage I -> com/pclewis/mcpatcher/mod/CustomAnimation.f I <init>@27
     PUTFIELD 0x00 0x06        PUTFIELD 0x00 0xb0
    field ref com.pclewis.mcpatcher.mod.CustomAnimation.tileSize I -> com/pclewis/mcpatcher/mod/CustomAnimation.e I <init>@32
     PUTFIELD 0x00 0x07        PUTFIELD 0x00 0xb2
    field ref com.pclewis.mcpatcher.mod.CustomAnimation.isScrolling Z -> com/pclewis/mcpatcher/mod/CustomAnimation.isScrolling Z <init>@58
     PUTFIELD 0x00 0x08        PUTFIELD 0x00 0x08
    field ref com.pclewis.mcpatcher.mod.CustomAnimation.isScrolling Z -> com/pclewis/mcpatcher/mod/CustomAnimation.isScrolling Z <init>@253
     GETFIELD 0x00 0x08        GETFIELD 0x00 0x08
    field ref com.pclewis.mcpatcher.mod.CustomAnimation.isScrolling Z -> com/pclewis/mcpatcher/mod/CustomAnimation.isScrolling Z a@69
     GETFIELD 0x00 0x08        GETFIELD 0x00 0x08
    field ref com.pclewis.mcpatcher.mod.CustomAnimation.imageData [B -> com/pclewis/mcpatcher/mod/CustomAnimation.a [B <init>@150
     GETFIELD 0x00 0x15        GETFIELD 0x00 0xb4
    field ref com.pclewis.mcpatcher.mod.CustomAnimation.imageData [B -> com/pclewis/mcpatcher/mod/CustomAnimation.a [B <init>@246
     GETFIELD 0x00 0x15        GETFIELD 0x00 0xb4
    field ref com.pclewis.mcpatcher.mod.CustomAnimation.imageData [B -> com/pclewis/mcpatcher/mod/CustomAnimation.a [B a@49
     GETFIELD 0x00 0x15        GETFIELD 0x00 0xb4
    field ref com.pclewis.mcpatcher.mod.CustomAnimation.imageData [B -> com/pclewis/mcpatcher/mod/CustomAnimation.a [B a@130
     GETFIELD 0x00 0x15        GETFIELD 0x00 0xb4
    field ref com.pclewis.mcpatcher.mod.CustomAnimation.imageData [B -> com/pclewis/mcpatcher/mod/CustomAnimation.a [B a@158
     GETFIELD 0x00 0x15        GETFIELD 0x00 0xb4
    field ref com.pclewis.mcpatcher.mod.CustomAnimation.imageData [B -> com/pclewis/mcpatcher/mod/CustomAnimation.a [B a@163
     GETFIELD 0x00 0x15        GETFIELD 0x00 0xb4
    field ref com.pclewis.mcpatcher.mod.CustomAnimation.imageData [B -> com/pclewis/mcpatcher/mod/CustomAnimation.a [B a@191
     GETFIELD 0x00 0x15        GETFIELD 0x00 0xb4
    method ref com.pclewis.mcpatcher.mod.CustomAnimation.ARGBtoRGBA ([I[B)V -> com/pclewis/mcpatcher/mod/CustomAnimation.ARGBtoRGBA ([I[B)V <init>@249
     INVOKESTATIC 0x00 0x1d    INVOKESTATIC 0x00 0x1d
    method ref com.pclewis.mcpatcher.mod.CustomAnimation.ARGBtoRGBA ([I[B)V -> com/pclewis/mcpatcher/mod/CustomAnimation.ARGBtoRGBA ([I[B)V <init>@344
     INVOKESTATIC 0x00 0x1d    INVOKESTATIC 0x00 0x1d
    field ref com.pclewis.mcpatcher.mod.CustomAnimation.temp [B -> com/pclewis/mcpatcher/mod/CustomAnimation.temp [B <init>@267
     PUTFIELD 0x00 0x1e        PUTFIELD 0x00 0x1e
    field ref com.pclewis.mcpatcher.mod.CustomAnimation.temp [B -> com/pclewis/mcpatcher/mod/CustomAnimation.temp [B a@145
     GETFIELD 0x00 0x1e        GETFIELD 0x00 0x1e
    field ref com.pclewis.mcpatcher.mod.CustomAnimation.temp [B -> com/pclewis/mcpatcher/mod/CustomAnimation.temp [B a@186
     GETFIELD 0x00 0x1e        GETFIELD 0x00 0x1e
    field ref com.pclewis.mcpatcher.mod.CustomAnimation.numFrames I -> com/pclewis/mcpatcher/mod/CustomAnimation.numFrames I <init>@285
     PUTFIELD 0x00 0x21        PUTFIELD 0x00 0x21
    field ref com.pclewis.mcpatcher.mod.CustomAnimation.numFrames I -> com/pclewis/mcpatcher/mod/CustomAnimation.numFrames I a@19
     GETFIELD 0x00 0x21        GETFIELD 0x00 0x21
    field ref com.pclewis.mcpatcher.mod.CustomAnimation.src [B -> com/pclewis/mcpatcher/mod/CustomAnimation.src [B <init>@335
     PUTFIELD 0x00 0x22        PUTFIELD 0x00 0x22
    field ref com.pclewis.mcpatcher.mod.CustomAnimation.src [B -> com/pclewis/mcpatcher/mod/CustomAnimation.src [B <init>@341
     GETFIELD 0x00 0x22        GETFIELD 0x00 0x22
    field ref com.pclewis.mcpatcher.mod.CustomAnimation.src [B -> com/pclewis/mcpatcher/mod/CustomAnimation.src [B a@1
     GETFIELD 0x00 0x22        GETFIELD 0x00 0x22
    field ref com.pclewis.mcpatcher.mod.CustomAnimation.src [B -> com/pclewis/mcpatcher/mod/CustomAnimation.src [B a@31
     GETFIELD 0x00 0x22        GETFIELD 0x00 0x22
    field ref com.pclewis.mcpatcher.mod.CustomAnimation.frame I -> com/pclewis/mcpatcher/mod/CustomAnimation.frame I a@9
     GETFIELD 0x00 0x23        GETFIELD 0x00 0x23
    field ref com.pclewis.mcpatcher.mod.CustomAnimation.frame I -> com/pclewis/mcpatcher/mod/CustomAnimation.frame I a@15
     PUTFIELD 0x00 0x23        PUTFIELD 0x00 0x23
    field ref com.pclewis.mcpatcher.mod.CustomAnimation.frame I -> com/pclewis/mcpatcher/mod/CustomAnimation.frame I a@27
     PUTFIELD 0x00 0x23        PUTFIELD 0x00 0x23
    field ref com.pclewis.mcpatcher.mod.CustomAnimation.frame I -> com/pclewis/mcpatcher/mod/CustomAnimation.frame I a@35
     GETFIELD 0x00 0x23        GETFIELD 0x00 0x23
    field ref com.pclewis.mcpatcher.mod.CustomAnimation.rand Ljava/util/Random; -> com/pclewis/mcpatcher/mod/CustomAnimation.rand Ljava/util/Random; a@104
     GETSTATIC 0x00 0x25       GETSTATIC 0x00 0x25
    field ref com.pclewis.mcpatcher.mod.CustomAnimation.rand Ljava/util/Random; -> com/pclewis/mcpatcher/mod/CustomAnimation.rand Ljava/util/Random; <clinit>@7
     PUTSTATIC 0x00 0x25       PUTSTATIC 0x00 0x25
   string replace net/minecraft/src/TextureFX -> av @58

Done!

#### Patch summary:
__Base
    added com/pclewis/mcpatcher/MCPatcherUtils.class
    added com/pclewis/mcpatcher/Config.class

HD Textures
    added com/pclewis/mcpatcher/mod/TextureUtils.class
    added com/pclewis/mcpatcher/mod/TileSize.class
    added com/pclewis/mcpatcher/mod/CustomAnimation.class
    RenderEngine (jf.class)
        [1] (i % 16) * 16 + j * 16 -> (i % 16) * int_size + j * int_size
        [1] (i / 16) * 16 + j * 16 -> (i / 16) * int_size + j * int_size
        [1] 1048576 -> int_glBufferSize
        [1] call TextureUtils.registerTextureFX
        [1] getInputStream(...), readTextureImage -> getResourceAsBufferedImage(...)
        [2] glTexSubImage2D(...,16,16) -> glTexSubImage2D(...,int_size,int_size)
        [4] imageData.clear(), .put(), .limit() -> imageData = TextureUtils.getByteBuffer()
        [1] insert method setTileSize (Lnet/minecraft/client/Minecraft;)V
        [14] readTextureImage(getInputStream(...)) -> getResourceAsBufferedImage(...)
    TextureFX (av.class)
        [1] array size 1024 -> int_numBytes
    Compass (au.class)
        [4] * 16 -> int_size
        [1] -4 -> int_compassCrossMin
        [1] -8 -> int_compassNeedleMin
        [2] 7.5D -> double_compassCenterMin
        [2] 8.5D -> double_compassCenterMax
        [1] array size 256 -> int_numPixels
        [1] getRGB(...16,16,...16) -> getRGB(...int_size,int_size,...int_size)
        [1] if i > 16 -> int_compassNeedleMax
        [1] if i > 4 -> int_compassCrossMax
        [1] while i < 256 -> int_numPixels
    Fire (ry.class)
        [1] % 20 -> int_flameHeight
        [4] * 16 -> int_size
        [1] 1.06F -> float_flameNudge
        [2] array size 320 -> int_flameArraySize
        [1] if i < 19 -> int_flameHeightMinus1
        [2] while i < 16 -> int_size
        [2] while i < 20 -> int_flameHeight
        [1] while i < 256 -> int_numPixels
    StillLava (ce.class)
        [10] & 15 -> int_sizeMinus1
        [12] * 16 -> int_size
        [4] array size 256 -> int_numPixels
        [2] while i < 16 -> int_size
        [1] while i < 256 -> int_numPixels
    FlowLava (ic.class)
        [10] & 15 -> int_sizeMinus1
        [1] & 255 -> int_numPixelsMinus1
        [13] * 16 -> int_size
        [4] array size 256 -> int_numPixels
        [2] while i < 16 -> int_size
        [1] while i < 256 -> int_numPixels
    StillWater (vk.class)
        [2] & 15 -> int_sizeMinus1
        [9] * 16 -> int_size
        [4] array size 256 -> int_numPixels
        [4] while i < 16 -> int_size
        [1] while i < 256 -> int_numPixels
    FlowWater (od.class)
        [2] & 15 -> int_sizeMinus1
        [1] & 255 -> int_numPixelsMinus1
        [10] * 16 -> int_size
        [4] array size 256 -> int_numPixels
        [4] while i < 16 -> int_size
        [1] while i < 256 -> int_numPixels
    ItemRenderer (qv.class)
        [4] 0.001953125F -> float_texNudge
        [4] 16.0F -> float_size
        [4] while i < 16 -> int_size
    Watch (kq.class)
        [1] % 16 -> int_size
        [2] & 15 -> int_sizeMinus1
        [3] * 16 -> int_size
        [1] / 16 -> int_size
        [2] 15.0D -> double_sizeMinus1
        [2] 16.0D -> double_size
        [2] array size 256 -> int_numPixels
        [2] getRGB(...16,16,...16) -> getRGB(...int_size,int_size,...int_size)
        [1] while i < 256 -> int_numPixels
    Portal (hq.class)
        [1] * 16 -> int_size
        [2] * 8 -> int_sizeHalf
        [2] 16.0F -> float_size
        [1] array size 32x1024 -> int_numBytes
        [2] while i < 16 -> int_size
        [1] while i < 256 -> int_numPixels
    Minecraft (net/minecraft/client/Minecraft.class)
        [1] TextureUtils.setMinecraft(this) on startup
        [1] TextureUtils.setTileSize(), renderEngine.setTileSize() on startup
        [9] remove registerTextureFX call
    GLAllocation (gc.class)
    TexturePackList (ih.class)
        [1] TexturePackList.setTileSize(selectedTexturePack) on texture pack change
    TexturePackBase (h.class)
    TexturePackDefault (ow.class)
    FontRenderer (se.class)
        [1] insert method initialize ()V
    GameSettings (kr.class)
    GetResource (multiple matches: au fw kq ow se uh vh)
        [8] ImageIO.read(getResource(...)) -> getResourceAsBufferedImage(...)
    ColorizerWater (hu.class)
        [1] make field colorBuffer public
    ColorizerGrass (hx.class)
        [1] make field colorBuffer public
    ColorizerFoliage (je.class)
        [1] make field colorBuffer public

HD Font
    FontRenderer (se.class)
        [2] font charWidth computation: j + 2 -> (128 * j + 256) / i
        [2] font whitespace width 2 -> i / 64
        [2] font width 7 -> i / 16 - 1
        [7] font width 8 -> i / 16

Better Grass
    Material (lj.class)
    Block (un.class)
    BlockGrass (wg.class)
        [1] check surrounding blocks in getBlockTexture
        [1] initialize grassMatrix
        [1] insert field grassMatrix [[I
    IBlockAccess (xg.class)
    RenderBlocks (ct.class)
        [2] if (getBlockTexture == 0) useBiomeColor = true (AO)
        [4] if (getBlockTexture == 0) useBiomeColor = true (non-AO)

