MCPatcher version is 2.3.1
OS: Linux 3.1.7-1.fc16.x86_64 amd64
JVM: Sun Microsystems Inc. 1.6.0_30 (64 bit)
Classpath: out/artifacts/mcpatcher/mcpatcher.jar
Minecraft version is 1.1 (md5 e92302d2acdba7c97e0d8df1e10d2006)

Analyzing /home/prupe/.minecraft/bin/minecraft-1.1.jar (1446 files)
  Material matches aan.class
  EntityLiving matches aar.class
  EntityLiving matches aar.class
  ItemSpawnerEgg matches aaw.class
   getItemNameIS matches d (Lyq;)Ljava/lang/String;
   getColorFromDamage matches b (II)I
  NBTTagCompound matches abx.class
  BlockStem matches ach.class
   getRenderColor matches d (I)I
  FlowWater matches ack.class
  BlockFluid matches aes.class
   colorMultiplier matches b (Laiw;III)I
  BlockRedstoneWire matches aff.class
   randomDisplayTick matches b (Lvq;IIILjava/util/Random;)V
  BiomeGenSwamp matches afp.class
  TexturePackCustom matches ahk.class
  WorldProvider matches aip.class
   getFogColor matches b (FF)Lbk;
  IBlockAccess matches aiw.class
  IBlockAccess matches aiw.class
  BlockMycelium matches aje.class
   getBlockTexture matches d (Laiw;IIII)I
  RenderSpider matches ajy.class
  StillLava matches bo.class
  GLAllocation matches ep.class
   createDirectByteBuffer matches c (I)Ljava/nio/ByteBuffer;
  RenderLiving matches ey.class
   doRenderLiving matches a (Laar;DDDFF)V
  EntityDropParticleFX matches fs.class
   onUpdate matches B_ ()V
  FlowLava matches fv.class
  TexturePackList matches fy.class
  TexturePackList matches fy.class
  TexturePackList matches fy.class
  ColorizerFoliage matches gk.class
  ColorizerFoliage matches gk.class
  TexturePackBase matches h.class
   getInputStream matches a (Ljava/lang/String;)Ljava/io/InputStream;
  TexturePackBase matches h.class
   getInputStream matches a (Ljava/lang/String;)Ljava/io/InputStream;
  TexturePackBase matches h.class
   getInputStream matches a (Ljava/lang/String;)Ljava/io/InputStream;
  Watch matches hg.class
  GameSettings matches hh.class
  PotionHelper matches hl.class
  TexturePackDefault matches kl.class
  EntityRenderer matches kz.class
   updateFogColor matches g (F)V
   updateLightmap matches e ()V
  RenderGlobal matches l.class
   renderClouds matches b (F)V
  ItemRenderer matches lv.class
  ItemRenderer matches lv.class
  Fire matches mn.class
  FontRenderer matches mq.class
  FontRenderer matches mq.class
  Entity matches ms.class
  Entity matches ms.class
   setPositionAndRotation matches b (DDDFF)V
  EntitySplashFX matches nb.class
  Block matches oe.class
  Block matches oe.class
   getRenderColor matches d (I)I
  StillWater matches pd.class
  BlockGrass matches qb.class
   getBlockTexture matches d (Laiw;IIII)I
  EntityRainFX matches qj.class
  WorldChunkManager matches qu.class
  EntityFX matches qv.class
   setPositionAndRotation matches b (DDDFF)V
  RenderEnderman matches rv.class
  TextureFX matches sr.class
   onTick matches a ()V
  Compass matches ss.class
  BlockLeaves matches tb.class
   colorMultiplier matches b (Laiw;III)I
  ItemBlock matches tw.class
  EntityBubbleFX matches tz.class
   setPositionAndRotation matches b (DDDFF)V
  RenderBlocks matches uc.class
   renderStandardBlockWithAmbientOcclusion matches a (Loe;IIIFFF)Z
   renderStandardBlockWithColorMultiplier matches b (Loe;IIIFFF)Z
   non-AO multipliers (R G B) = (14 15 16)
   AO faces (N S E W) = (17 18 15 16)
  RenderBlocks matches uc.class
   renderBlockRedstoneWire matches g (Loe;III)Z
   renderBlockFallingSand matches a (Loe;Lvq;III)V
   renderBlockFluids matches n (Loe;III)Z
  World matches vq.class
   getSkyColor matches a (Lms;F)Lbk;
   getSunAngle matches b (F)F
  BlockCauldron matches vw.class
   colorMultiplier matches b (Laiw;III)I
   getRenderColor matches d (I)I
  BlockLilyPad matches wl.class
  Item matches ww.class
   getColorFromDamage matches b (II)I
   getColorFromDamage(II)I has 2 params
  Portal matches xs.class
  ColorizerWater matches xw.class
  ColorizerGrass matches xy.class
  EntityReddustFX matches ye.class
  Potion matches yg.class
   setPotionName matches a (Ljava/lang/String;)Lyg;
  EntityList matches yr.class
   addMapping matches a (Ljava/lang/Class;Ljava/lang/String;I)V
   getEntityString matches a (I)Ljava/lang/String;
  RenderEngine matches yz.class
   refreshTextures matches b ()V
  BiomeGenBase matches zp.class
   getFoliageColor matches b (Laiw;III)I
   setBiomeName matches a (Ljava/lang/String;)Lzp;
  Minecraft matches net/minecraft/client/Minecraft.class
  Minecraft matches net/minecraft/client/Minecraft.class
   runTick matches k ()V
  Minecraft matches net/minecraft/client/Minecraft.class
  Minecraft matches net/minecraft/client/Minecraft.class

Analyzing /home/prupe/.minecraft/bin/minecraft-1.1.jar (second pass)
  Minecraft (net/minecraft/client/Minecraft.class)
  RenderEngine (yz.class)
   field imageData matches h Ljava/nio/ByteBuffer;
   field textureList matches i Ljava/util/List;
   method registerTextureFX matches a (Lsr;)V
   method readTextureImage matches a (Ljava/io/InputStream;)Ljava/awt/image/BufferedImage;
   method setupTexture matches a (Ljava/awt/image/BufferedImage;I)V
   method getImageRGB matches a (Ljava/awt/image/BufferedImage;[I)[I
   method readTextureImageData matches a (Ljava/lang/String;)[I
  TextureFX (sr.class)
   field imageData matches f [B
   field tileNumber matches g I
   field tileSize matches j I
   field tileImage matches k I
  Compass (ss.class)
  Fire (mn.class)
  StillLava (bo.class)
  FlowLava (fv.class)
  StillWater (pd.class)
  FlowWater (ack.class)
  ItemRenderer (lv.class)
  Watch (hg.class)
  Portal (xs.class)
  Minecraft (net/minecraft/client/Minecraft.class)
   field texturePackList matches E Lfy;
   field renderEngine matches p Lyz;
   field gameSettings matches A Lhh;
   field fontRenderer matches q Lmq;
   field alternateFontRenderer matches r Lmq;
  GLAllocation (ep.class)
  TexturePackList (fy.class)
   field selectedTexturePack matches a Lh;
   field defaultTexturePack matches c Lh;
   field minecraft matches e Lnet/minecraft/client/Minecraft;
   method updateAvailableTexturePacks matches a ()V
   method setTexturePack matches a (Lh;)Z
   method availableTexturePacks matches b ()Ljava/util/List;
  TexturePackBase (h.class)
   field texturePackFileName matches a Ljava/lang/String;
   method openTexturePackFile matches a ()V
   method closeTexturePackFile matches b ()V
  TexturePackCustom (ahk.class)
   field zipFile matches e Ljava/util/zip/ZipFile;
   field file matches h Ljava/io/File;
  TexturePackDefault (kl.class)
  FontRenderer (mq.class)
  GameSettings (hh.class)
  ColorizerWater (xw.class)
   field colorBuffer matches a [I
  ColorizerGrass (xy.class)
   field colorBuffer matches a [I
  ColorizerFoliage (gk.class)
   field colorBuffer matches a [I
  FontRenderer (mq.class)
   method getStringWidth matches a (Ljava/lang/String;)I
  Material (aan.class)
   field ground matches b Laan;
  Block (oe.class)
   field blockID matches bO I
   field blocksList matches m [Loe;
   method getBlockTexture matches d (Laiw;IIII)I
  BlockGrass (qb.class)
  BlockMycelium (aje.class)
  IBlockAccess (aiw.class)
   method getBlockId matches a (III)I
   method getBlockMetadata matches e (III)I
   method getBlockMaterial matches f (III)Laan;
  RenderBlocks (uc.class)
   field blockAccess matches a Laiw;
  RenderLiving (ey.class)
  RenderSpider (ajy.class)
  RenderEnderman (rv.class)
  Entity (ms.class)
   field entityId matches f I
   field nextEntityID matches a I
   method getEntityTexture matches M ()Ljava/lang/String;
   method writeToNBT matches d (Labx;)V
   method readFromNBT matches e (Labx;)V
  EntityLiving (aar.class)
  NBTTagCompound (abx.class)
   method getLong matches g (Ljava/lang/String;)J
   method setLong matches a (Ljava/lang/String;J)V
  Minecraft (net/minecraft/client/Minecraft.class)
   field texturePackList matches E Lfy;
  TexturePackList (fy.class)
   field selectedTexturePack matches a Lh;
   field defaultTexturePack matches c Lh;
   field minecraft matches e Lnet/minecraft/client/Minecraft;
  TexturePackBase (h.class)
   field texturePackFileName matches a Ljava/lang/String;
  Minecraft (net/minecraft/client/Minecraft.class)
   field texturePackList matches E Lfy;
  TexturePackList (fy.class)
   field selectedTexturePack matches a Lh;
   field defaultTexturePack matches c Lh;
   field minecraft matches e Lnet/minecraft/client/Minecraft;
  TexturePackBase (h.class)
   field texturePackFileName matches a Ljava/lang/String;
  IBlockAccess (aiw.class)
   method getBlockId matches a (III)I
   method getBlockMetadata matches e (III)I
  Block (oe.class)
   field blockID matches bO I
   field blocksList matches m [Loe;
  BiomeGenBase (zp.class)
   method getGrassColor matches a (Laiw;III)I
   method getFoliageColor matches b (Laiw;III)I
   field color matches x I
  BiomeGenSwamp (afp.class)
  BlockFluid (aes.class)
  BlockCauldron (vw.class)
  Item (ww.class)
  ItemBlock (tw.class)
   field blockID matches a I
  ItemRenderer (lv.class)
  Potion (yg.class)
  PotionHelper (hl.class)
  ColorizerFoliage (gk.class)
  BlockLeaves (tb.class)
  World (vq.class)
   method getWorldChunkManager matches a ()Lqu;
  WorldProvider (aip.class)
  WorldChunkManager (qu.class)
   method getBiomeGenAt matches a (II)Lzp;
  Entity (ms.class)
   field worldObj matches k Lvq;
  EntityFX (qv.class)
  EntityRainFX (qj.class)
  EntityDropParticleFX (fs.class)
  EntitySplashFX (nb.class)
  EntityBubbleFX (tz.class)
  EntityLiving (aar.class)
  EntityRenderer (kz.class)
  BlockLilyPad (wl.class)
  BlockRedstoneWire (aff.class)
  RenderBlocks (uc.class)
   method renderBlockCauldron matches a (Lvw;III)Z
  EntityReddustFX (ye.class)
  RenderGlobal (l.class)
  BlockStem (ach.class)
  EntityList (yr.class)
  ItemSpawnerEgg (aaw.class)

5 available mods:
[YES] HD Textures 1.2 - Provides support for texture packs of size 32x32 and higher.
[YES] HD Font 1.2 - Provides support for higher resolution fonts.
[YES] Better Grass 1.0 - Improves the look of the sides of grass blocks. Inspired by MrMessiah's mod.
[YES] Random Mobs 1.1 - Randomize mob skins if texture pack supports it. Based on Balthichou's mod.
[YES] Custom Colors 1.2 - Gives texture packs control over hardcoded colors in the game.

#### Class map:
HD Textures
    class ColorizerFoliage (gk.class)
        field colorBuffer -> a [I
    class ColorizerGrass (xy.class)
        field colorBuffer -> a [I
    class ColorizerWater (xw.class)
        field colorBuffer -> a [I
    class Compass (ss.class)
    class Fire (mn.class)
    class FlowLava (fv.class)
    class FlowWater (ack.class)
    class FontRenderer (mq.class)
        field charWidth -> d [I
        field fontTextureName -> a I
        field isUnicode -> l Z
    class GLAllocation (ep.class)
        method createDirectByteBuffer -> c (I)Ljava/nio/ByteBuffer;
    class GameSettings (hh.class)
    class ItemRenderer (lv.class)
    class Minecraft (net/minecraft/client/Minecraft.class)
        method runTick -> k ()V
        field alternateFontRenderer -> r Lmq;
        field fontRenderer -> q Lmq;
        field gameSettings -> A Lhh;
        field renderEngine -> p Lyz;
        field texturePackList -> E Lfy;
    class Portal (xs.class)
    class RenderEngine (yz.class)
        method getImageRGB -> a (Ljava/awt/image/BufferedImage;[I)[I
        method readTextureImage -> a (Ljava/io/InputStream;)Ljava/awt/image/BufferedImage;
        method readTextureImageData -> a (Ljava/lang/String;)[I
        method refreshTextures -> b ()V
        method registerTextureFX -> a (Lsr;)V
        method setupTexture -> a (Ljava/awt/image/BufferedImage;I)V
        field imageData -> h Ljava/nio/ByteBuffer;
        field textureList -> i Ljava/util/List;
    class StillLava (bo.class)
    class StillWater (pd.class)
    class TextureFX (sr.class)
        method onTick -> a ()V
        field imageData -> f [B
        field tileImage -> k I
        field tileNumber -> g I
        field tileSize -> j I
    class TexturePackBase (h.class)
        method closeTexturePackFile -> b ()V
        method getInputStream -> a (Ljava/lang/String;)Ljava/io/InputStream;
        method openTexturePackFile -> a ()V
        field texturePackFileName -> a Ljava/lang/String;
    class TexturePackCustom (ahk.class) extends TexturePackBase
        method closeTexturePackFile -> b ()V
        method getInputStream -> a (Ljava/lang/String;)Ljava/io/InputStream;
        method openTexturePackFile -> a ()V
        field file -> h Ljava/io/File;
        field texturePackFileName -> a Ljava/lang/String;
        field zipFile -> e Ljava/util/zip/ZipFile;
    class TexturePackDefault (kl.class)
    class TexturePackList (fy.class)
        method availableTexturePacks -> b ()Ljava/util/List;
        method setTexturePack -> a (Lh;)Z
        method updateAvailableTexturePacks -> a ()V
        field defaultTexturePack -> c Lh;
        field minecraft -> e Lnet/minecraft/client/Minecraft;
        field selectedTexturePack -> a Lh;
    class Watch (hg.class)
    class net.minecraft.client.Minecraft alias for Minecraft
    class net.minecraft.src.ColorizerFoliage alias for ColorizerFoliage
    class net.minecraft.src.ColorizerGrass alias for ColorizerGrass
    class net.minecraft.src.ColorizerWater alias for ColorizerWater
    class net.minecraft.src.Compass alias for Compass
    class net.minecraft.src.Fire alias for Fire
    class net.minecraft.src.FlowLava alias for FlowLava
    class net.minecraft.src.FlowWater alias for FlowWater
    class net.minecraft.src.FontRenderer alias for FontRenderer
    class net.minecraft.src.GLAllocation alias for GLAllocation
    class net.minecraft.src.GameSettings alias for GameSettings
    class net.minecraft.src.ItemRenderer alias for ItemRenderer
    class net.minecraft.src.Portal alias for Portal
    class net.minecraft.src.RenderEngine alias for RenderEngine
    class net.minecraft.src.StillLava alias for StillLava
    class net.minecraft.src.StillWater alias for StillWater
    class net.minecraft.src.TextureFX alias for TextureFX
    class net.minecraft.src.TexturePackBase alias for TexturePackBase
    class net.minecraft.src.TexturePackCustom alias for TexturePackCustom
    class net.minecraft.src.TexturePackDefault alias for TexturePackDefault
    class net.minecraft.src.TexturePackList alias for TexturePackList
    class net.minecraft.src.Watch alias for Watch

HD Font
    class FontRenderer (mq.class)
        method getStringWidth -> a (Ljava/lang/String;)I
        field charWidth -> d [I
        field fontTextureName -> a I
    class net.minecraft.src.FontRenderer alias for FontRenderer

Better Grass
    class Block (oe.class)
        method getBlockTexture -> d (Laiw;IIII)I
        field blockID -> bO I
        field blocksList -> m [Loe;
    class BlockGrass (qb.class)
        method getBlockTexture -> d (Laiw;IIII)I
    class BlockMycelium (aje.class)
        method getBlockTexture -> d (Laiw;IIII)I
    class IBlockAccess (aiw.class)
        method getBlockId -> a (III)I
        method getBlockMaterial -> f (III)Laan;
        method getBlockMetadata -> e (III)I
    class Material (aan.class)
        field builtSnow -> v Laan;
        field ground -> b Laan;
        field snow -> u Laan;
    class RenderBlocks (uc.class)
        method renderStandardBlockWithAmbientOcclusion -> a (Loe;IIIFFF)Z
        method renderStandardBlockWithColorMultiplier -> b (Loe;IIIFFF)Z
        field blockAccess -> a Laiw;
    class net.minecraft.src.Block alias for Block
    class net.minecraft.src.BlockGrass alias for BlockGrass
    class net.minecraft.src.BlockMycelium alias for BlockMycelium
    class net.minecraft.src.IBlockAccess alias for IBlockAccess
    class net.minecraft.src.Material alias for Material
    class net.minecraft.src.RenderBlocks alias for RenderBlocks

Random Mobs
    class Entity (ms.class)
        method getEntityTexture -> M ()Ljava/lang/String;
        method readFromNBT -> e (Labx;)V
        method writeToNBT -> d (Labx;)V
        field entityId -> f I
        field nextEntityID -> a I
    class EntityLiving (aar.class) extends Entity
        method getEntityTexture -> M ()Ljava/lang/String;
        method readFromNBT -> e (Labx;)V
        method writeToNBT -> d (Labx;)V
        field entityId -> f I
        field nextEntityID -> a I
    class Minecraft (net/minecraft/client/Minecraft.class)
        field texturePackList -> E Lfy;
    class NBTTagCompound (abx.class)
        method getLong -> g (Ljava/lang/String;)J
        method setLong -> a (Ljava/lang/String;J)V
    class RenderEnderman (rv.class)
    class RenderLiving (ey.class)
        method doRenderLiving -> a (Laar;DDDFF)V
    class RenderSpider (ajy.class)
    class TexturePackBase (h.class)
        method getInputStream -> a (Ljava/lang/String;)Ljava/io/InputStream;
        field texturePackFileName -> a Ljava/lang/String;
    class TexturePackList (fy.class)
        field defaultTexturePack -> c Lh;
        field minecraft -> e Lnet/minecraft/client/Minecraft;
        field selectedTexturePack -> a Lh;
    class net.minecraft.client.Minecraft alias for Minecraft
    class net.minecraft.src.Entity alias for Entity
    class net.minecraft.src.EntityLiving alias for EntityLiving
    class net.minecraft.src.NBTTagCompound alias for NBTTagCompound
    class net.minecraft.src.RenderEnderman alias for RenderEnderman
    class net.minecraft.src.RenderLiving alias for RenderLiving
    class net.minecraft.src.RenderSpider alias for RenderSpider
    class net.minecraft.src.TexturePackBase alias for TexturePackBase
    class net.minecraft.src.TexturePackList alias for TexturePackList

Custom Colors
    class BiomeGenBase (zp.class)
        method getFoliageColor -> b (Laiw;III)I
        method getGrassColor -> a (Laiw;III)I
        method setBiomeName -> a (Ljava/lang/String;)Lzp;
        field biomeID -> K I
        field biomeName -> w Ljava/lang/String;
        field color -> x I
        field rainfall -> E F
        field temperature -> D F
        field waterColorMultiplier -> F I
    class BiomeGenSwamp (afp.class) extends BiomeGenBase
        method getFoliageColor -> b (Laiw;III)I
        method getGrassColor -> a (Laiw;III)I
        method setBiomeName -> a (Ljava/lang/String;)Lzp;
        field biomeID -> K I
        field biomeName -> w Ljava/lang/String;
        field color -> x I
        field rainfall -> E F
        field temperature -> D F
        field waterColorMultiplier -> F I
    class Block (oe.class)
        method colorMultiplier -> b (Laiw;III)I
        method getRenderColor -> d (I)I
        field blockID -> bO I
        field blocksList -> m [Loe;
    class BlockCauldron (vw.class) extends Block
        method colorMultiplier -> b (Laiw;III)I
        method getRenderColor -> d (I)I
        field blockID -> bO I
        field blocksList -> m [Loe;
    class BlockFluid (aes.class)
        method colorMultiplier -> b (Laiw;III)I
    class BlockLeaves (tb.class)
        method colorMultiplier -> b (Laiw;III)I
    class BlockLilyPad (wl.class)
    class BlockRedstoneWire (aff.class)
        method randomDisplayTick -> b (Lvq;IIILjava/util/Random;)V
    class BlockStem (ach.class)
        method getRenderColor -> d (I)I
    class ColorizerFoliage (gk.class)
        method getFoliageColorBirch -> b ()I
        method getFoliageColorPine -> a ()I
    class Entity (ms.class)
        method setPositionAndRotation -> b (DDDFF)V
        field posX -> o D
        field posY -> p D
        field posZ -> q D
        field prevPosX -> l D
        field prevPosY -> m D
        field prevPosZ -> n D
        field worldObj -> k Lvq;
    class EntityBubbleFX (tz.class) extends EntityFX
        method setPositionAndRotation -> b (DDDFF)V
        field particleBlue -> aq F
        field particleGreen -> ap F
        field particleRed -> ao F
        field posX -> o D
        field posY -> p D
        field posZ -> q D
        field prevPosX -> l D
        field prevPosY -> m D
        field prevPosZ -> n D
        field worldObj -> k Lvq;
    class EntityDropParticleFX (fs.class) extends EntityFX
        method onUpdate -> B_ ()V
        method setPositionAndRotation -> b (DDDFF)V
        field particleBlue -> aq F
        field particleGreen -> ap F
        field particleRed -> ao F
        field posX -> o D
        field posY -> p D
        field posZ -> q D
        field prevPosX -> l D
        field prevPosY -> m D
        field prevPosZ -> n D
        field timer -> au I
        field worldObj -> k Lvq;
    class EntityFX (qv.class) extends Entity
        method setPositionAndRotation -> b (DDDFF)V
        field particleBlue -> aq F
        field particleGreen -> ap F
        field particleRed -> ao F
        field posX -> o D
        field posY -> p D
        field posZ -> q D
        field prevPosX -> l D
        field prevPosY -> m D
        field prevPosZ -> n D
        field worldObj -> k Lvq;
    class EntityList (yr.class)
        method addMapping -> a (Ljava/lang/Class;Ljava/lang/String;I)V
        method getEntityString -> a (I)Ljava/lang/String;
    class EntityLiving (aar.class) extends Entity
        method setPositionAndRotation -> b (DDDFF)V
        field posX -> o D
        field posY -> p D
        field posZ -> q D
        field prevPosX -> l D
        field prevPosY -> m D
        field prevPosZ -> n D
        field worldObj -> k Lvq;
    class EntityRainFX (qj.class) extends EntityFX
        method setPositionAndRotation -> b (DDDFF)V
        field particleBlue -> aq F
        field particleGreen -> ap F
        field particleRed -> ao F
        field posX -> o D
        field posY -> p D
        field posZ -> q D
        field prevPosX -> l D
        field prevPosY -> m D
        field prevPosZ -> n D
        field worldObj -> k Lvq;
    class EntityReddustFX (ye.class)
    class EntityRenderer (kz.class)
        method updateFogColor -> g (F)V
        method updateLightmap -> e ()V
        field fogColorBlue -> p F
        field fogColorGreen -> o F
        field fogColorRed -> n F
        field lightmapColors -> Q [I
        field lightmapTexture -> d I
        field mc -> r Lnet/minecraft/client/Minecraft;
        field torchFlickerX -> e F
    class EntitySplashFX (nb.class) extends EntityRainFX
        method setPositionAndRotation -> b (DDDFF)V
        field particleBlue -> aq F
        field particleGreen -> ap F
        field particleRed -> ao F
        field posX -> o D
        field posY -> p D
        field posZ -> q D
        field prevPosX -> l D
        field prevPosY -> m D
        field prevPosZ -> n D
        field worldObj -> k Lvq;
    class GameSettings (hh.class)
        field gammaSetting -> N F
    class IBlockAccess (aiw.class)
        method getBlockId -> a (III)I
        method getBlockMetadata -> e (III)I
        method getWorldChunkManager -> a ()Lqu;
    class Item (ww.class)
        method getColorFromDamage -> b (II)I
    class ItemBlock (tw.class) extends Item
        method getColorFromDamage -> b (II)I
        field blockID -> a I
    class ItemRenderer (lv.class)
    class ItemSpawnerEgg (aaw.class) extends Item
        method getColorFromDamage -> b (II)I
        method getItemNameIS -> d (Lyq;)Ljava/lang/String;
    class ItemStack (yq.class)
        method getItemDamage -> i ()I
    class Minecraft (net/minecraft/client/Minecraft.class)
        field gameSettings -> A Lhh;
        field renderEngine -> p Lyz;
        field texturePackList -> E Lfy;
    class Potion (yg.class)
        method setPotionName -> a (Ljava/lang/String;)Lyg;
        field color -> N I
        field id -> H I
        field name -> I Ljava/lang/String;
    class PotionHelper (hl.class)
    class RenderBlocks (uc.class)
        method renderBlockCauldron -> a (Lvw;III)Z
        method renderBlockFallingSand -> a (Loe;Lvq;III)V
        method renderBlockFluids -> n (Loe;III)Z
        method renderBlockRedstoneWire -> g (Loe;III)Z
        field blockAccess -> a Laiw;
    class RenderEngine (yz.class)
        method createTextureFromBytes -> a ([IIII)V
    class RenderGlobal (l.class)
        method renderClouds -> b (F)V
    class Tessellator (aby.class)
        method setColorOpaque_F -> a (FFF)V
    class TexturePackBase (h.class)
        method getInputStream -> a (Ljava/lang/String;)Ljava/io/InputStream;
        field texturePackFileName -> a Ljava/lang/String;
    class TexturePackList (fy.class)
        field defaultTexturePack -> c Lh;
        field minecraft -> e Lnet/minecraft/client/Minecraft;
        field selectedTexturePack -> a Lh;
    class Vec3D (bk.class)
    class World (vq.class)
        method getSkyColor -> a (Lms;F)Lbk;
        method getSunAngle -> b (F)F
        method getWorldChunkManager -> a ()Lqu;
        field lightningFlash -> s I
        field worldProvider -> y Laip;
    class WorldChunkManager (qu.class)
        method getBiomeGenAt -> a (II)Lzp;
        method getRainfall -> b (II)F
        method getTemperature -> a (III)F
    class WorldProvider (aip.class)
        method getFogColor -> b (FF)Lbk;
        field lightBrightnessTable -> g [F
        field worldType -> h I
    class net.minecraft.client.Minecraft alias for Minecraft
    class net.minecraft.src.BiomeGenBase alias for BiomeGenBase
    class net.minecraft.src.BiomeGenSwamp alias for BiomeGenSwamp
    class net.minecraft.src.Block alias for Block
    class net.minecraft.src.BlockCauldron alias for BlockCauldron
    class net.minecraft.src.BlockFluid alias for BlockFluid
    class net.minecraft.src.BlockLeaves alias for BlockLeaves
    class net.minecraft.src.BlockLilyPad alias for BlockLilyPad
    class net.minecraft.src.BlockRedstoneWire alias for BlockRedstoneWire
    class net.minecraft.src.BlockStem alias for BlockStem
    class net.minecraft.src.ColorizerFoliage alias for ColorizerFoliage
    class net.minecraft.src.Entity alias for Entity
    class net.minecraft.src.EntityBubbleFX alias for EntityBubbleFX
    class net.minecraft.src.EntityDropParticleFX alias for EntityDropParticleFX
    class net.minecraft.src.EntityFX alias for EntityFX
    class net.minecraft.src.EntityList alias for EntityList
    class net.minecraft.src.EntityLiving alias for EntityLiving
    class net.minecraft.src.EntityRainFX alias for EntityRainFX
    class net.minecraft.src.EntityReddustFX alias for EntityReddustFX
    class net.minecraft.src.EntityRenderer alias for EntityRenderer
    class net.minecraft.src.EntitySplashFX alias for EntitySplashFX
    class net.minecraft.src.GameSettings alias for GameSettings
    class net.minecraft.src.IBlockAccess alias for IBlockAccess
    class net.minecraft.src.Item alias for Item
    class net.minecraft.src.ItemBlock alias for ItemBlock
    class net.minecraft.src.ItemRenderer alias for ItemRenderer
    class net.minecraft.src.ItemSpawnerEgg alias for ItemSpawnerEgg
    class net.minecraft.src.ItemStack alias for ItemStack
    class net.minecraft.src.Potion alias for Potion
    class net.minecraft.src.PotionHelper alias for PotionHelper
    class net.minecraft.src.RenderBlocks alias for RenderBlocks
    class net.minecraft.src.RenderEngine alias for RenderEngine
    class net.minecraft.src.RenderGlobal alias for RenderGlobal
    class net.minecraft.src.Tessellator alias for Tessellator
    class net.minecraft.src.TexturePackBase alias for TexturePackBase
    class net.minecraft.src.TexturePackList alias for TexturePackList
    class net.minecraft.src.Vec3D alias for Vec3D
    class net.minecraft.src.World alias for World
    class net.minecraft.src.WorldChunkManager alias for WorldChunkManager
    class net.minecraft.src.WorldProvider alias for WorldProvider


Patching...
 applying ItemSpawnerEgg patch to aaw.class for mod Custom Colors
    override spawner egg color b(II)I@26
     IRETURN                   ILOAD_1
                               ILOAD_2
                               INVOKESTATIC 0x00 0x8d
                               IRETURN
    override spawner egg color b(II)I@36
     IRETURN                   ILOAD_1
                               ILOAD_2
                               INVOKESTATIC 0x00 0x8d
                               IRETURN
    override spawner egg color b(II)I@44
                               ILOAD_1
                               ILOAD_2
                               INVOKESTATIC 0x00 0x8d
   increasing stack size from 2 to 3
 applying BlockStem patch to ach.class for mod Custom Colors
    override pumpkin and melon stem color d(I)I@31
                               ILOAD_1
                               INVOKESTATIC 0x00 0x9e
 applying FlowWater patch to ack.class for mod HD Textures
    array size 256 -> int_numPixels <init>()V@13
     SIPUSH 0x01 0x00          GETSTATIC 0x00 0x47
     NEWARRAY 0x06             NEWARRAY 0x06
    array size 256 -> int_numPixels <init>()V@22
     SIPUSH 0x01 0x00          GETSTATIC 0x00 0x47
     NEWARRAY 0x06             NEWARRAY 0x06
    array size 256 -> int_numPixels <init>()V@31
     SIPUSH 0x01 0x00          GETSTATIC 0x00 0x47
     NEWARRAY 0x06             NEWARRAY 0x06
    array size 256 -> int_numPixels <init>()V@40
     SIPUSH 0x01 0x00          GETSTATIC 0x00 0x47
     NEWARRAY 0x06             NEWARRAY 0x06
    while i < 256 -> int_numPixels a()V@260
     SIPUSH 0x01 0x00          GETSTATIC 0x00 0x47
     IF_ICMPGE 0x00 0xd4       IF_ICMPGE 0x00 0xd4
    while i < 16 -> int_size a()V@13
     BIPUSH 0x10               GETSTATIC 0x00 0x4a
     IF_ICMPGE 0x00 0x65       IF_ICMPGE 0x00 0x65
    while i < 16 -> int_size a()V@22
     BIPUSH 0x10               GETSTATIC 0x00 0x4a
     IF_ICMPGE 0x00 0x57       IF_ICMPGE 0x00 0x57
    while i < 16 -> int_size a()V@121
     BIPUSH 0x10               GETSTATIC 0x00 0x4a
     IF_ICMPGE 0x00 0x76       IF_ICMPGE 0x00 0x76
    while i < 16 -> int_size a()V@130
     BIPUSH 0x10               GETSTATIC 0x00 0x4a
     IF_ICMPGE 0x00 0x68       IF_ICMPGE 0x00 0x68
    & 255 -> int_numPixelsMinus1 a()V@283
     SIPUSH 0x00 0xff          GETSTATIC 0x00 0x4d
     IAND                      IAND
    & 15 -> int_sizeMinus1 a()V@42
     BIPUSH 0x0f               GETSTATIC 0x00 0x50
     IAND                      IAND
    & 15 -> int_sizeMinus1 a()V@50
     BIPUSH 0x0f               GETSTATIC 0x00 0x50
     IAND                      IAND
    * 16 -> int_size a()V@65
     BIPUSH 0x10               GETSTATIC 0x00 0x4a
     IMUL                      IMUL
    * 16 -> int_size a()V@85
     BIPUSH 0x10               GETSTATIC 0x00 0x4a
     IMUL                      IMUL
    * 16 -> int_size a()V@100
     BIPUSH 0x10               GETSTATIC 0x00 0x4a
     IMUL                      IMUL
    * 16 -> int_size a()V@147
     BIPUSH 0x10               GETSTATIC 0x00 0x4a
     IMUL                      IMUL
    * 16 -> int_size a()V@160
     BIPUSH 0x10               GETSTATIC 0x00 0x4a
     IMUL                      IMUL
    * 16 -> int_size a()V@177
     BIPUSH 0x10               GETSTATIC 0x00 0x4a
     IMUL                      IMUL
    * 16 -> int_size a()V@194
     BIPUSH 0x10               GETSTATIC 0x00 0x4a
     IMUL                      IMUL
    * 16 -> int_size a()V@207
     BIPUSH 0x10               GETSTATIC 0x00 0x4a
     IMUL                      IMUL
    * 16 -> int_size a()V@234
     BIPUSH 0x10               GETSTATIC 0x00 0x4a
     IMUL                      IMUL
    * 16 -> int_size a()V@290
     BIPUSH 0x10               GETSTATIC 0x00 0x4a
     IMUL                      IMUL
 applying BlockFluid patch to aes.class for mod Custom Colors
    override water color b(Laiw;III)I@52
     INVOKEVIRTUAL 0x00 0x4d   NOP
     GETFIELD 0x00 0x38        NOP
                               NOP
                               INVOKESTATIC 0x00 0xe9
 applying BlockRedstoneWire patch to aff.class for mod Custom Colors
    override redstone wire particle color b(Lvq;IIILjava/util/Random;)V@70
     label A -> instruction 96
     label B -> instruction 148
     branch offset IFEQ A -> +21 @75
     branch offset GOTO B -> +55 @93
     ILOAD 0x06                ILOAD 0x06
     I2F                       INVOKESTATIC 0x00 0xd6
     LDC 0x07                  IFEQ 0x00 0x15
     FDIV                      GETSTATIC 0x00 0xda
     FSTORE 0x0d               FSTORE 0x0e
     FLOAD 0x0d                GETSTATIC 0x00 0xdd
     LDC 0x05                  FSTORE 0x0f
     FMUL                      GETSTATIC 0x00 0xe0
     LDC 0x03                  FSTORE 0x10
     FADD                      GOTO 0x00 0x37
     FSTORE 0x0e               ILOAD 0x06
     ILOAD 0x06                I2F
     IFNE 0x00 0x06            LDC 0x07
     FCONST_0                  FDIV
     FSTORE 0x0e               FSTORE 0x0d
     FLOAD 0x0d                FLOAD 0x0d
     FLOAD 0x0d                LDC 0x05
     FMUL                      FMUL
     LDC 0x06                  LDC 0x03
     FMUL                      FADD
     LDC 0x04                  FSTORE 0x0e
     FSUB                      ILOAD 0x06
     FSTORE 0x0f               IFNE 0x00 0x06
     FLOAD 0x0d                FCONST_0
     FLOAD 0x0d                FSTORE 0x0e
     FMUL                      FLOAD 0x0d
     LDC 0x05                  FLOAD 0x0d
     FMUL                      FMUL
     LDC 0x06                  LDC 0x06
     FSUB                      FMUL
     FSTORE 0x10               LDC 0x04
                               FSUB
                               FSTORE 0x0f
                               FLOAD 0x0d
                               FLOAD 0x0d
                               FMUL
                               LDC 0x05
                               FMUL
                               LDC 0x06
                               FSUB
                               FSTORE 0x10
 applying BiomeGenSwamp patch to afp.class for mod Custom Colors
    override swamp grass color a(Laiw;III)I@38
     LDC 0x03                  LDC 0x03
     IAND                      IAND
     LDC 0x01                  LDC 0x01
     IADD                      IADD
     ICONST_2                  ICONST_2
     IDIV                      IDIV
                               GETSTATIC 0x00 0x4e
                               DLOAD 0x05
                               DLOAD 0x07
                               INVOKESTATIC 0x00 0x52
   increasing stack size from 4 to 6
    override swamp foliage color b(Laiw;III)I@38
     LDC 0x03                  LDC 0x03
     IAND                      IAND
     LDC 0x01                  LDC 0x01
     IADD                      IADD
     ICONST_2                  ICONST_2
     IDIV                      IDIV
                               GETSTATIC 0x00 0x55
                               DLOAD 0x05
                               DLOAD 0x07
                               INVOKESTATIC 0x00 0x52
   increasing stack size from 4 to 6
 applying GetResource patch to agr.class for mod HD Textures
    ImageIO.read(getResource(...)) -> getResourceAsBufferedImage(...) <init>()V@66
     LDC 0x0e                  NOP
     LDC 0x0b                  NOP
     INVOKEVIRTUAL 0x00 0x30   NOP
     INVOKESTATIC 0x00 0x33    NOP
                               NOP
                               LDC 0x0b
                               INVOKESTATIC 0x00 0x9a
 applying TexturePackCustom patch to ahk.class for mod HD Textures
    make field zipFile public
    make field file public
    insert field origZip Ljava/util/zip/ZipFile;
    insert field tmpFile Ljava/io/File;
    insert field lastModified J
    openTexturePackFile(this) a()V@19
                               ALOAD_0
                               INVOKESTATIC 0x00 0x9a
    closeTexturePackFile(this) b()V@0
                               ALOAD_0
                               INVOKESTATIC 0x00 0x9d
 applying GetResource patch to ahk.class for mod HD Textures
 applying WorldProvider patch to aip.class for mod Custom Colors
    override fog color b(FF)Lbk;@31
     label A -> instruction 64
     label B -> instruction 75
     branch offset IFEQ A -> +27 @37
     branch offset GOTO B -> +14 @61
     LDC 0x0a                  GETSTATIC 0x00 0xb3
     FSTORE 0x04               INVOKESTATIC 0x00 0xb7
     LDC 0x0b                  IFEQ 0x00 0x1b
     FSTORE 0x05               GETSTATIC 0x00 0xba
     FCONST_1                  ICONST_0
     FSTORE 0x06               FALOAD
                               FSTORE 0x04
                               GETSTATIC 0x00 0xba
                               ICONST_1
                               FALOAD
                               FSTORE 0x05
                               GETSTATIC 0x00 0xba
                               ICONST_2
                               FALOAD
                               FSTORE 0x06
                               GOTO 0x00 0x0e
                               LDC 0x0a
                               FSTORE 0x04
                               LDC 0x0b
                               FSTORE 0x05
                               FCONST_1
                               FSTORE 0x06
 applying BlockMycelium patch to aje.class for mod Better Grass
    insert field grassMatrix [[I
    initialize grassMatrix <init>(I)V@20
     label A -> instruction 68
     branch offset IF_ACMPNE A -> +44 @24
                               GETSTATIC 0x00 0x5e
                               ACONST_NULL
                               IF_ACMPNE 0x00 0x2c
                               ICONST_4
                               ICONST_2
                               MULTIANEWARRAY 0x00 0x5f 0x02
                               PUTSTATIC 0x00 0x5e
                               GETSTATIC 0x00 0x5e
                               ICONST_0
                               AALOAD
                               ICONST_1
                               ICONST_M1
                               IASTORE
                               GETSTATIC 0x00 0x5e
                               ICONST_1
                               AALOAD
                               ICONST_1
                               ICONST_1
                               IASTORE
                               GETSTATIC 0x00 0x5e
                               ICONST_2
                               AALOAD
                               ICONST_0
                               ICONST_M1
                               IASTORE
                               GETSTATIC 0x00 0x5e
                               ICONST_3
                               AALOAD
                               ICONST_0
                               ICONST_1
                               IASTORE
    check surrounding blocks in getBlockTexture d(Laiw;IIII)I@30
     label A -> instruction 93
     label B -> instruction 90
     label C -> instruction 145
     branch offset IF_ACMPEQ A -> +55 @38
     branch offset IF_ACMPEQ A -> +47 @46
     branch offset IF_ICMPEQ B -> +6 @84
     branch offset IF_ACMPEQ C -> +14 @131
     branch offset IF_ACMPEQ C -> +6 @139
     ALOAD 0x06                IINC 0x05 0xfe
     GETSTATIC 0x00 0x0a       ALOAD 0x06
     IF_ACMPEQ 0x00 0x0b       GETSTATIC 0x00 0x0a
     ALOAD 0x06                IF_ACMPEQ 0x00 0x37
     GETSTATIC 0x00 0x0b       ALOAD 0x06
     IF_ACMPNE 0x00 0x06       GETSTATIC 0x00 0x0b
     BIPUSH 0x44               IF_ACMPEQ 0x00 0x2f
     IRETURN                   ALOAD 0x01
     BIPUSH 0x4d               ILOAD 0x02
                               GETSTATIC 0x00 0x64
                               ILOAD 0x05
                               AALOAD
                               ICONST_0
                               IALOAD
                               IADD
                               ILOAD 0x03
                               ICONST_1
                               ISUB
                               ILOAD 0x04
                               GETSTATIC 0x00 0x64
                               ILOAD 0x05
                               AALOAD
                               ICONST_1
                               IALOAD
                               IADD
                               INVOKEINTERFACE 0x00 0x61 0x04 0x00
                               BIPUSH 0x6e
                               IF_ICMPEQ 0x00 0x06
                               BIPUSH 0x4d
                               IRETURN
                               BIPUSH 0x4e
                               IRETURN
                               ALOAD 0x01
                               ILOAD 0x02
                               GETSTATIC 0x00 0x64
                               ILOAD 0x05
                               AALOAD
                               ICONST_0
                               IALOAD
                               IADD
                               ILOAD 0x03
                               ILOAD 0x04
                               GETSTATIC 0x00 0x64
                               ILOAD 0x05
                               AALOAD
                               ICONST_1
                               IALOAD
                               IADD
                               INVOKEINTERFACE 0x00 0x1c 0x04 0x00
                               ASTORE 0x06
                               ALOAD 0x06
                               GETSTATIC 0x00 0x0a
                               IF_ACMPEQ 0x00 0x0e
                               ALOAD 0x06
                               GETSTATIC 0x00 0x0b
                               IF_ACMPEQ 0x00 0x06
                               BIPUSH 0x44
                               IRETURN
                               BIPUSH 0x42
   increasing stack size from 4 to 6
 applying RenderSpider patch to ajy.class for mod Random Mobs
    override spider eye texture a(Lbv;IF)I@7
     LDC 0x04                  ALOAD_1
                               LDC 0x04
                               INVOKESTATIC 0x00 0x52
 applying StillLava patch to bo.class for mod HD Textures
    array size 256 -> int_numPixels <init>()V@11
     SIPUSH 0x01 0x00          GETSTATIC 0x00 0x4a
     NEWARRAY 0x06             NEWARRAY 0x06
    array size 256 -> int_numPixels <init>()V@20
     SIPUSH 0x01 0x00          GETSTATIC 0x00 0x4a
     NEWARRAY 0x06             NEWARRAY 0x06
    array size 256 -> int_numPixels <init>()V@29
     SIPUSH 0x01 0x00          GETSTATIC 0x00 0x4a
     NEWARRAY 0x06             NEWARRAY 0x06
    array size 256 -> int_numPixels <init>()V@38
     SIPUSH 0x01 0x00          GETSTATIC 0x00 0x4a
     NEWARRAY 0x06             NEWARRAY 0x06
    while i < 256 -> int_numPixels a()V@367
     SIPUSH 0x01 0x00          GETSTATIC 0x00 0x4a
     IF_ICMPGE 0x00 0xc7       IF_ICMPGE 0x00 0xc7
    while i < 16 -> int_size a()V@3
     BIPUSH 0x10               GETSTATIC 0x00 0x4d
     IF_ICMPGE 0x01 0x55       IF_ICMPGE 0x01 0x55
    while i < 16 -> int_size a()V@12
     BIPUSH 0x10               GETSTATIC 0x00 0x4d
     IF_ICMPGE 0x01 0x47       IF_ICMPGE 0x01 0x47
    & 15 -> int_sizeMinus1 a()V@89
     BIPUSH 0x0f               GETSTATIC 0x00 0x50
     IAND                      IAND
    & 15 -> int_sizeMinus1 a()V@100
     BIPUSH 0x0f               GETSTATIC 0x00 0x50
     IAND                      IAND
    & 15 -> int_sizeMinus1 a()V@155
     BIPUSH 0x0f               GETSTATIC 0x00 0x50
     IAND                      IAND
    & 15 -> int_sizeMinus1 a()V@162
     BIPUSH 0x0f               GETSTATIC 0x00 0x50
     IAND                      IAND
    & 15 -> int_sizeMinus1 a()V@178
     BIPUSH 0x0f               GETSTATIC 0x00 0x50
     IAND                      IAND
    & 15 -> int_sizeMinus1 a()V@185
     BIPUSH 0x0f               GETSTATIC 0x00 0x50
     IAND                      IAND
    & 15 -> int_sizeMinus1 a()V@202
     BIPUSH 0x0f               GETSTATIC 0x00 0x50
     IAND                      IAND
    & 15 -> int_sizeMinus1 a()V@209
     BIPUSH 0x0f               GETSTATIC 0x00 0x50
     IAND                      IAND
    & 15 -> int_sizeMinus1 a()V@226
     BIPUSH 0x0f               GETSTATIC 0x00 0x50
     IAND                      IAND
    & 15 -> int_sizeMinus1 a()V@233
     BIPUSH 0x0f               GETSTATIC 0x00 0x50
     IAND                      IAND
    * 16 -> int_size a()V@115
     BIPUSH 0x10               GETSTATIC 0x00 0x4d
     IMUL                      IMUL
    * 16 -> int_size a()V@141
     BIPUSH 0x10               GETSTATIC 0x00 0x4d
     IMUL                      IMUL
    * 16 -> int_size a()V@168
     BIPUSH 0x10               GETSTATIC 0x00 0x4d
     IMUL                      IMUL
    * 16 -> int_size a()V@192
     BIPUSH 0x10               GETSTATIC 0x00 0x4d
     IMUL                      IMUL
    * 16 -> int_size a()V@217
     BIPUSH 0x10               GETSTATIC 0x00 0x4d
     IMUL                      IMUL
    * 16 -> int_size a()V@242
     BIPUSH 0x10               GETSTATIC 0x00 0x4d
     IMUL                      IMUL
    * 16 -> int_size a()V@263
     BIPUSH 0x10               GETSTATIC 0x00 0x4d
     IMUL                      IMUL
    * 16 -> int_size a()V@276
     BIPUSH 0x10               GETSTATIC 0x00 0x4d
     IMUL                      IMUL
    * 16 -> int_size a()V@293
     BIPUSH 0x10               GETSTATIC 0x00 0x4d
     IMUL                      IMUL
    * 16 -> int_size a()V@310
     BIPUSH 0x10               GETSTATIC 0x00 0x4d
     IMUL                      IMUL
    * 16 -> int_size a()V@323
     BIPUSH 0x10               GETSTATIC 0x00 0x4d
     IMUL                      IMUL
    * 16 -> int_size a()V@350
     BIPUSH 0x10               GETSTATIC 0x00 0x4d
     IMUL                      IMUL
 applying GetResource patch to ei.class for mod HD Textures
    ImageIO.read(getResource(...)) -> getResourceAsBufferedImage(...) <init>()V@5
     LDC 0x0a                  NOP
     LDC 0x01                  NOP
     INVOKEVIRTUAL 0x00 0x14   NOP
     INVOKESTATIC 0x00 0x15    NOP
                               NOP
                               LDC 0x01
                               INVOKESTATIC 0x00 0x4b
 applying RenderLiving patch to ey.class for mod Random Mobs
    replace mob textures a(Laar;FFFFFF)V@5
     ALOAD_1                   ALOAD_1
     INVOKEVIRTUAL 0x00 0x42   INVOKESTATIC 0x01 0x28
 applying EntityDropParticleFX patch to fs.class for mod Custom Colors
    override water drop color <init>(Lvq;DDDLaan;)V@36
     label A -> instruction 91
     label B -> instruction 108
     branch offset IFEQ A -> +33 @58
     branch offset GOTO B -> +20 @88
     ALOAD_0                   ALOAD_0
     FCONST_0                  GETFIELD 0x00 0x23
     PUTFIELD 0x00 0x1e        INVOKEVIRTUAL 0x00 0x9f
     ALOAD_0                   ALOAD_0
     FCONST_0                  GETFIELD 0x00 0x27
     PUTFIELD 0x00 0x1f        ALOAD_0
     ALOAD_0                   GETFIELD 0x00 0x28
     FCONST_1                  ALOAD_0
     PUTFIELD 0x00 0x20        GETFIELD 0x00 0x29
                               INVOKESTATIC 0x00 0xa5
                               IFEQ 0x00 0x21
                               ALOAD_0
                               GETSTATIC 0x00 0xa9
                               ICONST_0
                               FALOAD
                               PUTFIELD 0x00 0x1e
                               ALOAD_0
                               GETSTATIC 0x00 0xa9
                               ICONST_1
                               FALOAD
                               PUTFIELD 0x00 0x1f
                               ALOAD_0
                               GETSTATIC 0x00 0xa9
                               ICONST_2
                               FALOAD
                               PUTFIELD 0x00 0x20
                               GOTO 0x00 0x14
                               ALOAD_0
                               LDC 0x03
                               PUTFIELD 0x00 0x1e
                               ALOAD_0
                               LDC 0x04
                               PUTFIELD 0x00 0x1f
                               ALOAD_0
                               FCONST_1
                               PUTFIELD 0x00 0x20
    remove water drop color update B_()V@34
     ALOAD_0                   NOP
     LDC 0x03                  NOP
     PUTFIELD 0x00 0x1e        NOP
     ALOAD_0                   NOP
     LDC 0x04                  NOP
     PUTFIELD 0x00 0x1f        NOP
     ALOAD_0                   NOP
     FCONST_1                  NOP
     PUTFIELD 0x00 0x20        NOP
                               NOP
                               NOP
                               NOP
                               NOP
                               NOP
                               NOP
                               NOP
                               NOP
    override lava drop color B_()V@54
     label A -> instruction 91
     label B -> instruction 132
     branch offset IFEQ A -> +27 @64
     branch offset GOTO B -> +44 @88
     ALOAD_0                   BIPUSH 0x28
     FCONST_1                  ALOAD_0
     PUTFIELD 0x00 0x1e        GETFIELD 0x00 0x21
     ALOAD_0                   ISUB
     LDC 0x06                  INVOKESTATIC 0x00 0xad
     BIPUSH 0x28               IFEQ 0x00 0x1b
     ALOAD_0                   ALOAD_0
     GETFIELD 0x00 0x21        GETSTATIC 0x00 0xb0
     ISUB                      PUTFIELD 0x00 0x1e
     BIPUSH 0x10               ALOAD_0
     IADD                      GETSTATIC 0x00 0xb3
     I2F                       PUTFIELD 0x00 0x1f
     FDIV                      ALOAD_0
     PUTFIELD 0x00 0x1f        GETSTATIC 0x00 0xb6
     ALOAD_0                   PUTFIELD 0x00 0x20
     LDC 0x05                  GOTO 0x00 0x2c
     BIPUSH 0x28               ALOAD_0
     ALOAD_0                   FCONST_1
     GETFIELD 0x00 0x21        PUTFIELD 0x00 0x1e
     ISUB                      ALOAD_0
     BIPUSH 0x08               LDC 0x06
     IADD                      BIPUSH 0x28
     I2F                       ALOAD_0
     FDIV                      GETFIELD 0x00 0x21
     PUTFIELD 0x00 0x20        ISUB
                               BIPUSH 0x10
                               IADD
                               I2F
                               FDIV
                               PUTFIELD 0x00 0x1f
                               ALOAD_0
                               LDC 0x05
                               BIPUSH 0x28
                               ALOAD_0
                               GETFIELD 0x00 0x21
                               ISUB
                               BIPUSH 0x08
                               IADD
                               I2F
                               FDIV
                               PUTFIELD 0x00 0x20
 applying FlowLava patch to fv.class for mod HD Textures
    array size 256 -> int_numPixels <init>()V@13
     SIPUSH 0x01 0x00          GETSTATIC 0x00 0x50
     NEWARRAY 0x06             NEWARRAY 0x06
    array size 256 -> int_numPixels <init>()V@22
     SIPUSH 0x01 0x00          GETSTATIC 0x00 0x50
     NEWARRAY 0x06             NEWARRAY 0x06
    array size 256 -> int_numPixels <init>()V@31
     SIPUSH 0x01 0x00          GETSTATIC 0x00 0x50
     NEWARRAY 0x06             NEWARRAY 0x06
    array size 256 -> int_numPixels <init>()V@40
     SIPUSH 0x01 0x00          GETSTATIC 0x00 0x50
     NEWARRAY 0x06             NEWARRAY 0x06
    while i < 256 -> int_numPixels a()V@377
     SIPUSH 0x01 0x00          GETSTATIC 0x00 0x50
     IF_ICMPGE 0x00 0xd5       IF_ICMPGE 0x00 0xd5
    while i < 16 -> int_size a()V@13
     BIPUSH 0x10               GETSTATIC 0x00 0x53
     IF_ICMPGE 0x01 0x55       IF_ICMPGE 0x01 0x55
    while i < 16 -> int_size a()V@22
     BIPUSH 0x10               GETSTATIC 0x00 0x53
     IF_ICMPGE 0x01 0x47       IF_ICMPGE 0x01 0x47
    & 255 -> int_numPixelsMinus1 a()V@400
     SIPUSH 0x00 0xff          GETSTATIC 0x00 0x56
     IAND                      IAND
    & 15 -> int_sizeMinus1 a()V@99
     BIPUSH 0x0f               GETSTATIC 0x00 0x59
     IAND                      IAND
    & 15 -> int_sizeMinus1 a()V@110
     BIPUSH 0x0f               GETSTATIC 0x00 0x59
     IAND                      IAND
    & 15 -> int_sizeMinus1 a()V@165
     BIPUSH 0x0f               GETSTATIC 0x00 0x59
     IAND                      IAND
    & 15 -> int_sizeMinus1 a()V@172
     BIPUSH 0x0f               GETSTATIC 0x00 0x59
     IAND                      IAND
    & 15 -> int_sizeMinus1 a()V@188
     BIPUSH 0x0f               GETSTATIC 0x00 0x59
     IAND                      IAND
    & 15 -> int_sizeMinus1 a()V@195
     BIPUSH 0x0f               GETSTATIC 0x00 0x59
     IAND                      IAND
    & 15 -> int_sizeMinus1 a()V@212
     BIPUSH 0x0f               GETSTATIC 0x00 0x59
     IAND                      IAND
    & 15 -> int_sizeMinus1 a()V@219
     BIPUSH 0x0f               GETSTATIC 0x00 0x59
     IAND                      IAND
    & 15 -> int_sizeMinus1 a()V@236
     BIPUSH 0x0f               GETSTATIC 0x00 0x59
     IAND                      IAND
    & 15 -> int_sizeMinus1 a()V@243
     BIPUSH 0x0f               GETSTATIC 0x00 0x59
     IAND                      IAND
    * 16 -> int_size a()V@125
     BIPUSH 0x10               GETSTATIC 0x00 0x53
     IMUL                      IMUL
    * 16 -> int_size a()V@151
     BIPUSH 0x10               GETSTATIC 0x00 0x53
     IMUL                      IMUL
    * 16 -> int_size a()V@178
     BIPUSH 0x10               GETSTATIC 0x00 0x53
     IMUL                      IMUL
    * 16 -> int_size a()V@202
     BIPUSH 0x10               GETSTATIC 0x00 0x53
     IMUL                      IMUL
    * 16 -> int_size a()V@227
     BIPUSH 0x10               GETSTATIC 0x00 0x53
     IMUL                      IMUL
    * 16 -> int_size a()V@252
     BIPUSH 0x10               GETSTATIC 0x00 0x53
     IMUL                      IMUL
    * 16 -> int_size a()V@273
     BIPUSH 0x10               GETSTATIC 0x00 0x53
     IMUL                      IMUL
    * 16 -> int_size a()V@286
     BIPUSH 0x10               GETSTATIC 0x00 0x53
     IMUL                      IMUL
    * 16 -> int_size a()V@303
     BIPUSH 0x10               GETSTATIC 0x00 0x53
     IMUL                      IMUL
    * 16 -> int_size a()V@320
     BIPUSH 0x10               GETSTATIC 0x00 0x53
     IMUL                      IMUL
    * 16 -> int_size a()V@333
     BIPUSH 0x10               GETSTATIC 0x00 0x53
     IMUL                      IMUL
    * 16 -> int_size a()V@360
     BIPUSH 0x10               GETSTATIC 0x00 0x53
     IMUL                      IMUL
    * 16 -> int_size a()V@418
     BIPUSH 0x10               GETSTATIC 0x00 0x53
     IMUL                      IMUL
 applying TexturePackList patch to fy.class for mod HD Textures
    make field defaultTexturePack public
    TexturePackList.setTileSize(selectedTexturePack) on texture pack change a(Lh;)Z@54
     ALOAD_0                   ALOAD_0
     GETFIELD 0x00 0x14        GETFIELD 0x00 0x14
     INVOKEVIRTUAL 0x00 0x21   INVOKEVIRTUAL 0x00 0x21
     ICONST_1                  INVOKESTATIC 0x00 0xc7
                               POP
                               ALOAD_0
                               GETFIELD 0x00 0x18
                               DUP
                               GETFIELD 0x00 0xcb
                               SWAP
                               INVOKEVIRTUAL 0x00 0xcf
                               INVOKESTATIC 0x00 0xd2
                               ICONST_1
 applying ColorizerFoliage patch to gk.class for mod HD Textures
    make field colorBuffer public
 applying ColorizerFoliage patch to gk.class for mod Custom Colors
    override default pine foliage color a()I@0
     LDC 0x03                  LDC 0x03
                               GETSTATIC 0x00 0x21
                               INVOKESTATIC 0x00 0x25
   increasing stack size from 1 to 2
    override default birch foliage color b()I@0
     LDC 0x04                  LDC 0x04
                               GETSTATIC 0x00 0x28
                               INVOKESTATIC 0x00 0x25
   increasing stack size from 1 to 2
    override default basic foliage color c()I@0
     LDC 0x02                  LDC 0x02
                               GETSTATIC 0x00 0x2b
                               INVOKESTATIC 0x00 0x25
   increasing stack size from 1 to 2
 applying Watch patch to hg.class for mod HD Textures
    16.0D -> double_size a()V@332
     LDC2_W 0x00 0x23          GETSTATIC 0x00 0x90
    16.0D -> double_size a()V@354
     LDC2_W 0x00 0x23          GETSTATIC 0x00 0x90
    15.0D -> double_sizeMinus1 a()V@286
     LDC2_W 0x00 0x21          GETSTATIC 0x00 0x93
    15.0D -> double_sizeMinus1 a()V@303
     LDC2_W 0x00 0x21          GETSTATIC 0x00 0x93
    getRGB(...16,16,...16) -> getRGB(...int_size,int_size,...int_size) <init>(Lnet/minecraft/client/Minecraft;)V@77
     BIPUSH 0x10               GETSTATIC 0x00 0x96
     BIPUSH 0x10               GETSTATIC 0x00 0x96
     ALOAD_0                   ALOAD_0
     GETFIELD 0x00 0x27        GETFIELD 0x00 0x27
     ICONST_0                  ICONST_0
     BIPUSH 0x10               GETSTATIC 0x00 0x96
    getRGB(...16,16,...16) -> getRGB(...int_size,int_size,...int_size) <init>(Lnet/minecraft/client/Minecraft;)V@109
     BIPUSH 0x10               GETSTATIC 0x00 0x96
     BIPUSH 0x10               GETSTATIC 0x00 0x96
     ALOAD_0                   ALOAD_0
     GETFIELD 0x00 0x28        GETFIELD 0x00 0x28
     ICONST_0                  ICONST_0
     BIPUSH 0x10               GETSTATIC 0x00 0x96
    array size 256 -> int_numPixels <init>(Lnet/minecraft/client/Minecraft;)V@12
     SIPUSH 0x01 0x00          GETSTATIC 0x00 0x99
     NEWARRAY 0x0a             NEWARRAY 0x0a
    array size 256 -> int_numPixels <init>(Lnet/minecraft/client/Minecraft;)V@21
     SIPUSH 0x01 0x00          GETSTATIC 0x00 0x99
     NEWARRAY 0x0a             NEWARRAY 0x0a
    * 16 -> int_size <init>(Lnet/minecraft/client/Minecraft;)V@57
     BIPUSH 0x10               GETSTATIC 0x00 0x96
     IMUL                      IMUL
    * 16 -> int_size <init>(Lnet/minecraft/client/Minecraft;)V@69
     BIPUSH 0x10               GETSTATIC 0x00 0x96
     IMUL                      IMUL
    * 16 -> int_size a()V@371
     BIPUSH 0x10               GETSTATIC 0x00 0x96
     IMUL                      IMUL
    while i < 256 -> int_numPixels a()V@194
     SIPUSH 0x01 0x00          GETSTATIC 0x00 0x99
     IF_ICMPGE 0x01 0x90       IF_ICMPGE 0x01 0x90
    & 15 -> int_sizeMinus1 a()V@363
     BIPUSH 0x0f               GETSTATIC 0x00 0x9c
     IAND                      IAND
    & 15 -> int_sizeMinus1 a()V@369
     BIPUSH 0x0f               GETSTATIC 0x00 0x9c
     IAND                      IAND
    / 16 -> int_size a()V@299
     BIPUSH 0x10               GETSTATIC 0x00 0x96
     IDIV                      IDIV
     I2D                       I2D
    % 16 -> int_size a()V@282
     BIPUSH 0x10               GETSTATIC 0x00 0x96
     IREM                      IREM
 applying GetResource patch to hg.class for mod HD Textures
    ImageIO.read(getResource(...)) -> getResourceAsBufferedImage(...) <init>(Lnet/minecraft/client/Minecraft;)V@39
     LDC 0x0b                  NOP
     LDC 0x02                  NOP
     INVOKEVIRTUAL 0x00 0x35   NOP
     INVOKESTATIC 0x00 0x39    NOP
                               NOP
                               LDC 0x02
                               INVOKESTATIC 0x00 0xa9
    ImageIO.read(getResource(...)) -> getResourceAsBufferedImage(...) <init>(Lnet/minecraft/client/Minecraft;)V@97
     LDC 0x0b                  NOP
     LDC 0x03                  NOP
     INVOKEVIRTUAL 0x00 0x35   NOP
     INVOKESTATIC 0x00 0x39    NOP
                               NOP
                               LDC 0x03
                               INVOKESTATIC 0x00 0xa9
 applying PotionHelper patch to hl.class for mod Custom Colors
    override water bottle color a(Ljava/util/Collection;)I@0
     LDC 0x01                  INVOKESTATIC 0x01 0x46
     ISTORE_1                  ISTORE_1
 applying GetResource patch to kl.class for mod HD Textures
    ImageIO.read(getResource(...)) -> getResourceAsBufferedImage(...) <init>()V@22
     LDC 0x09                  NOP
     LDC 0x02                  NOP
     INVOKEVIRTUAL 0x00 0x14   NOP
     INVOKESTATIC 0x00 0x15    NOP
                               NOP
                               LDC 0x02
                               INVOKESTATIC 0x00 0x5b
 applying EntityRenderer patch to kz.class for mod Custom Colors
    make field torchFlickerX public
    override lightmap e()V@7
     label A -> instruction 17
     branch offset IFEQ A -> +4 @13
     ASTORE_1                  ASTORE_1
                               ALOAD_0
                               ALOAD_1
                               INVOKESTATIC 0x04 0x77
                               IFEQ 0x00 0x04
                               RETURN
    override fog color g(F)V@33
     label A -> instruction 77
     branch offset IFEQ A -> +30 @47
     FCONST_1                  ALOAD_2
     FLOAD 0x04                INVOKEVIRTUAL 0x01 0xe2
     F2D                       ALOAD_3
     LDC2_W 0x00 0x9f          INVOKESTATIC 0x04 0x7b
     INVOKESTATIC 0x01 0x76    GETSTATIC 0x04 0x7e
     D2F                       INVOKESTATIC 0x04 0x82
     FSUB                      IFEQ 0x00 0x1e
     FSTORE 0x04               ALOAD_0
     ALOAD_2                   GETSTATIC 0x04 0x85
     ALOAD_0                   ICONST_0
     GETFIELD 0x01 0x14        FALOAD
     GETFIELD 0x01 0x27        PUTFIELD 0x01 0x10
     FLOAD_1                   ALOAD_0
     INVOKEVIRTUAL 0x01 0xe6   GETSTATIC 0x04 0x85
     ASTORE 0x05               ICONST_1
     ALOAD 0x05                FALOAD
     GETFIELD 0x00 0xd0        PUTFIELD 0x01 0x11
     D2F                       ALOAD_0
     FSTORE 0x06               GETSTATIC 0x04 0x85
     ALOAD 0x05                ICONST_2
     GETFIELD 0x00 0xd1        FALOAD
     D2F                       PUTFIELD 0x01 0x12
     FSTORE 0x07               FCONST_1
     ALOAD 0x05                FLOAD 0x04
     GETFIELD 0x00 0xd2        F2D
     D2F                       LDC2_W 0x00 0x9f
     FSTORE 0x08               INVOKESTATIC 0x01 0x76
     ALOAD_2                   D2F
     FLOAD_1                   FSUB
     INVOKEVIRTUAL 0x01 0xf0   FSTORE 0x04
     ASTORE 0x09               ALOAD_2
     ALOAD_0                   ALOAD_0
     ALOAD 0x09                GETFIELD 0x01 0x14
     GETFIELD 0x00 0xd0        GETFIELD 0x01 0x27
     D2F                       FLOAD_1
     PUTFIELD 0x01 0x10        INVOKEVIRTUAL 0x01 0xe6
     ALOAD_0                   ASTORE 0x05
     ALOAD 0x09                ALOAD 0x05
     GETFIELD 0x00 0xd1        GETFIELD 0x00 0xd0
     D2F                       D2F
     PUTFIELD 0x01 0x11        FSTORE 0x06
     ALOAD_0                   ALOAD 0x05
     ALOAD 0x09                GETFIELD 0x00 0xd1
     GETFIELD 0x00 0xd2        D2F
     D2F                       FSTORE 0x07
     PUTFIELD 0x01 0x12        ALOAD 0x05
                               GETFIELD 0x00 0xd2
                               D2F
                               FSTORE 0x08
                               ALOAD_2
                               FLOAD_1
                               INVOKEVIRTUAL 0x01 0xf0
                               ASTORE 0x09
                               ALOAD_0
                               ALOAD 0x09
                               GETFIELD 0x00 0xd0
                               D2F
                               PUTFIELD 0x01 0x10
                               ALOAD_0
                               ALOAD 0x09
                               GETFIELD 0x00 0xd1
                               D2F
                               PUTFIELD 0x01 0x11
                               ALOAD_0
                               ALOAD 0x09
                               GETFIELD 0x00 0xd2
                               D2F
                               PUTFIELD 0x01 0x12
    override underwater ambient color g(F)V@593
     label A -> instruction 629
     branch offset IFEQ A -> +30 @599
     ALOAD_0                   ALOAD_0
     LDC 0x0f                  LDC 0x0f
     PUTFIELD 0x01 0x10        PUTFIELD 0x01 0x10
     ALOAD_0                   ALOAD_0
     LDC 0x0f                  LDC 0x0f
     PUTFIELD 0x01 0x11        PUTFIELD 0x01 0x11
     ALOAD_0                   ALOAD_0
     LDC 0x16                  LDC 0x16
     PUTFIELD 0x01 0x12        PUTFIELD 0x01 0x12
                               GETSTATIC 0x04 0x88
                               INVOKESTATIC 0x04 0x82
                               IFEQ 0x00 0x1e
                               ALOAD_0
                               GETSTATIC 0x04 0x85
                               ICONST_0
                               FALOAD
                               PUTFIELD 0x01 0x10
                               ALOAD_0
                               GETSTATIC 0x04 0x85
                               ICONST_1
                               FALOAD
                               PUTFIELD 0x01 0x11
                               ALOAD_0
                               GETSTATIC 0x04 0x85
                               ICONST_2
                               FALOAD
                               PUTFIELD 0x01 0x12
 applying RenderGlobal patch to l.class for mod Custom Colors
    override cloud type b(F)V@0
     ALOAD_0                   ALOAD_0
     GETFIELD 0x01 0x47        GETFIELD 0x01 0x47
     GETFIELD 0x01 0x5c        GETFIELD 0x01 0x5c
     GETFIELD 0x01 0x75        GETFIELD 0x01 0x75
     GETFIELD 0x01 0x0c        GETFIELD 0x01 0x0c
     IFEQ 0x00 0x04            IFEQ 0x00 0x04
     RETURN                    RETURN
     ALOAD_0                   ALOAD_0
     GETFIELD 0x01 0x47        GETFIELD 0x01 0x47
     GETFIELD 0x01 0x5a        GETFIELD 0x01 0x5a
     GETFIELD 0x01 0x21        GETFIELD 0x01 0x21
     IFEQ 0x00 0x09            INVOKESTATIC 0x04 0xe6
                               IFEQ 0x00 0x09
 applying ItemRenderer patch to lv.class for mod HD Textures
    tool pixel top a(Laby;FFFF)V@331
     FLOAD 0x06                FLOAD 0x06
     FLOAD 0x09                FLOAD 0x09
     FMUL                      FMUL
     LDC 0x1b                  GETSTATIC 0x01 0xdf
     FADD                      FADD
     FSTORE 0x0b               FSTORE 0x0b
    tool pixel top a(Laby;FFFF)V@463
     FLOAD 0x06                FLOAD 0x06
     FLOAD 0x09                FLOAD 0x09
     FMUL                      FMUL
     LDC 0x1b                  GETSTATIC 0x01 0xdf
     FADD                      FADD
     FSTORE 0x0b               FSTORE 0x0b
    16.0F -> float_size a(Laby;FFFF)V@185
     LDC 0x37                  GETSTATIC 0x01 0xe2
    16.0F -> float_size a(Laby;FFFF)V@313
     LDC 0x37                  GETSTATIC 0x01 0xe2
    16.0F -> float_size a(Laby;FFFF)V@445
     LDC 0x37                  GETSTATIC 0x01 0xe2
    16.0F -> float_size a(Laby;FFFF)V@583
     LDC 0x37                  GETSTATIC 0x01 0xe2
    while i < 16 -> int_size a(Laby;FFFF)V@177
     BIPUSH 0x10               GETSTATIC 0x01 0xe5
     IF_ICMPGE 0x00 0x69       IF_ICMPGE 0x00 0x69
    while i < 16 -> int_size a(Laby;FFFF)V@306
     BIPUSH 0x10               GETSTATIC 0x01 0xe5
     IF_ICMPGE 0x00 0x6d       IF_ICMPGE 0x00 0x6d
    while i < 16 -> int_size a(Laby;FFFF)V@439
     BIPUSH 0x10               GETSTATIC 0x01 0xe5
     IF_ICMPGE 0x00 0x72       IF_ICMPGE 0x00 0x72
    while i < 16 -> int_size a(Laby;FFFF)V@578
     BIPUSH 0x10               GETSTATIC 0x01 0xe5
     IF_ICMPGE 0x00 0x6e       IF_ICMPGE 0x00 0x6e
    tool tex calculation a(Laar;Lyq;I)V@135
     BIPUSH 0x10               BIPUSH 0x10
     IREM                      IREM
     BIPUSH 0x10               GETSTATIC 0x01 0xe5
     IMUL                      IMUL
     I2F                       I2F
     FCONST_0                  FCONST_0
     FADD                      FADD
     LDC 0x46                  GETSTATIC 0x01 0xe8
    tool tex calculation a(Laar;Lyq;I)V@153
     BIPUSH 0x10               BIPUSH 0x10
     IREM                      IREM
     BIPUSH 0x10               GETSTATIC 0x01 0xe5
     IMUL                      IMUL
     I2F                       I2F
     LDC 0x36                  GETSTATIC 0x01 0xeb
     FADD                      FADD
     LDC 0x46                  GETSTATIC 0x01 0xe8
    tool tex calculation a(Laar;Lyq;I)V@173
     BIPUSH 0x10               BIPUSH 0x10
     IDIV                      IDIV
     BIPUSH 0x10               GETSTATIC 0x01 0xe5
     IMUL                      IMUL
     I2F                       I2F
     FCONST_0                  FCONST_0
     FADD                      FADD
     LDC 0x46                  GETSTATIC 0x01 0xe8
    tool tex calculation a(Laar;Lyq;I)V@191
     BIPUSH 0x10               BIPUSH 0x10
     IDIV                      IDIV
     BIPUSH 0x10               GETSTATIC 0x01 0xe5
     IMUL                      IMUL
     I2F                       I2F
     LDC 0x36                  GETSTATIC 0x01 0xeb
     FADD                      FADD
     LDC 0x46                  GETSTATIC 0x01 0xe8
    0.001953125F -> float_texNudge a(Laby;FFFF)V@201
     LDC 0x16                  GETSTATIC 0x01 0xee
    0.001953125F -> float_texNudge a(Laby;FFFF)V@331
     LDC 0x16                  GETSTATIC 0x01 0xee
    0.001953125F -> float_texNudge a(Laby;FFFF)V@466
     LDC 0x16                  GETSTATIC 0x01 0xee
    0.001953125F -> float_texNudge a(Laby;FFFF)V@606
     LDC 0x16                  GETSTATIC 0x01 0xee
 applying ItemRenderer patch to lv.class for mod Custom Colors
    override water block color in third person a(Laar;Lyq;I)V@260
     LDC 0x0d                  LDC 0x0d
     LDC 0x14                  LDC 0x14
     FCONST_0                  FCONST_0
     INVOKESTATIC 0x00 0xc1    INVOKESTATIC 0x00 0xc1
                               ALOAD_2
                               GETFIELD 0x00 0x9a
                               INVOKESTATIC 0x01 0xf3
 applying Fire patch to mn.class for mod HD Textures
    1.06F -> float_flameNudge a()V@143
     LDC 0x02                  GETSTATIC 0x00 0x3f
    array size 320 -> int_flameArraySize <init>(I)V@16
     SIPUSH 0x01 0x40          GETSTATIC 0x00 0x42
     NEWARRAY 0x06             NEWARRAY 0x06
    array size 320 -> int_flameArraySize <init>(I)V@25
     SIPUSH 0x01 0x40          GETSTATIC 0x00 0x42
     NEWARRAY 0x06             NEWARRAY 0x06
    while i < 256 -> int_numPixels a()V@227
     SIPUSH 0x01 0x00          GETSTATIC 0x00 0x45
     IF_ICMPGE 0x00 0xf5       IF_ICMPGE 0x00 0xf5
    while i < 20 -> int_flameHeight a()V@11
     BIPUSH 0x14               GETSTATIC 0x00 0x48
     IF_ICMPGE 0x00 0xbb       IF_ICMPGE 0x00 0xbb
    while i < 20 -> int_flameHeight a()V@92
     BIPUSH 0x14               GETSTATIC 0x00 0x48
     IF_ICMPGE 0x00 0x15       IF_ICMPGE 0x00 0x15
    while i < 16 -> int_size a()V@3
     BIPUSH 0x10               GETSTATIC 0x00 0x4b
     IF_ICMPGE 0x00 0xcb       IF_ICMPGE 0x00 0xcb
    while i < 16 -> int_size a()V@86
     BIPUSH 0x10               GETSTATIC 0x00 0x4b
     IF_ICMPGE 0x00 0x1d       IF_ICMPGE 0x00 0x1d
    % 20 -> int_flameHeight a()V@29
     BIPUSH 0x14               GETSTATIC 0x00 0x48
     IREM                      IREM
    if i < 19 -> int_flameHeightMinus1 a()V@155
     BIPUSH 0x13               GETSTATIC 0x00 0x4e
     IF_ICMPLT 0x00 0x2a       IF_ICMPLT 0x00 0x2a
    * 16 -> int_size a()V@33
     BIPUSH 0x10               GETSTATIC 0x00 0x4b
     IMUL                      IMUL
    * 16 -> int_size a()V@112
     BIPUSH 0x10               GETSTATIC 0x00 0x4b
     IMUL                      IMUL
    * 16 -> int_size a()V@142
     BIPUSH 0x10               GETSTATIC 0x00 0x4b
     IMUL                      IMUL
    * 16 -> int_size a()V@170
     BIPUSH 0x10               GETSTATIC 0x00 0x4b
     IMUL                      IMUL
 applying FontRenderer patch to mq.class for mod HD Textures
    make field isUnicode public
    insert method initialize ()V stack size 8, local vars 18
 applying GetResource patch to mq.class for mod HD Textures
    ImageIO.read(getResource(...)) -> getResourceAsBufferedImage(...) <init>(Lhh;Ljava/lang/String;Lyz;Z)V@71
     LDC 0x25                  NOP
     ALOAD_2                   NOP
     INVOKEVIRTUAL 0x00 0x3a   NOP
     INVOKESTATIC 0x00 0x58    NOP
                               NOP
                               ALOAD_2
                               INVOKESTATIC 0x01 0x37
    ImageIO.read(getResource(...)) -> getResourceAsBufferedImage(...) initialize(Lhh;Ljava/lang/String;Lyz;)V@71
     LDC 0x25                  NOP
     ALOAD_2                   NOP
     INVOKEVIRTUAL 0x00 0x3a   NOP
     INVOKESTATIC 0x00 0x58    NOP
                               NOP
                               ALOAD_2
                               INVOKESTATIC 0x01 0x37
 applying FontRenderer patch to mq.class for mod HD Font
    insert field charWidthf [F
    FontUtils.computeCharWidths on init <init>(Lhh;Ljava/lang/String;Lyz;Z)V@156
     ICONST_0                  NOP
     ISTORE 0x09               NOP
     ILOAD 0x09                NOP
     SIPUSH 0x01 0x00          NOP
     IF_ICMPGE 0x00 0x88       NOP
     ILOAD 0x09                NOP
     BIPUSH 0x10               NOP
     IREM                      NOP
     ISTORE 0x0a               NOP
     ILOAD 0x09                NOP
     BIPUSH 0x10               NOP
     IDIV                      NOP
     ISTORE 0x0b               NOP
     BIPUSH 0x07               NOP
     ISTORE 0x0c               NOP
     ILOAD 0x0c                NOP
     IFLT 0x00 0x56            NOP
     ILOAD 0x0a                NOP
     BIPUSH 0x08               NOP
     IMUL                      NOP
     ILOAD 0x0c                NOP
     IADD                      NOP
     ISTORE 0x0d               NOP
     ICONST_1                  NOP
     ISTORE 0x0e               NOP
     ICONST_0                  NOP
     ISTORE 0x0f               NOP
     ILOAD 0x0f                NOP
     BIPUSH 0x08               NOP
     IF_ICMPGE 0x00 0x31       NOP
     ILOAD 0x0e                NOP
     IFEQ 0x00 0x2c            NOP
     ILOAD 0x0b                NOP
     BIPUSH 0x08               NOP
     IMUL                      NOP
     ILOAD 0x0f                NOP
     IADD                      NOP
     ILOAD 0x06                NOP
     IMUL                      NOP
     ISTORE 0x10               NOP
     ALOAD 0x08                NOP
     ILOAD 0x0d                NOP
     ILOAD 0x10                NOP
     IADD                      NOP
     IALOAD                    NOP
     SIPUSH 0x00 0xff          NOP
     IAND                      NOP
     ISTORE 0x11               NOP
     ILOAD 0x11                NOP
     IFLE 0x00 0x06            NOP
     ICONST_0                  NOP
     ISTORE 0x0e               NOP
     IINC 0x0f 0x01            NOP
     GOTO 0xff 0xce            NOP
     ILOAD 0x0e                NOP
     IFNE 0x00 0x06            NOP
     GOTO 0x00 0x09            NOP
     IINC 0x0c 0xff            NOP
     GOTO 0xff 0xab            NOP
     ILOAD 0x09                NOP
     BIPUSH 0x20               NOP
     IF_ICMPNE 0x00 0x06       NOP
     ICONST_2                  NOP
     ISTORE 0x0c               NOP
     ALOAD_0                   NOP
     GETFIELD 0x00 0x2a        NOP
     ILOAD 0x09                NOP
     ILOAD 0x0c                NOP
     ICONST_2                  NOP
     IADD                      NOP
     IASTORE                   NOP
     IINC 0x09 0x01            NOP
     GOTO 0xff 0x76            NOP
                               NOP
                               NOP
                               NOP
                               NOP
                               NOP
                               NOP
                               NOP
                               NOP
                               NOP
                               NOP
                               NOP
                               NOP
                               NOP
                               NOP
                               NOP
                               NOP
                               NOP
                               NOP
                               NOP
                               NOP
                               NOP
                               NOP
                               NOP
                               NOP
                               NOP
                               NOP
                               NOP
                               NOP
                               NOP
                               NOP
                               NOP
                               NOP
                               NOP
                               NOP
                               NOP
                               NOP
                               NOP
                               NOP
                               NOP
                               NOP
                               NOP
                               NOP
                               NOP
                               NOP
                               NOP
                               NOP
                               NOP
                               NOP
                               NOP
                               NOP
                               NOP
                               NOP
                               NOP
                               NOP
                               NOP
                               ALOAD_0
                               ALOAD_2
                               ALOAD 0x05
                               ALOAD 0x08
                               ALOAD_0
                               GETFIELD 0x00 0x2a
                               INVOKESTATIC 0x01 0x3f
                               PUTFIELD 0x01 0x41
    FontUtils.computeCharWidths on init initialize(Lhh;Ljava/lang/String;Lyz;)V@156
     ICONST_0                  NOP
     ISTORE 0x09               NOP
     ILOAD 0x09                NOP
     SIPUSH 0x01 0x00          NOP
     IF_ICMPGE 0x00 0x88       NOP
     ILOAD 0x09                NOP
     BIPUSH 0x10               NOP
     IREM                      NOP
     ISTORE 0x0a               NOP
     ILOAD 0x09                NOP
     BIPUSH 0x10               NOP
     IDIV                      NOP
     ISTORE 0x0b               NOP
     BIPUSH 0x07               NOP
     ISTORE 0x0c               NOP
     ILOAD 0x0c                NOP
     IFLT 0x00 0x56            NOP
     ILOAD 0x0a                NOP
     BIPUSH 0x08               NOP
     IMUL                      NOP
     ILOAD 0x0c                NOP
     IADD                      NOP
     ISTORE 0x0d               NOP
     ICONST_1                  NOP
     ISTORE 0x0e               NOP
     ICONST_0                  NOP
     ISTORE 0x0f               NOP
     ILOAD 0x0f                NOP
     BIPUSH 0x08               NOP
     IF_ICMPGE 0x00 0x31       NOP
     ILOAD 0x0e                NOP
     IFEQ 0x00 0x2c            NOP
     ILOAD 0x0b                NOP
     BIPUSH 0x08               NOP
     IMUL                      NOP
     ILOAD 0x0f                NOP
     IADD                      NOP
     ILOAD 0x06                NOP
     IMUL                      NOP
     ISTORE 0x10               NOP
     ALOAD 0x08                NOP
     ILOAD 0x0d                NOP
     ILOAD 0x10                NOP
     IADD                      NOP
     IALOAD                    NOP
     SIPUSH 0x00 0xff          NOP
     IAND                      NOP
     ISTORE 0x11               NOP
     ILOAD 0x11                NOP
     IFLE 0x00 0x06            NOP
     ICONST_0                  NOP
     ISTORE 0x0e               NOP
     IINC 0x0f 0x01            NOP
     GOTO 0xff 0xce            NOP
     ILOAD 0x0e                NOP
     IFNE 0x00 0x06            NOP
     GOTO 0x00 0x09            NOP
     IINC 0x0c 0xff            NOP
     GOTO 0xff 0xab            NOP
     ILOAD 0x09                NOP
     BIPUSH 0x20               NOP
     IF_ICMPNE 0x00 0x06       NOP
     ICONST_2                  NOP
     ISTORE 0x0c               NOP
     ALOAD_0                   NOP
     GETFIELD 0x00 0x2a        NOP
     ILOAD 0x09                NOP
     ILOAD 0x0c                NOP
     ICONST_2                  NOP
     IADD                      NOP
     IASTORE                   NOP
     IINC 0x09 0x01            NOP
     GOTO 0xff 0x76            NOP
                               NOP
                               NOP
                               NOP
                               NOP
                               NOP
                               NOP
                               NOP
                               NOP
                               NOP
                               NOP
                               NOP
                               NOP
                               NOP
                               NOP
                               NOP
                               NOP
                               NOP
                               NOP
                               NOP
                               NOP
                               NOP
                               NOP
                               NOP
                               NOP
                               NOP
                               NOP
                               NOP
                               NOP
                               NOP
                               NOP
                               NOP
                               NOP
                               NOP
                               NOP
                               NOP
                               NOP
                               NOP
                               NOP
                               NOP
                               NOP
                               NOP
                               NOP
                               NOP
                               NOP
                               NOP
                               NOP
                               NOP
                               NOP
                               NOP
                               NOP
                               NOP
                               NOP
                               NOP
                               NOP
                               NOP
                               ALOAD_0
                               ALOAD_2
                               ALOAD 0x05
                               ALOAD 0x08
                               ALOAD_0
                               GETFIELD 0x00 0x2a
                               INVOKESTATIC 0x01 0x3f
                               PUTFIELD 0x01 0x41
    use charWidthf in glTranslatef call a(I)V@47
     ALOAD_0                   NOP
     GETFIELD 0x00 0x2a        ALOAD_0
     ILOAD_1                   GETFIELD 0x01 0x41
     IALOAD                    ILOAD_1
     I2F                       FALOAD
    use charWidthf in glTranslatef call a(I)V@187
     ALOAD_0                   NOP
     GETFIELD 0x00 0x2a        ALOAD_0
     ILOAD_1                   GETFIELD 0x01 0x41
     IALOAD                    ILOAD_1
     I2F                       FALOAD
    use charWidthf in getStringWidth (init) a(Ljava/lang/String;)I@6
     ICONST_0                  FCONST_0
     ISTORE_2                  FSTORE_2
    use charWidthf in getStringWidth (loop) a(Ljava/lang/String;)I@61
     ILOAD_2                   FLOAD_2
     ALOAD_0                   ALOAD_0
     GETFIELD 0x00 0x2a        GETFIELD 0x01 0x41
     ILOAD 0x05                ILOAD 0x05
     BIPUSH 0x20               BIPUSH 0x20
     IADD                      IADD
     IALOAD                    FALOAD
     IADD                      FADD
     ISTORE_2                  FSTORE_2
    use charWidthf in getStringWidth (return value) a(Ljava/lang/String;)I@145
     ILOAD_2                   FLOAD_2
                               INVOKESTATIC 0x01 0x47
    getStringWidth int -> float a(Ljava/lang/String;)I@127
     ILOAD_2                   FLOAD_2
     ILOAD 0x07                ILOAD 0x07
     ILOAD 0x06                ILOAD 0x06
     ISUB                      ISUB
     ICONST_2                  ICONST_2
     IDIV                      IDIV
     ICONST_1                  ICONST_1
     IADD                      IADD
     IADD                      I2F
     ISTORE_2                  FADD
                               FSTORE_2
 applying Entity patch to ms.class for mod Random Mobs
    insert field randomMobsSkin J
    insert field randomMobsSkinSet Z
    write skin to nbt d(Labx;)V@0
                               ALOAD_1
                               LDC_W 0x02 0xee
                               ALOAD_0
                               GETFIELD 0x02 0xf0
                               INVOKEVIRTUAL 0x02 0xf3
    read skin from nbt e(Labx;)V@0
     label A -> instruction 25
     branch offset IFEQ A -> +8 @17
                               ALOAD_0
                               ALOAD_1
                               LDC_W 0x02 0xee
                               INVOKEVIRTUAL 0x02 0xf6
                               PUTFIELD 0x02 0xf0
                               ALOAD_0
                               GETFIELD 0x02 0xf0
                               LCONST_0
                               LCMP
                               IFEQ 0x00 0x08
                               ALOAD_0
                               ICONST_1
                               PUTFIELD 0x02 0xf8
 applying EntitySplashFX patch to nb.class for mod Custom Colors
    override splash drop color <init>(Lvq;DDDDDD)V@69
     label A -> instruction 124
     label B -> instruction 124
     branch offset IFEQ A -> +33 @91
     branch offset GOTO B -> +3 @121
                               ALOAD_0
                               GETFIELD 0x00 0x29
                               INVOKEVIRTUAL 0x00 0x2f
                               ALOAD_0
                               GETFIELD 0x00 0x32
                               ALOAD_0
                               GETFIELD 0x00 0x35
                               ALOAD_0
                               GETFIELD 0x00 0x37
                               INVOKESTATIC 0x00 0x3d
                               IFEQ 0x00 0x21
                               ALOAD_0
                               GETSTATIC 0x00 0x41
                               ICONST_0
                               FALOAD
                               PUTFIELD 0x00 0x44
                               ALOAD_0
                               GETSTATIC 0x00 0x41
                               ICONST_1
                               FALOAD
                               PUTFIELD 0x00 0x47
                               ALOAD_0
                               GETSTATIC 0x00 0x41
                               ICONST_2
                               FALOAD
                               PUTFIELD 0x00 0x4a
                               GOTO 0x00 0x03
 applying Block patch to oe.class for mod Custom Colors
    override color multiplier for all blocks b(Laiw;III)I@0
     LDC 0x01                  ALOAD_0
                               ALOAD_1
                               INVOKEINTERFACE 0x05 0xb9 0x01 0x00
                               ILOAD_2
                               ILOAD_3
                               ILOAD 0x04
                               INVOKESTATIC 0x05 0xbf
   increasing stack size from 1 to 5
    override default color for all blocks d(I)I@0
     LDC 0x01                  ALOAD_0
                               INVOKESTATIC 0x05 0xc2
 applying StillWater patch to pd.class for mod HD Textures
    array size 256 -> int_numPixels <init>()V@11
     SIPUSH 0x01 0x00          GETSTATIC 0x00 0x44
     NEWARRAY 0x06             NEWARRAY 0x06
    array size 256 -> int_numPixels <init>()V@20
     SIPUSH 0x01 0x00          GETSTATIC 0x00 0x44
     NEWARRAY 0x06             NEWARRAY 0x06
    array size 256 -> int_numPixels <init>()V@29
     SIPUSH 0x01 0x00          GETSTATIC 0x00 0x44
     NEWARRAY 0x06             NEWARRAY 0x06
    array size 256 -> int_numPixels <init>()V@38
     SIPUSH 0x01 0x00          GETSTATIC 0x00 0x44
     NEWARRAY 0x06             NEWARRAY 0x06
    while i < 256 -> int_numPixels a()V@262
     SIPUSH 0x01 0x00          GETSTATIC 0x00 0x44
     IF_ICMPGE 0x00 0xc8       IF_ICMPGE 0x00 0xc8
    while i < 16 -> int_size a()V@13
     BIPUSH 0x10               GETSTATIC 0x00 0x47
     IF_ICMPGE 0x00 0x67       IF_ICMPGE 0x00 0x67
    while i < 16 -> int_size a()V@22
     BIPUSH 0x10               GETSTATIC 0x00 0x47
     IF_ICMPGE 0x00 0x59       IF_ICMPGE 0x00 0x59
    while i < 16 -> int_size a()V@123
     BIPUSH 0x10               GETSTATIC 0x00 0x47
     IF_ICMPGE 0x00 0x76       IF_ICMPGE 0x00 0x76
    while i < 16 -> int_size a()V@132
     BIPUSH 0x10               GETSTATIC 0x00 0x47
     IF_ICMPGE 0x00 0x68       IF_ICMPGE 0x00 0x68
    & 15 -> int_sizeMinus1 a()V@45
     BIPUSH 0x0f               GETSTATIC 0x00 0x4a
     IAND                      IAND
    & 15 -> int_sizeMinus1 a()V@52
     BIPUSH 0x0f               GETSTATIC 0x00 0x4a
     IAND                      IAND
    * 16 -> int_size a()V@67
     BIPUSH 0x10               GETSTATIC 0x00 0x47
     IMUL                      IMUL
    * 16 -> int_size a()V@87
     BIPUSH 0x10               GETSTATIC 0x00 0x47
     IMUL                      IMUL
    * 16 -> int_size a()V@102
     BIPUSH 0x10               GETSTATIC 0x00 0x47
     IMUL                      IMUL
    * 16 -> int_size a()V@149
     BIPUSH 0x10               GETSTATIC 0x00 0x47
     IMUL                      IMUL
    * 16 -> int_size a()V@162
     BIPUSH 0x10               GETSTATIC 0x00 0x47
     IMUL                      IMUL
    * 16 -> int_size a()V@179
     BIPUSH 0x10               GETSTATIC 0x00 0x47
     IMUL                      IMUL
    * 16 -> int_size a()V@196
     BIPUSH 0x10               GETSTATIC 0x00 0x47
     IMUL                      IMUL
    * 16 -> int_size a()V@209
     BIPUSH 0x10               GETSTATIC 0x00 0x47
     IMUL                      IMUL
    * 16 -> int_size a()V@236
     BIPUSH 0x10               GETSTATIC 0x00 0x47
     IMUL                      IMUL
 applying BlockGrass patch to qb.class for mod Better Grass
    insert field grassMatrix [[I
    initialize grassMatrix <init>(I)V@19
     label A -> instruction 67
     branch offset IF_ACMPNE A -> +44 @23
                               GETSTATIC 0x00 0x70
                               ACONST_NULL
                               IF_ACMPNE 0x00 0x2c
                               ICONST_4
                               ICONST_2
                               MULTIANEWARRAY 0x00 0x71 0x02
                               PUTSTATIC 0x00 0x70
                               GETSTATIC 0x00 0x70
                               ICONST_0
                               AALOAD
                               ICONST_1
                               ICONST_M1
                               IASTORE
                               GETSTATIC 0x00 0x70
                               ICONST_1
                               AALOAD
                               ICONST_1
                               ICONST_1
                               IASTORE
                               GETSTATIC 0x00 0x70
                               ICONST_2
                               AALOAD
                               ICONST_0
                               ICONST_M1
                               IASTORE
                               GETSTATIC 0x00 0x70
                               ICONST_3
                               AALOAD
                               ICONST_0
                               ICONST_1
                               IASTORE
    check surrounding blocks in getBlockTexture d(Laiw;IIII)I@29
     label A -> instruction 89
     label B -> instruction 87
     label C -> instruction 141
     branch offset IF_ACMPEQ A -> +52 @37
     branch offset IF_ACMPEQ A -> +44 @45
     branch offset IF_ICMPEQ B -> +5 @82
     branch offset IF_ACMPEQ C -> +14 @127
     branch offset IF_ACMPEQ C -> +6 @135
     ALOAD 0x06                IINC 0x05 0xfe
     GETSTATIC 0x00 0x0f       ALOAD 0x06
     IF_ACMPEQ 0x00 0x0b       GETSTATIC 0x00 0x0f
     ALOAD 0x06                IF_ACMPEQ 0x00 0x34
     GETSTATIC 0x00 0x10       ALOAD 0x06
     IF_ACMPNE 0x00 0x06       GETSTATIC 0x00 0x10
     BIPUSH 0x44               IF_ACMPEQ 0x00 0x2c
     IRETURN                   ALOAD 0x01
     ICONST_3                  ILOAD 0x02
                               GETSTATIC 0x00 0x70
                               ILOAD 0x05
                               AALOAD
                               ICONST_0
                               IALOAD
                               IADD
                               ILOAD 0x03
                               ICONST_1
                               ISUB
                               ILOAD 0x04
                               GETSTATIC 0x00 0x70
                               ILOAD 0x05
                               AALOAD
                               ICONST_1
                               IALOAD
                               IADD
                               INVOKEINTERFACE 0x00 0x73 0x04 0x00
                               ICONST_2
                               IF_ICMPEQ 0x00 0x05
                               ICONST_3
                               IRETURN
                               ICONST_0
                               IRETURN
                               ALOAD 0x01
                               ILOAD 0x02
                               GETSTATIC 0x00 0x70
                               ILOAD 0x05
                               AALOAD
                               ICONST_0
                               IALOAD
                               IADD
                               ILOAD 0x03
                               ILOAD 0x04
                               GETSTATIC 0x00 0x70
                               ILOAD 0x05
                               AALOAD
                               ICONST_1
                               IALOAD
                               IADD
                               INVOKEINTERFACE 0x00 0x24 0x04 0x00
                               ASTORE 0x06
                               ALOAD 0x06
                               GETSTATIC 0x00 0x0f
                               IF_ACMPEQ 0x00 0x0e
                               ALOAD 0x06
                               GETSTATIC 0x00 0x10
                               IF_ACMPEQ 0x00 0x06
                               BIPUSH 0x44
                               IRETURN
                               BIPUSH 0x42
   increasing stack size from 4 to 6
 applying EntityRainFX patch to qj.class for mod Custom Colors
    override rain drop color <init>(Lvq;DDD)V@52
     label A -> instruction 107
     label B -> instruction 125
     branch offset IFEQ A -> +33 @74
     branch offset GOTO B -> +21 @104
     ALOAD_0                   ALOAD_0
     FCONST_1                  GETFIELD 0x00 0x21
     PUTFIELD 0x00 0x1d        INVOKEVIRTUAL 0x00 0x95
     ALOAD_0                   ALOAD_0
     FCONST_1                  GETFIELD 0x00 0x25
     PUTFIELD 0x00 0x1e        ALOAD_0
     ALOAD_0                   GETFIELD 0x00 0x26
     FCONST_1                  ALOAD_0
     PUTFIELD 0x00 0x1f        GETFIELD 0x00 0x27
                               INVOKESTATIC 0x00 0x9b
                               IFEQ 0x00 0x21
                               ALOAD_0
                               GETSTATIC 0x00 0x9f
                               ICONST_0
                               FALOAD
                               PUTFIELD 0x00 0x1d
                               ALOAD_0
                               GETSTATIC 0x00 0x9f
                               ICONST_1
                               FALOAD
                               PUTFIELD 0x00 0x1e
                               ALOAD_0
                               GETSTATIC 0x00 0x9f
                               ICONST_2
                               FALOAD
                               PUTFIELD 0x00 0x1f
                               GOTO 0x00 0x15
                               ALOAD_0
                               LDC 0x04
                               PUTFIELD 0x00 0x1d
                               ALOAD_0
                               LDC_W 0x00 0xa0
                               PUTFIELD 0x00 0x1e
                               ALOAD_0
                               FCONST_1
                               PUTFIELD 0x00 0x1f
 applying RenderEnderman patch to rv.class for mod Random Mobs
    override enderman eye texture a(Lis;IF)I@7
     LDC 0x09                  ALOAD_1
                               LDC 0x09
                               INVOKESTATIC 0x00 0x99
 applying TextureFX patch to sr.class for mod HD Textures
    array size 1024 -> int_numBytes <init>(I)V@5
     SIPUSH 0x04 0x00          GETSTATIC 0x00 0x38
     NEWARRAY 0x08             NEWARRAY 0x08
 applying Compass patch to ss.class for mod HD Textures
    7.5D -> double_compassCenterMin a()V@464
     LDC2_W 0x00 0x24          GETSTATIC 0x00 0xa6
    7.5D -> double_compassCenterMin a()V@675
     LDC2_W 0x00 0x24          GETSTATIC 0x00 0xa6
    8.5D -> double_compassCenterMax a()V@447
     LDC2_W 0x00 0x26          GETSTATIC 0x00 0xa9
    8.5D -> double_compassCenterMax a()V@658
     LDC2_W 0x00 0x26          GETSTATIC 0x00 0xa9
    array size 256 -> int_numPixels <init>(Lnet/minecraft/client/Minecraft;)V@12
     SIPUSH 0x01 0x00          GETSTATIC 0x00 0xac
     NEWARRAY 0x0a             NEWARRAY 0x0a
    * 16 -> int_size <init>(Lnet/minecraft/client/Minecraft;)V@48
     BIPUSH 0x10               GETSTATIC 0x00 0xaf
     IMUL                      IMUL
    * 16 -> int_size <init>(Lnet/minecraft/client/Minecraft;)V@60
     BIPUSH 0x10               GETSTATIC 0x00 0xaf
     IMUL                      IMUL
    * 16 -> int_size a()V@487
     BIPUSH 0x10               GETSTATIC 0x00 0xaf
     IMUL                      IMUL
    * 16 -> int_size a()V@699
     BIPUSH 0x10               GETSTATIC 0x00 0xaf
     IMUL                      IMUL
    while i < 256 -> int_numPixels a()V@3
     SIPUSH 0x01 0x00          GETSTATIC 0x00 0xac
     IF_ICMPGE 0x00 0xb9       IF_ICMPGE 0x00 0xb9
    -4 -> int_compassCrossMin a()V@437
     BIPUSH 0xfc               GETSTATIC 0x00 0xb2
    if i > 4 -> int_compassCrossMax a()V@444
     ICONST_4                  GETSTATIC 0x00 0xb5
     IF_ICMPGT 0x00 0xcc       IF_ICMPGT 0x00 0xcc
    -8 -> int_compassNeedleMin a()V@651
     BIPUSH 0xf8               GETSTATIC 0x00 0xb8
    if i > 16 -> int_compassNeedleMax a()V@658
     BIPUSH 0x10               GETSTATIC 0x00 0xbb
     IF_ICMPGT 0x00 0xeb       IF_ICMPGT 0x00 0xeb
    getRGB(...16,16,...16) -> getRGB(...int_size,int_size,...int_size) <init>(Lnet/minecraft/client/Minecraft;)V@70
     BIPUSH 0x10               GETSTATIC 0x00 0xaf
     BIPUSH 0x10               GETSTATIC 0x00 0xaf
     ALOAD_0                   ALOAD_0
     GETFIELD 0x00 0x2e        GETFIELD 0x00 0x2e
     ICONST_0                  ICONST_0
     BIPUSH 0x10               GETSTATIC 0x00 0xaf
 applying GetResource patch to ss.class for mod HD Textures
    ImageIO.read(getResource(...)) -> getResourceAsBufferedImage(...) <init>(Lnet/minecraft/client/Minecraft;)V@30
     LDC 0x09                  NOP
     LDC 0x02                  NOP
     INVOKEVIRTUAL 0x00 0x3e   NOP
     INVOKESTATIC 0x00 0x43    NOP
                               NOP
                               LDC 0x02
                               INVOKESTATIC 0x00 0xc8
 applying BlockLeaves patch to tb.class for mod Custom Colors
    override biome pine foliage color b(Laiw;III)I@20
     INVOKESTATIC 0x00 0x25    INVOKESTATIC 0x00 0x25
                               GETSTATIC 0x00 0xb6
                               ALOAD_1
                               INVOKEINTERFACE 0x00 0x3d 0x01 0x00
                               ILOAD_2
                               ILOAD_3
                               ILOAD 0x04
                               INVOKESTATIC 0x00 0xba
    override biome birch foliage color b(Laiw;III)I@48
     INVOKESTATIC 0x00 0x27    INVOKESTATIC 0x00 0x27
                               GETSTATIC 0x00 0xbd
                               ALOAD_1
                               INVOKEINTERFACE 0x00 0x3d 0x01 0x00
                               ILOAD_2
                               ILOAD_3
                               ILOAD 0x04
                               INVOKESTATIC 0x00 0xba
 applying ItemBlock patch to tw.class for mod Custom Colors
    insert method getColorFromDamage (II)I stack size 3, local vars 3
 applying EntityBubbleFX patch to tz.class for mod Custom Colors
    override bubble drop color <init>(Lvq;DDDDDD)V@16
     label A -> instruction 71
     label B -> instruction 86
     branch offset IFEQ A -> +33 @38
     branch offset GOTO B -> +18 @68
     ALOAD_0                   ALOAD_0
     FCONST_1                  GETFIELD 0x00 0x20
     PUTFIELD 0x00 0x1c        INVOKEVIRTUAL 0x00 0x82
     ALOAD_0                   ALOAD_0
     FCONST_1                  GETFIELD 0x00 0x24
     PUTFIELD 0x00 0x1d        ALOAD_0
     ALOAD_0                   GETFIELD 0x00 0x25
     FCONST_1                  ALOAD_0
     PUTFIELD 0x00 0x1e        GETFIELD 0x00 0x26
                               INVOKESTATIC 0x00 0x88
                               IFEQ 0x00 0x21
                               ALOAD_0
                               GETSTATIC 0x00 0x8c
                               ICONST_0
                               FALOAD
                               PUTFIELD 0x00 0x1c
                               ALOAD_0
                               GETSTATIC 0x00 0x8c
                               ICONST_1
                               FALOAD
                               PUTFIELD 0x00 0x1d
                               ALOAD_0
                               GETSTATIC 0x00 0x8c
                               ICONST_2
                               FALOAD
                               PUTFIELD 0x00 0x1e
                               GOTO 0x00 0x12
                               ALOAD_0
                               FCONST_1
                               PUTFIELD 0x00 0x1c
                               ALOAD_0
                               FCONST_1
                               PUTFIELD 0x00 0x1d
                               ALOAD_0
                               FCONST_1
                               PUTFIELD 0x00 0x1e
 applying RenderBlocks patch to uc.class for mod Better Grass
    if (getBlockTexture == 0) useBiomeColor = true (non-AO post-1.8) b(Loe;IIIFFF)Z@432
     label A -> instruction 472
     branch offset IFNE A -> +23 @449
     ALOAD_1                   ALOAD_1
     ALOAD_0                   ALOAD_0
     GETFIELD 0x00 0xe3        GETFIELD 0x00 0xe3
     ILOAD_2                   ILOAD_2
     ILOAD_3                   ILOAD_3
     ILOAD 0x04                ILOAD 0x04
     ICONST_2                  ICONST_2
     INVOKEVIRTUAL 0x01 0x5b   INVOKEVIRTUAL 0x01 0x5b
     ISTORE 0x1c               ISTORE 0x1c
     ALOAD_0                   ILOAD 0x1c
     ALOAD_1                   IFNE 0x00 0x17
     ILOAD_2                   ALOAD 0x08
     I2D                       FLOAD 0x05
     ILOAD_3                   FLOAD 0x05
     I2D                       FMUL
     ILOAD 0x04                FLOAD 0x06
     I2D                       FLOAD 0x06
     ILOAD 0x1c                FMUL
     INVOKEVIRTUAL 0x01 0x7e   FLOAD 0x07
     GETSTATIC 0x01 0x0a       FLOAD 0x07
     IFEQ 0x00 0x32            FMUL
     ILOAD 0x1c                INVOKEVIRTUAL 0x01 0x28
     ICONST_3                  ALOAD_0
     IF_ICMPNE 0x00 0x2c       ALOAD_1
     ALOAD_0                   ILOAD_2
     GETFIELD 0x01 0x0d        I2D
     IFGE 0x00 0x25            ILOAD_3
     ALOAD 0x08                I2D
     FLOAD 0x12                ILOAD 0x04
     FLOAD 0x05                I2D
     FMUL                      ILOAD 0x1c
     FLOAD 0x15                INVOKEVIRTUAL 0x01 0x7e
     FLOAD 0x06                GETSTATIC 0x01 0x0a
     FMUL                      IFEQ 0x00 0x32
     FLOAD 0x18                ILOAD 0x1c
     FLOAD 0x07                ICONST_3
     FMUL                      IF_ICMPNE 0x00 0x2c
     INVOKEVIRTUAL 0x01 0x28   ALOAD_0
                               GETFIELD 0x01 0x0d
                               IFGE 0x00 0x25
                               ALOAD 0x08
                               FLOAD 0x12
                               FLOAD 0x05
                               FMUL
                               FLOAD 0x15
                               FLOAD 0x06
                               FMUL
                               FLOAD 0x18
                               FLOAD 0x07
                               FMUL
                               INVOKEVIRTUAL 0x01 0x28
    if (getBlockTexture == 0) useBiomeColor = true (non-AO post-1.8) b(Loe;IIIFFF)Z@611
     label A -> instruction 651
     branch offset IFNE A -> +23 @628
     ALOAD_1                   ALOAD_1
     ALOAD_0                   ALOAD_0
     GETFIELD 0x00 0xe3        GETFIELD 0x00 0xe3
     ILOAD_2                   ILOAD_2
     ILOAD_3                   ILOAD_3
     ILOAD 0x04                ILOAD 0x04
     ICONST_3                  ICONST_3
     INVOKEVIRTUAL 0x01 0x5b   INVOKEVIRTUAL 0x01 0x5b
     ISTORE 0x1c               ISTORE 0x1c
     ALOAD_0                   ILOAD 0x1c
     ALOAD_1                   IFNE 0x00 0x17
     ILOAD_2                   ALOAD 0x08
     I2D                       FLOAD 0x05
     ILOAD_3                   FLOAD 0x05
     I2D                       FMUL
     ILOAD 0x04                FLOAD 0x06
     I2D                       FLOAD 0x06
     ILOAD 0x1c                FMUL
     INVOKEVIRTUAL 0x01 0x82   FLOAD 0x07
     GETSTATIC 0x01 0x0a       FLOAD 0x07
     IFEQ 0x00 0x32            FMUL
     ILOAD 0x1c                INVOKEVIRTUAL 0x01 0x28
     ICONST_3                  ALOAD_0
     IF_ICMPNE 0x00 0x2c       ALOAD_1
     ALOAD_0                   ILOAD_2
     GETFIELD 0x01 0x0d        I2D
     IFGE 0x00 0x25            ILOAD_3
     ALOAD 0x08                I2D
     FLOAD 0x12                ILOAD 0x04
     FLOAD 0x05                I2D
     FMUL                      ILOAD 0x1c
     FLOAD 0x15                INVOKEVIRTUAL 0x01 0x82
     FLOAD 0x06                GETSTATIC 0x01 0x0a
     FMUL                      IFEQ 0x00 0x32
     FLOAD 0x18                ILOAD 0x1c
     FLOAD 0x07                ICONST_3
     FMUL                      IF_ICMPNE 0x00 0x2c
     INVOKEVIRTUAL 0x01 0x28   ALOAD_0
                               GETFIELD 0x01 0x0d
                               IFGE 0x00 0x25
                               ALOAD 0x08
                               FLOAD 0x12
                               FLOAD 0x05
                               FMUL
                               FLOAD 0x15
                               FLOAD 0x06
                               FMUL
                               FLOAD 0x18
                               FLOAD 0x07
                               FMUL
                               INVOKEVIRTUAL 0x01 0x28
    if (getBlockTexture == 0) useBiomeColor = true (non-AO post-1.8) b(Loe;IIIFFF)Z@790
     label A -> instruction 830
     branch offset IFNE A -> +23 @807
     ALOAD_1                   ALOAD_1
     ALOAD_0                   ALOAD_0
     GETFIELD 0x00 0xe3        GETFIELD 0x00 0xe3
     ILOAD_2                   ILOAD_2
     ILOAD_3                   ILOAD_3
     ILOAD 0x04                ILOAD 0x04
     ICONST_4                  ICONST_4
     INVOKEVIRTUAL 0x01 0x5b   INVOKEVIRTUAL 0x01 0x5b
     ISTORE 0x1c               ISTORE 0x1c
     ALOAD_0                   ILOAD 0x1c
     ALOAD_1                   IFNE 0x00 0x17
     ILOAD_2                   ALOAD 0x08
     I2D                       FLOAD 0x05
     ILOAD_3                   FLOAD 0x05
     I2D                       FMUL
     ILOAD 0x04                FLOAD 0x06
     I2D                       FLOAD 0x06
     ILOAD 0x1c                FMUL
     INVOKEVIRTUAL 0x01 0x83   FLOAD 0x07
     GETSTATIC 0x01 0x0a       FLOAD 0x07
     IFEQ 0x00 0x32            FMUL
     ILOAD 0x1c                INVOKEVIRTUAL 0x01 0x28
     ICONST_3                  ALOAD_0
     IF_ICMPNE 0x00 0x2c       ALOAD_1
     ALOAD_0                   ILOAD_2
     GETFIELD 0x01 0x0d        I2D
     IFGE 0x00 0x25            ILOAD_3
     ALOAD 0x08                I2D
     FLOAD 0x13                ILOAD 0x04
     FLOAD 0x05                I2D
     FMUL                      ILOAD 0x1c
     FLOAD 0x16                INVOKEVIRTUAL 0x01 0x83
     FLOAD 0x06                GETSTATIC 0x01 0x0a
     FMUL                      IFEQ 0x00 0x32
     FLOAD 0x19                ILOAD 0x1c
     FLOAD 0x07                ICONST_3
     FMUL                      IF_ICMPNE 0x00 0x2c
     INVOKEVIRTUAL 0x01 0x28   ALOAD_0
                               GETFIELD 0x01 0x0d
                               IFGE 0x00 0x25
                               ALOAD 0x08
                               FLOAD 0x13
                               FLOAD 0x05
                               FMUL
                               FLOAD 0x16
                               FLOAD 0x06
                               FMUL
                               FLOAD 0x19
                               FLOAD 0x07
                               FMUL
                               INVOKEVIRTUAL 0x01 0x28
    if (getBlockTexture == 0) useBiomeColor = true (non-AO post-1.8) b(Loe;IIIFFF)Z@969
     label A -> instruction 1009
     branch offset IFNE A -> +23 @986
     ALOAD_1                   ALOAD_1
     ALOAD_0                   ALOAD_0
     GETFIELD 0x00 0xe3        GETFIELD 0x00 0xe3
     ILOAD_2                   ILOAD_2
     ILOAD_3                   ILOAD_3
     ILOAD 0x04                ILOAD 0x04
     ICONST_5                  ICONST_5
     INVOKEVIRTUAL 0x01 0x5b   INVOKEVIRTUAL 0x01 0x5b
     ISTORE 0x1c               ISTORE 0x1c
     ALOAD_0                   ILOAD 0x1c
     ALOAD_1                   IFNE 0x00 0x17
     ILOAD_2                   ALOAD 0x08
     I2D                       FLOAD 0x05
     ILOAD_3                   FLOAD 0x05
     I2D                       FMUL
     ILOAD 0x04                FLOAD 0x06
     I2D                       FLOAD 0x06
     ILOAD 0x1c                FMUL
     INVOKEVIRTUAL 0x01 0x85   FLOAD 0x07
     GETSTATIC 0x01 0x0a       FLOAD 0x07
     IFEQ 0x00 0x32            FMUL
     ILOAD 0x1c                INVOKEVIRTUAL 0x01 0x28
     ICONST_3                  ALOAD_0
     IF_ICMPNE 0x00 0x2c       ALOAD_1
     ALOAD_0                   ILOAD_2
     GETFIELD 0x01 0x0d        I2D
     IFGE 0x00 0x25            ILOAD_3
     ALOAD 0x08                I2D
     FLOAD 0x13                ILOAD 0x04
     FLOAD 0x05                I2D
     FMUL                      ILOAD 0x1c
     FLOAD 0x16                INVOKEVIRTUAL 0x01 0x85
     FLOAD 0x06                GETSTATIC 0x01 0x0a
     FMUL                      IFEQ 0x00 0x32
     FLOAD 0x19                ILOAD 0x1c
     FLOAD 0x07                ICONST_3
     FMUL                      IF_ICMPNE 0x00 0x2c
     INVOKEVIRTUAL 0x01 0x28   ALOAD_0
                               GETFIELD 0x01 0x0d
                               IFGE 0x00 0x25
                               ALOAD 0x08
                               FLOAD 0x13
                               FLOAD 0x05
                               FMUL
                               FLOAD 0x16
                               FLOAD 0x06
                               FMUL
                               FLOAD 0x19
                               FLOAD 0x07
                               FMUL
                               INVOKEVIRTUAL 0x01 0x28
    if (getBlockTexture == 0) useBiomeColor = true (AO) a(Loe;IIIFFF)Z@682
     label south -> instruction 773
     label north -> instruction 754
     label east -> instruction 716
     label west -> instruction 735
     branch offset IFNE east -> +6 @710
     branch offset IFNE west -> +6 @729
     branch offset IFNE north -> +6 @748
     branch offset IFNE south -> +6 @767
     ICONST_0                  ICONST_0
     DUP                       DUP
     ISTORE 0x12               ISTORE 0x12
     DUP                       DUP
     ISTORE 0x11               ISTORE 0x11
     DUP                       DUP
     ISTORE 0x10               ISTORE 0x10
     DUP                       DUP
     ISTORE 0x0f               ISTORE 0x0f
     ISTORE 0x0d               ISTORE 0x0d
                               ALOAD_1
                               ALOAD_0
                               GETFIELD 0x00 0xe3
                               ILOAD_2
                               ILOAD_3
                               ILOAD 0x04
                               ICONST_2
                               INVOKEVIRTUAL 0x01 0x5b
                               IFNE 0x00 0x06
                               ICONST_1
                               ISTORE 0x0f
                               ALOAD_1
                               ALOAD_0
                               GETFIELD 0x00 0xe3
                               ILOAD_2
                               ILOAD_3
                               ILOAD 0x04
                               ICONST_3
                               INVOKEVIRTUAL 0x01 0x5b
                               IFNE 0x00 0x06
                               ICONST_1
                               ISTORE 0x10
                               ALOAD_1
                               ALOAD_0
                               GETFIELD 0x00 0xe3
                               ILOAD_2
                               ILOAD_3
                               ILOAD 0x04
                               ICONST_4
                               INVOKEVIRTUAL 0x01 0x5b
                               IFNE 0x00 0x06
                               ICONST_1
                               ISTORE 0x11
                               ALOAD_1
                               ALOAD_0
                               GETFIELD 0x00 0xe3
                               ILOAD_2
                               ILOAD_3
                               ILOAD 0x04
                               ICONST_5
                               INVOKEVIRTUAL 0x01 0x5b
                               IFNE 0x00 0x06
                               ICONST_1
                               ISTORE 0x12
    if (getBlockTexture == 0) useBiomeColor = true (AO) a(Loe;IIIFFF)Z@780
     label south -> instruction 871
     label north -> instruction 852
     label east -> instruction 814
     label west -> instruction 833
     branch offset IFNE east -> +6 @808
     branch offset IFNE west -> +6 @827
     branch offset IFNE north -> +6 @846
     branch offset IFNE south -> +6 @865
     ICONST_0                  ICONST_0
     DUP                       DUP
     ISTORE 0x12               ISTORE 0x12
     DUP                       DUP
     ISTORE 0x11               ISTORE 0x11
     DUP                       DUP
     ISTORE 0x10               ISTORE 0x10
     DUP                       DUP
     ISTORE 0x0f               ISTORE 0x0f
     ISTORE 0x0d               ISTORE 0x0d
                               ALOAD_1
                               ALOAD_0
                               GETFIELD 0x00 0xe3
                               ILOAD_2
                               ILOAD_3
                               ILOAD 0x04
                               ICONST_2
                               INVOKEVIRTUAL 0x01 0x5b
                               IFNE 0x00 0x06
                               ICONST_1
                               ISTORE 0x0f
                               ALOAD_1
                               ALOAD_0
                               GETFIELD 0x00 0xe3
                               ILOAD_2
                               ILOAD_3
                               ILOAD 0x04
                               ICONST_3
                               INVOKEVIRTUAL 0x01 0x5b
                               IFNE 0x00 0x06
                               ICONST_1
                               ISTORE 0x10
                               ALOAD_1
                               ALOAD_0
                               GETFIELD 0x00 0xe3
                               ILOAD_2
                               ILOAD_3
                               ILOAD 0x04
                               ICONST_4
                               INVOKEVIRTUAL 0x01 0x5b
                               IFNE 0x00 0x06
                               ICONST_1
                               ISTORE 0x11
                               ALOAD_1
                               ALOAD_0
                               GETFIELD 0x00 0xe3
                               ILOAD_2
                               ILOAD_3
                               ILOAD 0x04
                               ICONST_5
                               INVOKEVIRTUAL 0x01 0x5b
                               IFNE 0x00 0x06
                               ICONST_1
                               ISTORE 0x12
 applying RenderBlocks patch to uc.class for mod Custom Colors
    override redstone wire color g(Loe;III)Z@62
     label A -> instruction 88
     label B -> instruction 141
     branch offset IFEQ A -> +21 @67
     branch offset GOTO B -> +56 @85
     ILOAD 0x06                ILOAD 0x06
     I2F                       INVOKESTATIC 0x03 0x56
     LDC 0x31                  IFEQ 0x00 0x15
     FDIV                      GETSTATIC 0x03 0x59
     FSTORE 0x09               FSTORE 0x0a
     FLOAD 0x09                GETSTATIC 0x03 0x5c
     LDC 0x1c                  FSTORE 0x0b
     FMUL                      GETSTATIC 0x03 0x5f
     LDC 0x18                  FSTORE 0x0c
     FADD                      GOTO 0x00 0x38
     FSTORE 0x0a               ILOAD 0x06
     ILOAD 0x06                I2F
     IFNE 0x00 0x07            LDC 0x31
     LDC 0x15                  FDIV
     FSTORE 0x0a               FSTORE 0x09
     FLOAD 0x09                FLOAD 0x09
     FLOAD 0x09                LDC 0x1c
     FMUL                      FMUL
     LDC 0x20                  LDC 0x18
     FMUL                      FADD
     LDC 0x1a                  FSTORE 0x0a
     FSUB                      ILOAD 0x06
     FSTORE 0x0b               IFNE 0x00 0x07
     FLOAD 0x09                LDC 0x15
     FLOAD 0x09                FSTORE 0x0a
     FMUL                      FLOAD 0x09
     LDC 0x1c                  FLOAD 0x09
     FMUL                      FMUL
     LDC 0x20                  LDC 0x20
     FSUB                      FMUL
     FSTORE 0x0c               LDC 0x1a
                               FSUB
                               FSTORE 0x0b
                               FLOAD 0x09
                               FLOAD 0x09
                               FMUL
                               LDC 0x1c
                               FMUL
                               LDC 0x20
                               FSUB
                               FSTORE 0x0c
    colorize cauldron water color a(Lvw;III)Z@337
     SIPUSH 0x00 0xcd          SIPUSH 0x00 0xcd
     ISTORE 0x0f               ISTORE 0x0f
                               INVOKESTATIC 0x03 0x62
                               ALOAD 0x05
                               GETSTATIC 0x03 0x66
                               ICONST_0
                               FALOAD
                               GETSTATIC 0x03 0x66
                               ICONST_1
                               FALOAD
                               GETSTATIC 0x03 0x66
                               ICONST_2
                               FALOAD
                               INVOKEVIRTUAL 0x01 0x28
    colorize falling sand and gravel a(Loe;Lvq;III)V@58
     ALOAD 0x0a                ALOAD_1
     FLOAD 0x06                ALOAD_2
     FLOAD 0x0c                INVOKEVIRTUAL 0x03 0x6b
     FMUL                      ILOAD_3
     FLOAD 0x06                ILOAD 0x04
     FLOAD 0x0c                ILOAD 0x05
     FMUL                      INVOKESTATIC 0x03 0x6f
     FLOAD 0x06                INVOKESTATIC 0x03 0x72
     FLOAD 0x0c                ALOAD 0x0a
     FMUL                      GETSTATIC 0x03 0x75
     INVOKEVIRTUAL 0x01 0x28   ICONST_0
                               FALOAD
                               FLOAD 0x0c
                               FMUL
                               GETSTATIC 0x03 0x75
                               ICONST_1
                               FALOAD
                               FLOAD 0x0c
                               FMUL
                               GETSTATIC 0x03 0x75
                               ICONST_2
                               FALOAD
                               FLOAD 0x0c
                               FMUL
                               INVOKEVIRTUAL 0x01 0x28
    colorize falling sand and gravel a(Loe;Lvq;III)V@137
     ALOAD 0x0a                ALOAD 0x0a
     FLOAD 0x07                GETSTATIC 0x03 0x75
     FLOAD 0x0c                ICONST_0
     FMUL                      FALOAD
     FLOAD 0x07                FLOAD 0x0c
     FLOAD 0x0c                FMUL
     FMUL                      GETSTATIC 0x03 0x75
     FLOAD 0x07                ICONST_1
     FLOAD 0x0c                FALOAD
     FMUL                      FLOAD 0x0c
     INVOKEVIRTUAL 0x01 0x28   FMUL
                               GETSTATIC 0x03 0x75
                               ICONST_2
                               FALOAD
                               FLOAD 0x0c
                               FMUL
                               INVOKEVIRTUAL 0x01 0x28
    colorize falling sand and gravel a(Loe;Lvq;III)V@200
     ALOAD 0x0a                ALOAD 0x0a
     FLOAD 0x08                GETSTATIC 0x03 0x75
     FLOAD 0x0c                ICONST_0
     FMUL                      FALOAD
     FLOAD 0x08                FLOAD 0x0c
     FLOAD 0x0c                FMUL
     FMUL                      GETSTATIC 0x03 0x75
     FLOAD 0x08                ICONST_1
     FLOAD 0x0c                FALOAD
     FMUL                      FLOAD 0x0c
     INVOKEVIRTUAL 0x01 0x28   FMUL
                               GETSTATIC 0x03 0x75
                               ICONST_2
                               FALOAD
                               FLOAD 0x0c
                               FMUL
                               INVOKEVIRTUAL 0x01 0x28
    colorize falling sand and gravel a(Loe;Lvq;III)V@263
     ALOAD 0x0a                ALOAD 0x0a
     FLOAD 0x08                GETSTATIC 0x03 0x75
     FLOAD 0x0c                ICONST_0
     FMUL                      FALOAD
     FLOAD 0x08                FLOAD 0x0c
     FLOAD 0x0c                FMUL
     FMUL                      GETSTATIC 0x03 0x75
     FLOAD 0x08                ICONST_1
     FLOAD 0x0c                FALOAD
     FMUL                      FLOAD 0x0c
     INVOKEVIRTUAL 0x01 0x28   FMUL
                               GETSTATIC 0x03 0x75
                               ICONST_2
                               FALOAD
                               FLOAD 0x0c
                               FMUL
                               INVOKEVIRTUAL 0x01 0x28
    colorize falling sand and gravel a(Loe;Lvq;III)V@326
     ALOAD 0x0a                ALOAD 0x0a
     FLOAD 0x09                GETSTATIC 0x03 0x75
     FLOAD 0x0c                ICONST_0
     FMUL                      FALOAD
     FLOAD 0x09                FLOAD 0x0c
     FLOAD 0x0c                FMUL
     FMUL                      GETSTATIC 0x03 0x75
     FLOAD 0x09                ICONST_1
     FLOAD 0x0c                FALOAD
     FMUL                      FLOAD 0x0c
     INVOKEVIRTUAL 0x01 0x28   FMUL
                               GETSTATIC 0x03 0x75
                               ICONST_2
                               FALOAD
                               FLOAD 0x0c
                               FMUL
                               INVOKEVIRTUAL 0x01 0x28
    colorize falling sand and gravel a(Loe;Lvq;III)V@389
     ALOAD 0x0a                ALOAD 0x0a
     FLOAD 0x09                GETSTATIC 0x03 0x75
     FLOAD 0x0c                ICONST_0
     FMUL                      FALOAD
     FLOAD 0x09                FLOAD 0x0c
     FLOAD 0x0c                FMUL
     FMUL                      GETSTATIC 0x03 0x75
     FLOAD 0x09                ICONST_1
     FLOAD 0x0c                FALOAD
     FMUL                      FLOAD 0x0c
     INVOKEVIRTUAL 0x01 0x28   FMUL
                               GETSTATIC 0x03 0x75
                               ICONST_2
                               FALOAD
                               FLOAD 0x0c
                               FMUL
                               INVOKEVIRTUAL 0x01 0x28
    colorize bottom of water block n(Loe;III)Z@745
     ALOAD 0x05                ALOAD 0x05
     FLOAD 0x0e                FLOAD 0x0e
     FLOAD 0x22                FLOAD 0x22
     FMUL                      FMUL
     FLOAD 0x0e                FLOAD 0x07
     FLOAD 0x22                FMUL
     FMUL                      FLOAD 0x0e
     FLOAD 0x0e                FLOAD 0x22
     FLOAD 0x22                FMUL
     FMUL                      FLOAD 0x08
     INVOKEVIRTUAL 0x01 0x28   FMUL
                               FLOAD 0x0e
                               FLOAD 0x22
                               FMUL
                               FLOAD 0x08
                               FMUL
                               INVOKEVIRTUAL 0x01 0x28
 applying World patch to vq.class for mod Custom Colors
    override sky color a(Lms;F)Lbk;@93
     label A -> instruction 132
     label B -> instruction 174
     branch offset IFEQ A -> +27 @105
     branch offset GOTO B -> +45 @129
     ILOAD 0x08                ALOAD_0
     BIPUSH 0x10               INVOKEVIRTUAL 0x01 0xbd
     ISHR                      ALOAD_1
     SIPUSH 0x00 0xff          INVOKESTATIC 0x05 0x24
     IAND                      ALOAD_0
     I2F                       INVOKESTATIC 0x05 0x28
     LDC 0x1c                  IFEQ 0x00 0x1b
     FDIV                      GETSTATIC 0x05 0x2b
     FSTORE 0x09               ICONST_0
     ILOAD 0x08                FALOAD
     BIPUSH 0x08               FSTORE 0x09
     ISHR                      GETSTATIC 0x05 0x2b
     SIPUSH 0x00 0xff          ICONST_1
     IAND                      FALOAD
     I2F                       FSTORE 0x0a
     LDC 0x1c                  GETSTATIC 0x05 0x2b
     FDIV                      ICONST_2
     FSTORE 0x0a               FALOAD
     ILOAD 0x08                FSTORE 0x0b
     SIPUSH 0x00 0xff          GOTO 0x00 0x2d
     IAND                      ILOAD 0x08
     I2F                       BIPUSH 0x10
     LDC 0x1c                  ISHR
     FDIV                      SIPUSH 0x00 0xff
     FSTORE 0x0b               IAND
                               I2F
                               LDC 0x1c
                               FDIV
                               FSTORE 0x09
                               ILOAD 0x08
                               BIPUSH 0x08
                               ISHR
                               SIPUSH 0x00 0xff
                               IAND
                               I2F
                               LDC 0x1c
                               FDIV
                               FSTORE 0x0a
                               ILOAD 0x08
                               SIPUSH 0x00 0xff
                               IAND
                               I2F
                               LDC 0x1c
                               FDIV
                               FSTORE 0x0b
 applying BlockLilyPad patch to wl.class for mod Custom Colors
    override lily pad color i()I@0
     LDC 0x01                  INVOKESTATIC 0x00 0x57
    override lily pad color d(I)I@0
     LDC 0x01                  INVOKESTATIC 0x00 0x57
    override lily pad color b(Laiw;III)I@0
     LDC 0x01                  INVOKESTATIC 0x00 0x57
 applying Portal patch to xs.class for mod HD Textures
    16.0F -> float_size <init>()V@98
     LDC 0x06                  GETSTATIC 0x00 0x50
    16.0F -> float_size <init>()V@112
     LDC 0x06                  GETSTATIC 0x00 0x50
    while i < 16 -> int_size <init>()V@50
     BIPUSH 0x10               GETSTATIC 0x00 0x53
     IF_ICMPGE 0x01 0x6c       IF_ICMPGE 0x01 0x6c
    while i < 16 -> int_size <init>()V@61
     BIPUSH 0x10               GETSTATIC 0x00 0x53
     IF_ICMPGE 0x01 0x5c       IF_ICMPGE 0x01 0x5c
    array size 32x1024 -> int_numBytes <init>()V@16
     BIPUSH 0x20               BIPUSH 0x20
     SIPUSH 0x04 0x00          GETSTATIC 0x00 0x56
     MULTIANEWARRAY 0x00 0x0d 0x02  MULTIANEWARRAY 0x00 0x0d 0x02
    * 16 -> int_size <init>()V@335
     BIPUSH 0x10               GETSTATIC 0x00 0x53
     IMUL                      IMUL
    * 8 -> int_sizeHalf <init>()V@81
     BIPUSH 0x08               GETSTATIC 0x00 0x59
     IMUL                      IMUL
    * 8 -> int_sizeHalf <init>()V@90
     BIPUSH 0x08               GETSTATIC 0x00 0x59
     IMUL                      IMUL
    while i < 256 -> int_numPixels a()V@26
     SIPUSH 0x01 0x00          GETSTATIC 0x00 0x5c
     IF_ICMPGE 0x00 0xb4       IF_ICMPGE 0x00 0xb4
 applying ColorizerWater patch to xw.class for mod HD Textures
    make field colorBuffer public
 applying ColorizerGrass patch to xy.class for mod HD Textures
    make field colorBuffer public
 applying EntityReddustFX patch to ye.class for mod Custom Colors
    override redstone particle color <init>(Lvq;DDDFFFF)V@56
     label A -> instruction 82
     branch offset IFEQ A -> +18 @64
     FCONST_1                  FCONST_1
     FSTORE 0x09               FSTORE 0x09
     INVOKESTATIC 0x00 0x2b    BIPUSH 0x0f
                               INVOKESTATIC 0x00 0x7a
                               IFEQ 0x00 0x12
                               GETSTATIC 0x00 0x7d
                               FSTORE 0x09
                               GETSTATIC 0x00 0x80
                               FSTORE 0x0a
                               GETSTATIC 0x00 0x83
                               FSTORE 0x0b
                               INVOKESTATIC 0x00 0x2b
 applying Potion patch to yg.class for mod Custom Colors
    make field name public
    insert field origColor I
    make field color public
    map potions by name a(Ljava/lang/String;)Lyg;@5
     ALOAD_0                   ALOAD_0
                               INVOKESTATIC 0x01 0x1e
                               ALOAD_0
 applying EntityList patch to yr.class for mod Custom Colors
    set up mapping for spawnable entities a(Ljava/lang/Class;Ljava/lang/String;III)V@0
                               ALOAD_1
                               ILOAD_2
                               ILOAD_3
                               ILOAD 0x04
                               INVOKESTATIC 0x01 0x4e
 applying RenderEngine patch to yz.class for mod HD Textures
    (i % 16) * 16 + j * 16 -> (i % 16) * int_size + j * int_size a()V@133
     BIPUSH 0x10               BIPUSH 0x10
     IREM                      IREM
     BIPUSH 0x10               GETSTATIC 0x01 0x7e
     IMUL                      IMUL
     ILOAD 0x04                ILOAD 0x04
     BIPUSH 0x10               GETSTATIC 0x01 0x7e
     IMUL                      IMUL
    (i / 16) * 16 + j * 16 -> (i / 16) * int_size + j * int_size a()V@151
     BIPUSH 0x10               BIPUSH 0x10
     IDIV                      IDIV
     BIPUSH 0x10               GETSTATIC 0x01 0x7e
     IMUL                      IMUL
     ILOAD 0x05                ILOAD 0x05
     BIPUSH 0x10               GETSTATIC 0x01 0x7e
     IMUL                      IMUL
    glTexSubImage2D(...,16,16) -> glTexSubImage2D(...,int_size,int_size) a()V@165
     BIPUSH 0x10               GETSTATIC 0x01 0x7e
     BIPUSH 0x10               GETSTATIC 0x01 0x7e
     SIPUSH 0x19 0x08          SIPUSH 0x19 0x08
     SIPUSH 0x14 0x01          SIPUSH 0x14 0x01
    readTextureImage(getInputStream(...)) -> getResourceAsBufferedImage(...) a(Ljava/lang/String;)[I@46
     INVOKEVIRTUAL 0x00 0x43   NOP
     INVOKESPECIAL 0x00 0x72   NOP
                               NOP
                               INVOKESTATIC 0x01 0x84
    readTextureImage(getInputStream(...)) -> getResourceAsBufferedImage(...) a(Ljava/lang/String;)[I@85
     INVOKEVIRTUAL 0x00 0x43   NOP
     INVOKESPECIAL 0x00 0x72   NOP
                               NOP
                               INVOKESTATIC 0x01 0x84
    readTextureImage(getInputStream(...)) -> getResourceAsBufferedImage(...) a(Ljava/lang/String;)[I@131
     INVOKEVIRTUAL 0x00 0x43   NOP
     INVOKESPECIAL 0x00 0x72   NOP
                               NOP
                               INVOKESTATIC 0x01 0x84
    readTextureImage(getInputStream(...)) -> getResourceAsBufferedImage(...) b(Ljava/lang/String;)I@71
     INVOKEVIRTUAL 0x00 0x43   NOP
     INVOKESPECIAL 0x00 0x72   NOP
                               NOP
                               INVOKESTATIC 0x01 0x84
    readTextureImage(getInputStream(...)) -> getResourceAsBufferedImage(...) b(Ljava/lang/String;)I@110
     INVOKEVIRTUAL 0x00 0x43   NOP
     INVOKESPECIAL 0x00 0x72   NOP
                               NOP
                               INVOKESTATIC 0x01 0x84
    readTextureImage(getInputStream(...)) -> getResourceAsBufferedImage(...) b(Ljava/lang/String;)I@151
     INVOKEVIRTUAL 0x00 0x43   NOP
     INVOKESPECIAL 0x00 0x72   NOP
                               NOP
                               INVOKESTATIC 0x01 0x84
    readTextureImage(getInputStream(...)) -> getResourceAsBufferedImage(...) b(Ljava/lang/String;)I@197
     INVOKEVIRTUAL 0x00 0x43   NOP
     INVOKESPECIAL 0x00 0x72   NOP
                               NOP
                               INVOKESTATIC 0x01 0x84
    readTextureImage(getInputStream(...)) -> getResourceAsBufferedImage(...) b()V@157
     INVOKEVIRTUAL 0x00 0x43   NOP
     INVOKESPECIAL 0x00 0x72   NOP
                               NOP
                               INVOKESTATIC 0x01 0x84
    readTextureImage(getInputStream(...)) -> getResourceAsBufferedImage(...) b()V@193
     INVOKEVIRTUAL 0x00 0x43   NOP
     INVOKESPECIAL 0x00 0x72   NOP
                               NOP
                               INVOKESTATIC 0x01 0x84
    readTextureImage(getInputStream(...)) -> getResourceAsBufferedImage(...) b()V@226
     INVOKEVIRTUAL 0x00 0x43   NOP
     INVOKESPECIAL 0x00 0x72   NOP
                               NOP
                               INVOKESTATIC 0x01 0x84
    readTextureImage(getInputStream(...)) -> getResourceAsBufferedImage(...) b()V@264
     INVOKEVIRTUAL 0x00 0x43   NOP
     INVOKESPECIAL 0x00 0x72   NOP
                               NOP
                               INVOKESTATIC 0x01 0x84
    readTextureImage(getInputStream(...)) -> getResourceAsBufferedImage(...) b()V@278
     INVOKEVIRTUAL 0x00 0x43   NOP
     INVOKESPECIAL 0x00 0x72   NOP
                               NOP
                               INVOKESTATIC 0x01 0x84
    readTextureImage(getInputStream(...)) -> getResourceAsBufferedImage(...) b()V@382
     INVOKEVIRTUAL 0x00 0x43   NOP
     INVOKESPECIAL 0x00 0x72   NOP
                               NOP
                               INVOKESTATIC 0x01 0x84
    readTextureImage(getInputStream(...)) -> getResourceAsBufferedImage(...) b()V@418
     INVOKEVIRTUAL 0x00 0x43   NOP
     INVOKESPECIAL 0x00 0x72   NOP
                               NOP
                               INVOKESTATIC 0x01 0x84
    readTextureImage(getInputStream(...)) -> getResourceAsBufferedImage(...) b()V@451
     INVOKEVIRTUAL 0x00 0x43   NOP
     INVOKESPECIAL 0x00 0x72   NOP
                               NOP
                               INVOKESTATIC 0x01 0x84
    readTextureImage(getInputStream(...)) -> getResourceAsBufferedImage(...) b()V@465
     INVOKEVIRTUAL 0x00 0x43   NOP
     INVOKESPECIAL 0x00 0x72   NOP
                               NOP
                               INVOKESTATIC 0x01 0x84
    getInputStream(...), readTextureImage -> getResourceAsBufferedImage(...) b(Ljava/lang/String;)I@220
     ALOAD_2                   NOP
     ALOAD_1                   NOP
     INVOKEVIRTUAL 0x00 0x43   NOP
     ASTORE 0x04               NOP
     ALOAD 0x04                NOP
     IFNONNULL 0x00 0x0f       NOP
     ALOAD_0                   NOP
     ALOAD_0                   NOP
     GETFIELD 0x00 0x3e        NOP
     ILOAD_3                   NOP
     INVOKEVIRTUAL 0x00 0x70   NOP
     GOTO 0x00 0x0e            NOP
     ALOAD_0                   NOP
     ALOAD_0                   NOP
     ALOAD 0x04                NOP
     INVOKESPECIAL 0x00 0x72   NOP
                               NOP
                               NOP
                               NOP
                               NOP
                               NOP
                               NOP
                               NOP
                               NOP
                               NOP
                               NOP
                               ALOAD_0
                               ALOAD_1
                               INVOKESTATIC 0x01 0x87
    imageData.clear(), .put(), .limit() -> imageData = TextureUtils.getByteBuffer() a(Ljava/awt/image/BufferedImage;I)V@397
     ALOAD_0                   NOP
     GETFIELD 0x00 0x39        NOP
     INVOKEVIRTUAL 0x00 0x57   NOP
     POP                       NOP
     ALOAD_0                   NOP
     GETFIELD 0x00 0x39        NOP
     ALOAD 0x06                NOP
     INVOKEVIRTUAL 0x00 0x5a   NOP
     POP                       NOP
     ALOAD_0                   NOP
     GETFIELD 0x00 0x39        NOP
     ICONST_0                  NOP
     INVOKEVIRTUAL 0x00 0x59   NOP
     ALOAD 0x06                NOP
     ARRAYLENGTH               NOP
     INVOKEVIRTUAL 0x00 0x56   NOP
     POP                       NOP
                               NOP
                               NOP
                               NOP
                               ALOAD_0
                               ALOAD_0
                               GETFIELD 0x00 0x39
                               ALOAD 0x06
                               INVOKESTATIC 0x01 0x8b
                               PUTFIELD 0x00 0x39
    imageData.clear(), .put(), .limit() -> imageData = TextureUtils.getByteBuffer() a([IIII)V@359
     ALOAD_0                   NOP
     GETFIELD 0x00 0x39        NOP
     INVOKEVIRTUAL 0x00 0x57   NOP
     POP                       NOP
     ALOAD_0                   NOP
     GETFIELD 0x00 0x39        NOP
     ALOAD 0x05                NOP
     INVOKEVIRTUAL 0x00 0x5a   NOP
     POP                       NOP
     ALOAD_0                   NOP
     GETFIELD 0x00 0x39        NOP
     ICONST_0                  NOP
     INVOKEVIRTUAL 0x00 0x59   NOP
     ALOAD 0x05                NOP
     ARRAYLENGTH               NOP
     INVOKEVIRTUAL 0x00 0x56   NOP
     POP                       NOP
                               NOP
                               NOP
                               NOP
                               ALOAD_0
                               ALOAD_0
                               GETFIELD 0x00 0x39
                               ALOAD 0x05
                               INVOKESTATIC 0x01 0x8b
                               PUTFIELD 0x00 0x39
    imageData.clear(), .put(), .limit() -> imageData = TextureUtils.getByteBuffer() a()V@46
     ALOAD_0                   NOP
     GETFIELD 0x00 0x39        NOP
     INVOKEVIRTUAL 0x00 0x57   NOP
     POP                       NOP
     ALOAD_0                   NOP
     GETFIELD 0x00 0x39        NOP
     ALOAD_3                   NOP
     GETFIELD 0x00 0x2e        NOP
     INVOKEVIRTUAL 0x00 0x5a   NOP
     POP                       NOP
     ALOAD_0                   NOP
     GETFIELD 0x00 0x39        NOP
     ICONST_0                  NOP
     INVOKEVIRTUAL 0x00 0x59   NOP
     ALOAD_3                   NOP
     GETFIELD 0x00 0x2e        NOP
     ARRAYLENGTH               NOP
     INVOKEVIRTUAL 0x00 0x56   NOP
     POP                       NOP
                               NOP
                               NOP
                               NOP
                               ALOAD_0
                               ALOAD_0
                               GETFIELD 0x00 0x39
                               ALOAD_3
                               GETFIELD 0x00 0x2e
                               INVOKESTATIC 0x01 0x8b
                               PUTFIELD 0x00 0x39
    call TextureUtils.registerTextureFX a(Lsr;)V@0
     ALOAD_0                   NOP
     GETFIELD 0x00 0x3a        NOP
     ALOAD_1                   NOP
     INVOKEINTERFACE 0x00 0x7e 0x02 0x00  NOP
     POP                       NOP
     ALOAD_1                   NOP
     INVOKEVIRTUAL 0x00 0x6b   NOP
                               ALOAD_0
                               GETFIELD 0x00 0x3a
                               ALOAD_1
                               INVOKESTATIC 0x01 0x8f
    null check in setupTexture a(Ljava/awt/image/BufferedImage;I)V@0
     label A -> instruction 5
     branch offset IFNONNULL A -> +4 @1
                               ALOAD_1
                               IFNONNULL 0x00 0x04
                               RETURN
    null check in getImageRGB a(Ljava/awt/image/BufferedImage;[I)[I@0
     label A -> instruction 6
     branch offset IFNONNULL A -> +5 @1
                               ALOAD_1
                               IFNONNULL 0x00 0x05
                               ALOAD_2
                               ARETURN
    insert method setTileSize (Lnet/minecraft/client/Minecraft;)V stack size 10, local vars 5
 applying BiomeGenBase patch to zp.class for mod Custom Colors
    map biomes by name a(Ljava/lang/String;)Lzp;@5
     ALOAD_0                   ALOAD_0
                               INVOKESTATIC 0x01 0xb8
                               ALOAD_0
 applying Minecraft patch to net/minecraft/client/Minecraft.class for mod __Base
    MCPatcherUtils.setMinecraft(this) <init>(Ljava/awt/Component;Ljava/awt/Canvas;Lnet/minecraft/client/MinecraftApplet;IIZ)V@0
     ALOAD_0                   ALOAD_0
     INVOKESPECIAL 0x02 0x11   INVOKESPECIAL 0x02 0x11
                               ALOAD_0
                               INVOKESTATIC 0x06 0xf4
                               LDC_W 0x06 0xf6
                               LDC_W 0x06 0xf8
                               INVOKESTATIC 0x06 0xfb
 applying Minecraft patch to net/minecraft/client/Minecraft.class for mod HD Textures
    TextureUtils.setTileSize(), renderEngine.setTileSize() on startup a()V@241
     ALOAD_0                   ALOAD_0
     NEW 0x00 0xf4             NEW 0x00 0xf4
     DUP                       DUP
     ALOAD_0                   ALOAD_0
     GETFIELD 0x01 0x3c        GETFIELD 0x01 0x3c
     ALOAD_0                   ALOAD_0
     GETFIELD 0x01 0x38        GETFIELD 0x01 0x38
     INVOKESPECIAL 0x03 0x10   INVOKESPECIAL 0x03 0x10
     PUTFIELD 0x01 0x6d        PUTFIELD 0x01 0x6d
                               INVOKESTATIC 0x07 0x00
                               POP
                               ALOAD_0
                               GETFIELD 0x01 0x6d
                               ALOAD_0
                               INVOKEVIRTUAL 0x07 0x02
    remove registerTextureFX call a()V@602
     ALOAD_0                   NOP
     GETFIELD 0x01 0x6d        NOP
     ALOAD_0                   NOP
     GETFIELD 0x01 0x5b        NOP
     INVOKEVIRTUAL 0x03 0x13   NOP
                               NOP
                               NOP
                               NOP
                               NOP
                               NOP
                               NOP
    remove registerTextureFX call a()V@613
     ALOAD_0                   NOP
     GETFIELD 0x01 0x6d        NOP
     ALOAD_0                   NOP
     GETFIELD 0x01 0x5a        NOP
     INVOKEVIRTUAL 0x03 0x13   NOP
                               NOP
                               NOP
                               NOP
                               NOP
                               NOP
                               NOP
    remove registerTextureFX call a()V@624
     ALOAD_0                   NOP
     GETFIELD 0x01 0x6d        NOP
     NEW 0x00 0xec             NOP
     DUP                       NOP
     INVOKESPECIAL 0x03 0x09   NOP
     INVOKEVIRTUAL 0x03 0x13   NOP
                               NOP
                               NOP
                               NOP
                               NOP
                               NOP
                               NOP
                               NOP
                               NOP
    remove registerTextureFX call a()V@638
     ALOAD_0                   NOP
     GETFIELD 0x01 0x6d        NOP
     NEW 0x00 0xd8             NOP
     DUP                       NOP
     ALOAD_0                   NOP
     INVOKESPECIAL 0x02 0xcb   NOP
     INVOKEVIRTUAL 0x03 0x13   NOP
                               NOP
                               NOP
                               NOP
                               NOP
                               NOP
                               NOP
                               NOP
                               NOP
    remove registerTextureFX call a()V@653
     ALOAD_0                   NOP
     GETFIELD 0x01 0x6d        NOP
     NEW 0x00 0x9e             NOP
     DUP                       NOP
     ALOAD_0                   NOP
     INVOKESPECIAL 0x01 0xef   NOP
     INVOKEVIRTUAL 0x03 0x13   NOP
                               NOP
                               NOP
                               NOP
                               NOP
                               NOP
                               NOP
                               NOP
                               NOP
    remove registerTextureFX call a()V@668
     ALOAD_0                   NOP
     GETFIELD 0x01 0x6d        NOP
     NEW 0x00 0x77             NOP
     DUP                       NOP
     INVOKESPECIAL 0x01 0xb3   NOP
     INVOKEVIRTUAL 0x03 0x13   NOP
                               NOP
                               NOP
                               NOP
                               NOP
                               NOP
                               NOP
                               NOP
                               NOP
    remove registerTextureFX call a()V@682
     ALOAD_0                   NOP
     GETFIELD 0x01 0x6d        NOP
     NEW 0x00 0x93             NOP
     DUP                       NOP
     INVOKESPECIAL 0x01 0xe1   NOP
     INVOKEVIRTUAL 0x03 0x13   NOP
                               NOP
                               NOP
                               NOP
                               NOP
                               NOP
                               NOP
                               NOP
                               NOP
    remove registerTextureFX call a()V@696
     ALOAD_0                   NOP
     GETFIELD 0x01 0x6d        NOP
     NEW 0x00 0xc2             NOP
     DUP                       NOP
     ICONST_0                  NOP
     INVOKESPECIAL 0x02 0x59   NOP
     INVOKEVIRTUAL 0x03 0x13   NOP
                               NOP
                               NOP
                               NOP
                               NOP
                               NOP
                               NOP
                               NOP
                               NOP
    remove registerTextureFX call a()V@711
     ALOAD_0                   NOP
     GETFIELD 0x01 0x6d        NOP
     NEW 0x00 0xc2             NOP
     DUP                       NOP
     ICONST_1                  NOP
     INVOKESPECIAL 0x02 0x59   NOP
     INVOKEVIRTUAL 0x03 0x13   NOP
                               NOP
                               NOP
                               NOP
                               NOP
                               NOP
                               NOP
                               NOP
                               NOP
    check for texture pack change on each tick k()V@0
                               ALOAD_0
                               INVOKESTATIC 0x07 0x05
  adding com/pclewis/mcpatcher/MCPatcherUtils.class for __Base
  adding com/pclewis/mcpatcher/Config.class for __Base
  adding com/pclewis/mcpatcher/mod/TileSize.class for HD Textures
  adding com/pclewis/mcpatcher/mod/TextureUtils.class for HD Textures
   method signature (Lnet/minecraft/client/Minecraft;Lnet/minecraft/src/FontRenderer;Ljava/lang/String;)V -> (Lnet/minecraft/client/Minecraft;Lmq;Ljava/lang/String;)V
   method signature (Ljava/util/List;Lnet/minecraft/src/TextureFX;)V -> (Ljava/util/List;Lsr;)V
   method signature (Lnet/minecraft/src/TextureFX;)Lnet/minecraft/src/TextureFX; -> (Lsr;)Lsr;
   method signature ()Lnet/minecraft/src/TexturePackBase; -> ()Lh;
   method signature (Lnet/minecraft/src/TexturePackBase;)Ljava/lang/String; -> (Lh;)Ljava/lang/String;
   method signature (Lnet/minecraft/src/TexturePackBase;Ljava/lang/String;)Ljava/io/InputStream; -> (Lh;Ljava/lang/String;)Ljava/io/InputStream;
   method signature (Lnet/minecraft/src/TexturePackBase;Ljava/lang/String;)Ljava/awt/image/BufferedImage; -> (Lh;Ljava/lang/String;)Ljava/awt/image/BufferedImage;
   method signature (Lnet/minecraft/src/TexturePackBase;)I -> (Lh;)I
   method signature (Lnet/minecraft/src/TexturePackBase;Ljava/lang/String;)Z -> (Lh;Ljava/lang/String;)Z
   method signature (Lnet/minecraft/src/TexturePackCustom;)V -> (Lahk;)V
   method signature (Lnet/minecraft/src/TexturePackCustom;)V -> (Lahk;)V
   field signature Lnet/minecraft/src/TexturePackBase; -> Lh;
    method ref com.pclewis.mcpatcher.mod.TextureUtils.getSelectedTexturePack ()Lnet/minecraft/src/TexturePackBase; -> com.pclewis.mcpatcher.mod.TextureUtils.getSelectedTexturePack ()Lh; setTileSize()Z@8
     INVOKESTATIC 0x00 0x04    INVOKESTATIC 0x03 0x3a
    method ref com.pclewis.mcpatcher.mod.TextureUtils.getSelectedTexturePack ()Lnet/minecraft/src/TexturePackBase; -> com.pclewis.mcpatcher.mod.TextureUtils.getSelectedTexturePack ()Lh; refreshTextureFX(Ljava/util/List;)V@104
     INVOKESTATIC 0x00 0x04    INVOKESTATIC 0x03 0x3a
    method ref com.pclewis.mcpatcher.mod.TextureUtils.getSelectedTexturePack ()Lnet/minecraft/src/TexturePackBase; -> com.pclewis.mcpatcher.mod.TextureUtils.getSelectedTexturePack ()Lh; getResourceAsStream(Ljava/lang/String;)Ljava/io/InputStream;@0
     INVOKESTATIC 0x00 0x04    INVOKESTATIC 0x03 0x3a
    method ref com.pclewis.mcpatcher.mod.TextureUtils.getSelectedTexturePack ()Lnet/minecraft/src/TexturePackBase; -> com.pclewis.mcpatcher.mod.TextureUtils.getSelectedTexturePack ()Lh; getResourceAsBufferedImage(Ljava/lang/String;)Ljava/awt/image/BufferedImage;@0
     INVOKESTATIC 0x00 0x04    INVOKESTATIC 0x03 0x3a
    method ref com.pclewis.mcpatcher.mod.TextureUtils.getSelectedTexturePack ()Lnet/minecraft/src/TexturePackBase; -> com.pclewis.mcpatcher.mod.TextureUtils.getSelectedTexturePack ()Lh; getTileSize()I@0
     INVOKESTATIC 0x00 0x04    INVOKESTATIC 0x03 0x3a
    method ref com.pclewis.mcpatcher.mod.TextureUtils.getSelectedTexturePack ()Lnet/minecraft/src/TexturePackBase; -> com.pclewis.mcpatcher.mod.TextureUtils.getSelectedTexturePack ()Lh; hasResource(Ljava/lang/String;)Z@0
     INVOKESTATIC 0x00 0x04    INVOKESTATIC 0x03 0x3a
    method ref com.pclewis.mcpatcher.mod.TextureUtils.getTexturePackName (Lnet/minecraft/src/TexturePackBase;)Ljava/lang/String; -> com.pclewis.mcpatcher.mod.TextureUtils.getTexturePackName (Lh;)Ljava/lang/String; setTileSize()Z@11
     INVOKESTATIC 0x00 0x05    INVOKESTATIC 0x03 0x3c
    method ref com.pclewis.mcpatcher.mod.TextureUtils.getTexturePackName (Lnet/minecraft/src/TexturePackBase;)Ljava/lang/String; -> com.pclewis.mcpatcher.mod.TextureUtils.getTexturePackName (Lh;)Ljava/lang/String; getResourceAsBufferedImage(Lh;Ljava/lang/String;)Ljava/awt/image/BufferedImage;@200
     INVOKESTATIC 0x00 0x05    INVOKESTATIC 0x03 0x3c
    field ref net.minecraft.src.FontRenderer.isUnicode Z -> mq.l Z setFontRenderer(Lnet/minecraft/client/Minecraft;Lmq;Ljava/lang/String;)V@1
     GETFIELD 0x00 0x0d        GETFIELD 0x03 0x41
    field ref net.minecraft.src.FontRenderer.isUnicode Z -> mq.l Z setFontRenderer(Lnet/minecraft/client/Minecraft;Lmq;Ljava/lang/String;)V@20
     PUTFIELD 0x00 0x0d        PUTFIELD 0x03 0x41
    field ref net.minecraft.client.Minecraft.gameSettings Lnet/minecraft/src/GameSettings; -> net/minecraft/client/Minecraft.A Lhh; setFontRenderer(Lnet/minecraft/client/Minecraft;Lmq;Ljava/lang/String;)V@7
     GETFIELD 0x00 0x0e        GETFIELD 0x03 0x45
    field ref net.minecraft.client.Minecraft.renderEngine Lnet/minecraft/src/RenderEngine; -> net/minecraft/client/Minecraft.p Lyz; setFontRenderer(Lnet/minecraft/client/Minecraft;Lmq;Ljava/lang/String;)V@12
     GETFIELD 0x00 0x0f        GETFIELD 0x03 0x48
    field ref net.minecraft.client.Minecraft.renderEngine Lnet/minecraft/src/RenderEngine; -> net/minecraft/client/Minecraft.p Lyz; checkTexturePackChange(Lnet/minecraft/client/Minecraft;)V@259
     GETFIELD 0x00 0x0f        GETFIELD 0x03 0x48
    field ref net.minecraft.client.Minecraft.renderEngine Lnet/minecraft/src/RenderEngine; -> net/minecraft/client/Minecraft.p Lyz; checkTexturePackChange(Lnet/minecraft/client/Minecraft;)V@289
     GETFIELD 0x00 0x0f        GETFIELD 0x03 0x48
    method ref net.minecraft.src.FontRenderer.initialize (Lnet/minecraft/src/GameSettings;Ljava/lang/String;Lnet/minecraft/src/RenderEngine;)V -> mq.initialize (Lhh;Ljava/lang/String;Lyz;)V setFontRenderer(Lnet/minecraft/client/Minecraft;Lmq;Ljava/lang/String;)V@15
     INVOKEVIRTUAL 0x00 0x10   INVOKEVIRTUAL 0x03 0x4b
    field ref net.minecraft.client.Minecraft.fontRenderer Lnet/minecraft/src/FontRenderer; -> net/minecraft/client/Minecraft.q Lmq; setFontRenderer()V@15
     GETFIELD 0x00 0x13        GETFIELD 0x03 0x4f
    field ref net.minecraft.client.Minecraft.fontRenderer Lnet/minecraft/src/FontRenderer; -> net/minecraft/client/Minecraft.q Lmq; setFontRenderer()V@28
     GETFIELD 0x00 0x13        GETFIELD 0x03 0x4f
    method ref com.pclewis.mcpatcher.mod.TextureUtils.setFontRenderer (Lnet/minecraft/client/Minecraft;Lnet/minecraft/src/FontRenderer;Ljava/lang/String;)V -> com.pclewis.mcpatcher.mod.TextureUtils.setFontRenderer (Lnet/minecraft/client/Minecraft;Lmq;Ljava/lang/String;)V setFontRenderer()V@20
     INVOKESTATIC 0x00 0x15    INVOKESTATIC 0x03 0x51
    method ref com.pclewis.mcpatcher.mod.TextureUtils.setFontRenderer (Lnet/minecraft/client/Minecraft;Lnet/minecraft/src/FontRenderer;Ljava/lang/String;)V -> com.pclewis.mcpatcher.mod.TextureUtils.setFontRenderer (Lnet/minecraft/client/Minecraft;Lmq;Ljava/lang/String;)V setFontRenderer()V@41
     INVOKESTATIC 0x00 0x15    INVOKESTATIC 0x03 0x51
    field ref net.minecraft.client.Minecraft.alternateFontRenderer Lnet/minecraft/src/FontRenderer; -> net/minecraft/client/Minecraft.r Lmq; setFontRenderer()V@24
     GETFIELD 0x00 0x16        GETFIELD 0x03 0x54
    field ref net.minecraft.client.Minecraft.alternateFontRenderer Lnet/minecraft/src/FontRenderer; -> net/minecraft/client/Minecraft.r Lmq; setFontRenderer()V@36
     GETFIELD 0x00 0x16        GETFIELD 0x03 0x54
    method ref com.pclewis.mcpatcher.mod.TextureUtils.refreshTextureFX (Lnet/minecraft/src/TextureFX;)Lnet/minecraft/src/TextureFX; -> com.pclewis.mcpatcher.mod.TextureUtils.refreshTextureFX (Lsr;)Lsr; registerTextureFX(Ljava/util/List;Lsr;)V@1
     INVOKESTATIC 0x00 0x18    INVOKESTATIC 0x03 0x56
    method ref com.pclewis.mcpatcher.mod.TextureUtils.refreshTextureFX (Lnet/minecraft/src/TextureFX;)Lnet/minecraft/src/TextureFX; -> com.pclewis.mcpatcher.mod.TextureUtils.refreshTextureFX (Lsr;)Lsr; refreshTextureFX(Ljava/util/List;)V@44
     INVOKESTATIC 0x00 0x18    INVOKESTATIC 0x03 0x56
    method ref net.minecraft.src.TextureFX.onTick ()V -> sr.a ()V registerTextureFX(Ljava/util/List;Lsr;)V@37
     INVOKEVIRTUAL 0x00 0x1d   INVOKEVIRTUAL 0x03 0x5b
    method ref net.minecraft.src.TextureFX.onTick ()V -> sr.a ()V refreshTextureFX(Ljava/util/List;)V@704
     INVOKEVIRTUAL 0x00 0x1d   INVOKEVIRTUAL 0x03 0x5b
    class ref net.minecraft.src.Compass -> ss refreshTextureFX(Lsr;)Lsr;@1
     INSTANCEOF 0x00 0x1e      INSTANCEOF 0x03 0x5d
    class ref net.minecraft.src.Compass -> ss refreshTextureFX(Ljava/util/List;)V@75
     NEW 0x00 0x1e             NEW 0x03 0x5d
    class ref net.minecraft.src.Watch -> hg refreshTextureFX(Lsr;)Lsr;@8
     INSTANCEOF 0x00 0x1f      INSTANCEOF 0x03 0x5f
    class ref net.minecraft.src.Watch -> hg refreshTextureFX(Ljava/util/List;)V@90
     NEW 0x00 0x1f             NEW 0x03 0x5f
    class ref net.minecraft.src.StillLava -> bo refreshTextureFX(Lsr;)Lsr;@15
     INSTANCEOF 0x00 0x20      INSTANCEOF 0x03 0x61
    class ref net.minecraft.src.StillLava -> bo refreshTextureFX(Ljava/util/List;)V@194
     NEW 0x00 0x20             NEW 0x03 0x61
    class ref net.minecraft.src.FlowLava -> fv refreshTextureFX(Lsr;)Lsr;@22
     INSTANCEOF 0x00 0x21      INSTANCEOF 0x03 0x63
    class ref net.minecraft.src.FlowLava -> fv refreshTextureFX(Ljava/util/List;)V@208
     NEW 0x00 0x21             NEW 0x03 0x63
    class ref net.minecraft.src.StillWater -> pd refreshTextureFX(Lsr;)Lsr;@29
     INSTANCEOF 0x00 0x22      INSTANCEOF 0x03 0x65
    class ref net.minecraft.src.StillWater -> pd refreshTextureFX(Ljava/util/List;)V@288
     NEW 0x00 0x22             NEW 0x03 0x65
    class ref net.minecraft.src.FlowWater -> ack refreshTextureFX(Lsr;)Lsr;@36
     INSTANCEOF 0x00 0x23      INSTANCEOF 0x03 0x67
    class ref net.minecraft.src.FlowWater -> ack refreshTextureFX(Ljava/util/List;)V@302
     NEW 0x00 0x23             NEW 0x03 0x67
    class ref net.minecraft.src.Fire -> mn refreshTextureFX(Lsr;)Lsr;@43
     INSTANCEOF 0x00 0x24      INSTANCEOF 0x03 0x69
    class ref net.minecraft.src.Fire -> mn refreshTextureFX(Ljava/util/List;)V@396
     NEW 0x00 0x24             NEW 0x03 0x69
    class ref net.minecraft.src.Fire -> mn refreshTextureFX(Ljava/util/List;)V@411
     NEW 0x00 0x24             NEW 0x03 0x69
    class ref net.minecraft.src.Portal -> xs refreshTextureFX(Lsr;)Lsr;@50
     INSTANCEOF 0x00 0x25      INSTANCEOF 0x03 0x6b
    class ref net.minecraft.src.Portal -> xs refreshTextureFX(Ljava/util/List;)V@476
     NEW 0x00 0x25             NEW 0x03 0x6b
    class ref com.pclewis.mcpatcher.mod.CustomAnimation -> com/pclewis/mcpatcher/mod/CustomAnimation refreshTextureFX(Lsr;)Lsr;@57
     INSTANCEOF 0x00 0x26      INSTANCEOF 0x00 0x26
    class ref com.pclewis.mcpatcher.mod.CustomAnimation -> com/pclewis/mcpatcher/mod/CustomAnimation refreshTextureFX(Ljava/util/List;)V@138
     NEW 0x00 0x26             NEW 0x00 0x26
    class ref com.pclewis.mcpatcher.mod.CustomAnimation -> com/pclewis/mcpatcher/mod/CustomAnimation refreshTextureFX(Ljava/util/List;)V@161
     NEW 0x00 0x26             NEW 0x00 0x26
    class ref com.pclewis.mcpatcher.mod.CustomAnimation -> com/pclewis/mcpatcher/mod/CustomAnimation refreshTextureFX(Ljava/util/List;)V@233
     NEW 0x00 0x26             NEW 0x00 0x26
    class ref com.pclewis.mcpatcher.mod.CustomAnimation -> com/pclewis/mcpatcher/mod/CustomAnimation refreshTextureFX(Ljava/util/List;)V@256
     NEW 0x00 0x26             NEW 0x00 0x26
    class ref com.pclewis.mcpatcher.mod.CustomAnimation -> com/pclewis/mcpatcher/mod/CustomAnimation refreshTextureFX(Ljava/util/List;)V@343
     NEW 0x00 0x26             NEW 0x00 0x26
    class ref com.pclewis.mcpatcher.mod.CustomAnimation -> com/pclewis/mcpatcher/mod/CustomAnimation refreshTextureFX(Ljava/util/List;)V@365
     NEW 0x00 0x26             NEW 0x00 0x26
    class ref com.pclewis.mcpatcher.mod.CustomAnimation -> com/pclewis/mcpatcher/mod/CustomAnimation refreshTextureFX(Ljava/util/List;)V@445
     NEW 0x00 0x26             NEW 0x00 0x26
    class ref com.pclewis.mcpatcher.mod.CustomAnimation -> com/pclewis/mcpatcher/mod/CustomAnimation refreshTextureFX(Ljava/util/List;)V@575
     NEW 0x00 0x26             NEW 0x00 0x26
    class ref net.minecraft.src.TextureFX -> sr refreshTextureFX(Lsr;)Lsr;@176
     CHECKCAST 0x00 0x2f       CHECKCAST 0x03 0x58
    class ref net.minecraft.src.TextureFX -> sr refreshTextureFX(Lsr;)Lsr;@209
     CHECKCAST 0x00 0x2f       CHECKCAST 0x03 0x58
    class ref net.minecraft.src.TextureFX -> sr refreshTextureFX(Lsr;)Lsr;@232
     CHECKCAST 0x00 0x2f       CHECKCAST 0x03 0x58
    class ref net.minecraft.src.TextureFX -> sr refreshTextureFX(Ljava/util/List;)V@39
     CHECKCAST 0x00 0x2f       CHECKCAST 0x03 0x58
    class ref net.minecraft.src.TextureFX -> sr refreshTextureFX(Ljava/util/List;)V@655
     CHECKCAST 0x00 0x2f       CHECKCAST 0x03 0x58
    class ref net.minecraft.src.TextureFX -> sr refreshTextureFX(Ljava/util/List;)V@697
     CHECKCAST 0x00 0x2f       CHECKCAST 0x03 0x58
    field ref net.minecraft.src.TextureFX.imageData [B -> sr.f [B refreshTextureFX(Lsr;)Lsr;@263
     GETFIELD 0x00 0x34        GETFIELD 0x03 0x6e
    field ref net.minecraft.src.TextureFX.imageData [B -> sr.f [B refreshTextureFX(Lsr;)Lsr;@289
     GETFIELD 0x00 0x34        GETFIELD 0x03 0x6e
    field ref net.minecraft.src.TextureFX.imageData [B -> sr.f [B refreshTextureFX(Lsr;)Lsr;@315
     PUTFIELD 0x00 0x34        PUTFIELD 0x03 0x6e
    method ref net.minecraft.src.Compass.<init> (Lnet/minecraft/client/Minecraft;)V -> ss.<init> (Lnet/minecraft/client/Minecraft;)V refreshTextureFX(Ljava/util/List;)V@80
     INVOKESPECIAL 0x00 0x3f   INVOKESPECIAL 0x03 0x70
    method ref net.minecraft.src.Watch.<init> (Lnet/minecraft/client/Minecraft;)V -> hg.<init> (Lnet/minecraft/client/Minecraft;)V refreshTextureFX(Ljava/util/List;)V@95
     INVOKESPECIAL 0x00 0x40   INVOKESPECIAL 0x03 0x71
    class ref net.minecraft.src.TexturePackDefault -> kl refreshTextureFX(Ljava/util/List;)V@113
     INSTANCEOF 0x00 0x41      INSTANCEOF 0x03 0x73
    method ref com.pclewis.mcpatcher.mod.CustomAnimation.<init> (IIILjava/lang/String;II)V -> com/pclewis/mcpatcher/mod/CustomAnimation.<init> (IIILjava/lang/String;II)V refreshTextureFX(Ljava/util/List;)V@151
     INVOKESPECIAL 0x00 0x44   INVOKESPECIAL 0x00 0x44
    method ref com.pclewis.mcpatcher.mod.CustomAnimation.<init> (IIILjava/lang/String;II)V -> com/pclewis/mcpatcher/mod/CustomAnimation.<init> (IIILjava/lang/String;II)V refreshTextureFX(Ljava/util/List;)V@175
     INVOKESPECIAL 0x00 0x44   INVOKESPECIAL 0x00 0x44
    method ref com.pclewis.mcpatcher.mod.CustomAnimation.<init> (IIILjava/lang/String;II)V -> com/pclewis/mcpatcher/mod/CustomAnimation.<init> (IIILjava/lang/String;II)V refreshTextureFX(Ljava/util/List;)V@246
     INVOKESPECIAL 0x00 0x44   INVOKESPECIAL 0x00 0x44
    method ref com.pclewis.mcpatcher.mod.CustomAnimation.<init> (IIILjava/lang/String;II)V -> com/pclewis/mcpatcher/mod/CustomAnimation.<init> (IIILjava/lang/String;II)V refreshTextureFX(Ljava/util/List;)V@269
     INVOKESPECIAL 0x00 0x44   INVOKESPECIAL 0x00 0x44
    method ref com.pclewis.mcpatcher.mod.CustomAnimation.<init> (IIILjava/lang/String;II)V -> com/pclewis/mcpatcher/mod/CustomAnimation.<init> (IIILjava/lang/String;II)V refreshTextureFX(Ljava/util/List;)V@355
     INVOKESPECIAL 0x00 0x44   INVOKESPECIAL 0x00 0x44
    method ref com.pclewis.mcpatcher.mod.CustomAnimation.<init> (IIILjava/lang/String;II)V -> com/pclewis/mcpatcher/mod/CustomAnimation.<init> (IIILjava/lang/String;II)V refreshTextureFX(Ljava/util/List;)V@377
     INVOKESPECIAL 0x00 0x44   INVOKESPECIAL 0x00 0x44
    method ref com.pclewis.mcpatcher.mod.CustomAnimation.<init> (IIILjava/lang/String;II)V -> com/pclewis/mcpatcher/mod/CustomAnimation.<init> (IIILjava/lang/String;II)V refreshTextureFX(Ljava/util/List;)V@457
     INVOKESPECIAL 0x00 0x44   INVOKESPECIAL 0x00 0x44
    method ref com.pclewis.mcpatcher.mod.CustomAnimation.<init> (IIILjava/lang/String;II)V -> com/pclewis/mcpatcher/mod/CustomAnimation.<init> (IIILjava/lang/String;II)V refreshTextureFX(Ljava/util/List;)V@611
     INVOKESPECIAL 0x00 0x44   INVOKESPECIAL 0x00 0x44
    method ref net.minecraft.src.StillLava.<init> ()V -> bo.<init> ()V refreshTextureFX(Ljava/util/List;)V@198
     INVOKESPECIAL 0x00 0x47   INVOKESPECIAL 0x03 0x75
    method ref net.minecraft.src.FlowLava.<init> ()V -> fv.<init> ()V refreshTextureFX(Ljava/util/List;)V@212
     INVOKESPECIAL 0x00 0x48   INVOKESPECIAL 0x03 0x76
    method ref net.minecraft.src.StillWater.<init> ()V -> pd.<init> ()V refreshTextureFX(Ljava/util/List;)V@292
     INVOKESPECIAL 0x00 0x4d   INVOKESPECIAL 0x03 0x77
    method ref net.minecraft.src.FlowWater.<init> ()V -> ack.<init> ()V refreshTextureFX(Ljava/util/List;)V@306
     INVOKESPECIAL 0x00 0x4e   INVOKESPECIAL 0x03 0x78
    method ref net.minecraft.src.Fire.<init> (I)V -> mn.<init> (I)V refreshTextureFX(Ljava/util/List;)V@401
     INVOKESPECIAL 0x00 0x56   INVOKESPECIAL 0x03 0x7a
    method ref net.minecraft.src.Fire.<init> (I)V -> mn.<init> (I)V refreshTextureFX(Ljava/util/List;)V@416
     INVOKESPECIAL 0x00 0x56   INVOKESPECIAL 0x03 0x7a
    method ref net.minecraft.src.Portal.<init> ()V -> xs.<init> ()V refreshTextureFX(Ljava/util/List;)V@480
     INVOKESPECIAL 0x00 0x5b   INVOKESPECIAL 0x03 0x7b
    field ref net.minecraft.src.ColorizerWater.colorBuffer [I -> xw.a [I refreshTextureFX(Ljava/util/List;)V@710
     GETSTATIC 0x00 0x68       GETSTATIC 0x03 0x7f
    field ref net.minecraft.src.ColorizerWater.colorBuffer [I -> xw.a [I refreshTextureFX(Ljava/util/List;)V@719
     GETSTATIC 0x00 0x68       GETSTATIC 0x03 0x7f
    field ref net.minecraft.src.ColorizerFoliage.colorBuffer [I -> gk.a [I refreshTextureFX(Ljava/util/List;)V@713
     GETSTATIC 0x00 0x69       GETSTATIC 0x03 0x82
    field ref net.minecraft.src.ColorizerFoliage.colorBuffer [I -> gk.a [I refreshTextureFX(Ljava/util/List;)V@735
     GETSTATIC 0x00 0x69       GETSTATIC 0x03 0x82
    field ref net.minecraft.src.ColorizerGrass.colorBuffer [I -> xy.a [I refreshTextureFX(Ljava/util/List;)V@727
     GETSTATIC 0x00 0x6c       GETSTATIC 0x03 0x85
    field ref net.minecraft.client.Minecraft.texturePackList Lnet/minecraft/src/TexturePackList; -> net/minecraft/client/Minecraft.E Lfy; getSelectedTexturePack()Lh;@13
     GETFIELD 0x00 0x70        GETFIELD 0x03 0x89
    field ref net.minecraft.client.Minecraft.texturePackList Lnet/minecraft/src/TexturePackList; -> net/minecraft/client/Minecraft.E Lfy; getSelectedTexturePack()Lh;@24
     GETFIELD 0x00 0x70        GETFIELD 0x03 0x89
    field ref net.minecraft.client.Minecraft.texturePackList Lnet/minecraft/src/TexturePackList; -> net/minecraft/client/Minecraft.E Lfy; checkTexturePackChange(Lnet/minecraft/client/Minecraft;)V@26
     GETFIELD 0x00 0x70        GETFIELD 0x03 0x89
    field ref net.minecraft.src.TexturePackList.selectedTexturePack Lnet/minecraft/src/TexturePackBase; -> fy.a Lh; getSelectedTexturePack()Lh;@27
     GETFIELD 0x00 0x71        GETFIELD 0x03 0x8d
    field ref net.minecraft.src.TexturePackList.selectedTexturePack Lnet/minecraft/src/TexturePackBase; -> fy.a Lh; checkTexturePackChange(Lnet/minecraft/client/Minecraft;)V@31
     GETFIELD 0x00 0x71        GETFIELD 0x03 0x8d
    field ref net.minecraft.src.TexturePackList.selectedTexturePack Lnet/minecraft/src/TexturePackBase; -> fy.a Lh; checkTexturePackChange(Lnet/minecraft/client/Minecraft;)V@42
     GETFIELD 0x00 0x71        GETFIELD 0x03 0x8d
    field ref net.minecraft.src.TexturePackList.selectedTexturePack Lnet/minecraft/src/TexturePackBase; -> fy.a Lh; checkTexturePackChange(Lnet/minecraft/client/Minecraft;)V@248
     PUTFIELD 0x00 0x71        PUTFIELD 0x03 0x8d
    field ref net.minecraft.src.TexturePackBase.texturePackFileName Ljava/lang/String; -> h.a Ljava/lang/String; getTexturePackName(Lh;)Ljava/lang/String;@10
     GETFIELD 0x00 0x73        GETFIELD 0x03 0x91
    method ref net.minecraft.src.GLAllocation.createDirectByteBuffer (I)Ljava/nio/ByteBuffer; -> ep.c (I)Ljava/nio/ByteBuffer; getByteBuffer(Ljava/nio/ByteBuffer;[B)Ljava/nio/ByteBuffer;@32
     INVOKESTATIC 0x00 0x77    INVOKESTATIC 0x03 0x96
    method ref net.minecraft.src.TexturePackBase.getInputStream (Ljava/lang/String;)Ljava/io/InputStream; -> h.a (Ljava/lang/String;)Ljava/io/InputStream; getResourceAsStream(Lh;Ljava/lang/String;)Ljava/io/InputStream;@8
     INVOKEVIRTUAL 0x00 0x84   INVOKEVIRTUAL 0x03 0x98
    method ref com.pclewis.mcpatcher.mod.TextureUtils.getResourceAsStream (Lnet/minecraft/src/TexturePackBase;Ljava/lang/String;)Ljava/io/InputStream; -> com.pclewis.mcpatcher.mod.TextureUtils.getResourceAsStream (Lh;Ljava/lang/String;)Ljava/io/InputStream; getResourceAsStream(Lh;Ljava/lang/String;)Ljava/io/InputStream;@51
     INVOKESTATIC 0x00 0x88    INVOKESTATIC 0x03 0x9a
    method ref com.pclewis.mcpatcher.mod.TextureUtils.getResourceAsStream (Lnet/minecraft/src/TexturePackBase;Ljava/lang/String;)Ljava/io/InputStream; -> com.pclewis.mcpatcher.mod.TextureUtils.getResourceAsStream (Lh;Ljava/lang/String;)Ljava/io/InputStream; getResourceAsStream(Ljava/lang/String;)Ljava/io/InputStream;@4
     INVOKESTATIC 0x00 0x88    INVOKESTATIC 0x03 0x9a
    method ref com.pclewis.mcpatcher.mod.TextureUtils.getResourceAsStream (Lnet/minecraft/src/TexturePackBase;Ljava/lang/String;)Ljava/io/InputStream; -> com.pclewis.mcpatcher.mod.TextureUtils.getResourceAsStream (Lh;Ljava/lang/String;)Ljava/io/InputStream; getResourceAsBufferedImage(Lh;Ljava/lang/String;)Ljava/awt/image/BufferedImage;@40
     INVOKESTATIC 0x00 0x88    INVOKESTATIC 0x03 0x9a
    method ref com.pclewis.mcpatcher.mod.TextureUtils.getResourceAsStream (Lnet/minecraft/src/TexturePackBase;Ljava/lang/String;)Ljava/io/InputStream; -> com.pclewis.mcpatcher.mod.TextureUtils.getResourceAsStream (Lh;Ljava/lang/String;)Ljava/io/InputStream; getTileSize(Lh;)I@46
     INVOKESTATIC 0x00 0x88    INVOKESTATIC 0x03 0x9a
    method ref com.pclewis.mcpatcher.mod.TextureUtils.getResourceAsStream (Lnet/minecraft/src/TexturePackBase;Ljava/lang/String;)Ljava/io/InputStream; -> com.pclewis.mcpatcher.mod.TextureUtils.getResourceAsStream (Lh;Ljava/lang/String;)Ljava/io/InputStream; hasResource(Lh;Ljava/lang/String;)Z@2
     INVOKESTATIC 0x00 0x88    INVOKESTATIC 0x03 0x9a
    field ref com.pclewis.mcpatcher.mod.TextureUtils.lastTexturePack Lnet/minecraft/src/TexturePackBase; -> com.pclewis.mcpatcher.mod.TextureUtils.lastTexturePack Lh; getResourceAsBufferedImage(Lh;Ljava/lang/String;)Ljava/awt/image/BufferedImage;@11
     GETSTATIC 0x00 0x92       GETSTATIC 0x03 0x9c
    field ref com.pclewis.mcpatcher.mod.TextureUtils.lastTexturePack Lnet/minecraft/src/TexturePackBase; -> com.pclewis.mcpatcher.mod.TextureUtils.lastTexturePack Lh; getResourceAsBufferedImage(Lh;Ljava/lang/String;)Ljava/awt/image/BufferedImage;@125
     GETSTATIC 0x00 0x92       GETSTATIC 0x03 0x9c
    field ref com.pclewis.mcpatcher.mod.TextureUtils.lastTexturePack Lnet/minecraft/src/TexturePackBase; -> com.pclewis.mcpatcher.mod.TextureUtils.lastTexturePack Lh; getResourceAsBufferedImage(Lh;Ljava/lang/String;)Ljava/awt/image/BufferedImage;@283
     PUTSTATIC 0x00 0x92       PUTSTATIC 0x03 0x9c
    field ref com.pclewis.mcpatcher.mod.TextureUtils.lastTexturePack Lnet/minecraft/src/TexturePackBase; -> com.pclewis.mcpatcher.mod.TextureUtils.lastTexturePack Lh; <clinit>()V@11
     PUTSTATIC 0x00 0x92       PUTSTATIC 0x03 0x9c
    method ref com.pclewis.mcpatcher.mod.TextureUtils.getResourceAsBufferedImage (Lnet/minecraft/src/TexturePackBase;Ljava/lang/String;)Ljava/awt/image/BufferedImage; -> com.pclewis.mcpatcher.mod.TextureUtils.getResourceAsBufferedImage (Lh;Ljava/lang/String;)Ljava/awt/image/BufferedImage; getResourceAsBufferedImage(Ljava/lang/String;)Ljava/awt/image/BufferedImage;@4
     INVOKESTATIC 0x00 0xad    INVOKESTATIC 0x03 0x9e
    method ref com.pclewis.mcpatcher.mod.TextureUtils.getTileSize (Lnet/minecraft/src/TexturePackBase;)I -> com.pclewis.mcpatcher.mod.TextureUtils.getTileSize (Lh;)I getTileSize()I@3
     INVOKESTATIC 0x00 0xb7    INVOKESTATIC 0x03 0xa0
    method ref com.pclewis.mcpatcher.mod.TextureUtils.hasResource (Lnet/minecraft/src/TexturePackBase;Ljava/lang/String;)Z -> com.pclewis.mcpatcher.mod.TextureUtils.hasResource (Lh;Ljava/lang/String;)Z hasResource(Ljava/lang/String;)Z@4
     INVOKESTATIC 0x00 0xb8    INVOKESTATIC 0x03 0xa2
    field ref net.minecraft.src.TexturePackCustom.zipFile Ljava/util/zip/ZipFile; -> ahk.e Ljava/util/zip/ZipFile; openTexturePackFile(Lahk;)V@7
     GETFIELD 0x00 0xc0        GETFIELD 0x03 0xa6
    field ref net.minecraft.src.TexturePackCustom.zipFile Ljava/util/zip/ZipFile; -> ahk.e Ljava/util/zip/ZipFile; openTexturePackFile(Lahk;)V@50
     GETFIELD 0x00 0xc0        GETFIELD 0x03 0xa6
    field ref net.minecraft.src.TexturePackCustom.zipFile Ljava/util/zip/ZipFile; -> ahk.e Ljava/util/zip/ZipFile; openTexturePackFile(Lahk;)V@136
     GETFIELD 0x00 0xc0        GETFIELD 0x03 0xa6
    field ref net.minecraft.src.TexturePackCustom.zipFile Ljava/util/zip/ZipFile; -> ahk.e Ljava/util/zip/ZipFile; openTexturePackFile(Lahk;)V@144
     PUTFIELD 0x00 0xc0        PUTFIELD 0x03 0xa6
    field ref net.minecraft.src.TexturePackCustom.zipFile Ljava/util/zip/ZipFile; -> ahk.e Ljava/util/zip/ZipFile; closeTexturePackFile(Lahk;)V@8
     GETFIELD 0x00 0xc0        GETFIELD 0x03 0xa6
    field ref net.minecraft.src.TexturePackCustom.zipFile Ljava/util/zip/ZipFile; -> ahk.e Ljava/util/zip/ZipFile; closeTexturePackFile(Lahk;)V@19
     PUTFIELD 0x00 0xc0        PUTFIELD 0x03 0xa6
    field ref net.minecraft.src.TexturePackCustom.file Ljava/io/File; -> ahk.h Ljava/io/File; openTexturePackFile(Lahk;)V@22
     GETFIELD 0x00 0xc1        GETFIELD 0x03 0xa8
    field ref net.minecraft.src.TexturePackCustom.file Ljava/io/File; -> ahk.h Ljava/io/File; openTexturePackFile(Lahk;)V@61
     GETFIELD 0x00 0xc1        GETFIELD 0x03 0xa8
    field ref net.minecraft.src.TexturePackCustom.file Ljava/io/File; -> ahk.h Ljava/io/File; openTexturePackFile(Lahk;)V@158
     GETFIELD 0x00 0xc1        GETFIELD 0x03 0xa8
    field ref net.minecraft.src.TexturePackCustom.file Ljava/io/File; -> ahk.h Ljava/io/File; checkTexturePackChange(Lnet/minecraft/client/Minecraft;)V@50
     GETFIELD 0x00 0xc1        GETFIELD 0x03 0xa8
    field ref net.minecraft.src.TexturePackCustom.file Ljava/io/File; -> ahk.h Ljava/io/File; checkTexturePackChange(Lnet/minecraft/client/Minecraft;)V@91
     GETFIELD 0x00 0xc1        GETFIELD 0x03 0xa8
    field ref net.minecraft.src.TexturePackCustom.file Ljava/io/File; -> ahk.h Ljava/io/File; checkTexturePackChange(Lnet/minecraft/client/Minecraft;)V@126
     GETFIELD 0x00 0xc1        GETFIELD 0x03 0xa8
    field ref net.minecraft.src.TexturePackCustom.file Ljava/io/File; -> ahk.h Ljava/io/File; checkTexturePackChange(Lnet/minecraft/client/Minecraft;)V@221
     GETFIELD 0x00 0xc1        GETFIELD 0x03 0xa8
    field ref net.minecraft.src.TexturePackCustom.file Ljava/io/File; -> ahk.h Ljava/io/File; checkTexturePackChange(Lnet/minecraft/client/Minecraft;)V@225
     GETFIELD 0x00 0xc1        GETFIELD 0x03 0xa8
    field ref net.minecraft.src.TexturePackCustom.lastModified J -> ahk.lastModified J openTexturePackFile(Lahk;)V@28
     PUTFIELD 0x00 0xc3        PUTFIELD 0x03 0xaa
    field ref net.minecraft.src.TexturePackCustom.lastModified J -> ahk.lastModified J openTexturePackFile(Lahk;)V@178
     GETFIELD 0x00 0xc3        GETFIELD 0x03 0xaa
    field ref net.minecraft.src.TexturePackCustom.lastModified J -> ahk.lastModified J checkTexturePackChange(Lnet/minecraft/client/Minecraft;)V@59
     GETFIELD 0x00 0xc3        GETFIELD 0x03 0xaa
    field ref net.minecraft.src.TexturePackCustom.lastModified J -> ahk.lastModified J checkTexturePackChange(Lnet/minecraft/client/Minecraft;)V@73
     GETFIELD 0x00 0xc3        GETFIELD 0x03 0xaa
    field ref net.minecraft.src.TexturePackCustom.lastModified J -> ahk.lastModified J checkTexturePackChange(Lnet/minecraft/client/Minecraft;)V@101
     GETFIELD 0x00 0xc3        GETFIELD 0x03 0xaa
    field ref net.minecraft.src.TexturePackCustom.tmpFile Ljava/io/File; -> ahk.tmpFile Ljava/io/File; openTexturePackFile(Lahk;)V@39
     PUTFIELD 0x00 0xc7        PUTFIELD 0x03 0xac
    field ref net.minecraft.src.TexturePackCustom.tmpFile Ljava/io/File; -> ahk.tmpFile Ljava/io/File; openTexturePackFile(Lahk;)V@43
     GETFIELD 0x00 0xc7        GETFIELD 0x03 0xac
    field ref net.minecraft.src.TexturePackCustom.tmpFile Ljava/io/File; -> ahk.tmpFile Ljava/io/File; openTexturePackFile(Lahk;)V@73
     GETFIELD 0x00 0xc7        GETFIELD 0x03 0xac
    field ref net.minecraft.src.TexturePackCustom.tmpFile Ljava/io/File; -> ahk.tmpFile Ljava/io/File; openTexturePackFile(Lahk;)V@127
     GETFIELD 0x00 0xc7        GETFIELD 0x03 0xac
    field ref net.minecraft.src.TexturePackCustom.tmpFile Ljava/io/File; -> ahk.tmpFile Ljava/io/File; openTexturePackFile(Lahk;)V@168
     GETFIELD 0x00 0xc7        GETFIELD 0x03 0xac
    field ref net.minecraft.src.TexturePackCustom.tmpFile Ljava/io/File; -> ahk.tmpFile Ljava/io/File; closeTexturePackFile(Lahk;)V@28
     GETFIELD 0x00 0xc7        GETFIELD 0x03 0xac
    field ref net.minecraft.src.TexturePackCustom.tmpFile Ljava/io/File; -> ahk.tmpFile Ljava/io/File; closeTexturePackFile(Lahk;)V@44
     GETFIELD 0x00 0xc7        GETFIELD 0x03 0xac
    field ref net.minecraft.src.TexturePackCustom.tmpFile Ljava/io/File; -> ahk.tmpFile Ljava/io/File; closeTexturePackFile(Lahk;)V@56
     PUTFIELD 0x00 0xc7        PUTFIELD 0x03 0xac
    field ref net.minecraft.src.TexturePackCustom.origZip Ljava/util/zip/ZipFile; -> ahk.origZip Ljava/util/zip/ZipFile; openTexturePackFile(Lahk;)V@139
     PUTFIELD 0x00 0xd3        PUTFIELD 0x03 0xae
    field ref net.minecraft.src.TexturePackCustom.origZip Ljava/util/zip/ZipFile; -> ahk.origZip Ljava/util/zip/ZipFile; closeTexturePackFile(Lahk;)V@1
     GETFIELD 0x00 0xd3        GETFIELD 0x03 0xae
    field ref net.minecraft.src.TexturePackCustom.origZip Ljava/util/zip/ZipFile; -> ahk.origZip Ljava/util/zip/ZipFile; closeTexturePackFile(Lahk;)V@16
     GETFIELD 0x00 0xd3        GETFIELD 0x03 0xae
    field ref net.minecraft.src.TexturePackCustom.origZip Ljava/util/zip/ZipFile; -> ahk.origZip Ljava/util/zip/ZipFile; closeTexturePackFile(Lahk;)V@24
     PUTFIELD 0x00 0xd3        PUTFIELD 0x03 0xae
    class ref net.minecraft.src.TexturePackCustom -> ahk checkTexturePackChange(Lnet/minecraft/client/Minecraft;)V@34
     INSTANCEOF 0x00 0xda      INSTANCEOF 0x03 0xa4
    class ref net.minecraft.src.TexturePackCustom -> ahk checkTexturePackChange(Lnet/minecraft/client/Minecraft;)V@45
     CHECKCAST 0x00 0xda       CHECKCAST 0x03 0xa4
    class ref net.minecraft.src.TexturePackCustom -> ahk checkTexturePackChange(Lnet/minecraft/client/Minecraft;)V@203
     INSTANCEOF 0x00 0xda      INSTANCEOF 0x03 0xa4
    class ref net.minecraft.src.TexturePackCustom -> ahk checkTexturePackChange(Lnet/minecraft/client/Minecraft;)V@214
     CHECKCAST 0x00 0xda       CHECKCAST 0x03 0xa4
    method ref net.minecraft.src.TexturePackCustom.closeTexturePackFile ()V -> ahk.b ()V checkTexturePackChange(Lnet/minecraft/client/Minecraft;)V@161
     INVOKEVIRTUAL 0x00 0xdc   INVOKEVIRTUAL 0x03 0xb1
    method ref net.minecraft.src.TexturePackList.updateAvailableTexturePacks ()V -> fy.a ()V checkTexturePackChange(Lnet/minecraft/client/Minecraft;)V@165
     INVOKEVIRTUAL 0x00 0xdd   INVOKEVIRTUAL 0x03 0xb2
    method ref net.minecraft.src.TexturePackList.availableTexturePacks ()Ljava/util/List; -> fy.b ()Ljava/util/List; checkTexturePackChange(Lnet/minecraft/client/Minecraft;)V@169
     INVOKEVIRTUAL 0x00 0xde   INVOKEVIRTUAL 0x03 0xb4
    class ref net.minecraft.src.TexturePackBase -> h checkTexturePackChange(Lnet/minecraft/client/Minecraft;)V@196
     CHECKCAST 0x00 0xdf       CHECKCAST 0x03 0x8f
    field ref net.minecraft.src.TexturePackList.defaultTexturePack Lnet/minecraft/src/TexturePackBase; -> fy.c Lh; checkTexturePackChange(Lnet/minecraft/client/Minecraft;)V@245
     GETFIELD 0x00 0xe2        GETFIELD 0x03 0xb6
    field ref net.minecraft.src.TexturePackList.defaultTexturePack Lnet/minecraft/src/TexturePackBase; -> fy.c Lh; checkTexturePackChange(Lnet/minecraft/client/Minecraft;)V@281
     GETFIELD 0x00 0xe2        GETFIELD 0x03 0xb6
    method ref net.minecraft.src.TexturePackList.setTexturePack (Lnet/minecraft/src/TexturePackBase;)Z -> fy.a (Lh;)Z checkTexturePackChange(Lnet/minecraft/client/Minecraft;)V@254
     INVOKEVIRTUAL 0x00 0xe3   INVOKEVIRTUAL 0x03 0xb9
    method ref net.minecraft.src.TexturePackList.setTexturePack (Lnet/minecraft/src/TexturePackBase;)Z -> fy.a (Lh;)Z checkTexturePackChange(Lnet/minecraft/client/Minecraft;)V@284
     INVOKEVIRTUAL 0x00 0xe3   INVOKEVIRTUAL 0x03 0xb9
    method ref net.minecraft.src.RenderEngine.setTileSize (Lnet/minecraft/client/Minecraft;)V -> yz.setTileSize (Lnet/minecraft/client/Minecraft;)V checkTexturePackChange(Lnet/minecraft/client/Minecraft;)V@263
     INVOKEVIRTUAL 0x00 0xe4   INVOKEVIRTUAL 0x03 0xbd
    method ref net.minecraft.src.RenderEngine.setTileSize (Lnet/minecraft/client/Minecraft;)V -> yz.setTileSize (Lnet/minecraft/client/Minecraft;)V checkTexturePackChange(Lnet/minecraft/client/Minecraft;)V@293
     INVOKEVIRTUAL 0x00 0xe4   INVOKEVIRTUAL 0x03 0xbd
   string replace Lnet/minecraft/src/TexturePackCustom; -> Lahk; @8380
   string replace Lnet/minecraft/src/TexturePackList; -> Lfy; @9438
   string replace Lnet/minecraft/src/FontRenderer; -> Lmq; @844
   string replace Lnet/minecraft/src/TexturePackBase; -> Lh; @3107
   string replace Lnet/minecraft/src/TextureFX; -> Lsr; @1335
  adding com/pclewis/mcpatcher/mod/CustomAnimation.class for HD Textures
   method onTick -> a
    field ref com.pclewis.mcpatcher.mod.CustomAnimation.rand Ljava/util/Random; -> com/pclewis/mcpatcher/mod/CustomAnimation.rand Ljava/util/Random; access$100()Ljava/util/Random;@0
     GETSTATIC 0x00 0x01       GETSTATIC 0x00 0x01
    field ref com.pclewis.mcpatcher.mod.CustomAnimation.rand Ljava/util/Random; -> com/pclewis/mcpatcher/mod/CustomAnimation.rand Ljava/util/Random; <clinit>()V@7
     PUTSTATIC 0x00 0x01       PUTSTATIC 0x00 0x01
    method ref com.pclewis.mcpatcher.mod.CustomAnimation.ARGBtoRGBA ([I[B)V -> com/pclewis/mcpatcher/mod/CustomAnimation.ARGBtoRGBA ([I[B)V access$000([I[B)V@2
     INVOKESTATIC 0x00 0x02    INVOKESTATIC 0x00 0x02
    method ref net.minecraft.src.TextureFX.<init> (I)V -> sr.<init> (I)V <init>(IIILjava/lang/String;II)V@2
     INVOKESPECIAL 0x00 0x03   INVOKESPECIAL 0x00 0xa8
    field ref com.pclewis.mcpatcher.mod.CustomAnimation.tileNumber I -> com/pclewis/mcpatcher/mod/CustomAnimation.g I <init>(IIILjava/lang/String;II)V@7
     PUTFIELD 0x00 0x04        PUTFIELD 0x00 0xab
    field ref com.pclewis.mcpatcher.mod.CustomAnimation.tileNumber I -> com/pclewis/mcpatcher/mod/CustomAnimation.g I <init>(IIILjava/lang/String;II)V@114
     GETFIELD 0x00 0x04        GETFIELD 0x00 0xab
    field ref com.pclewis.mcpatcher.mod.CustomAnimation.tileImage I -> com/pclewis/mcpatcher/mod/CustomAnimation.k I <init>(IIILjava/lang/String;II)V@12
     PUTFIELD 0x00 0x05        PUTFIELD 0x00 0xae
    field ref com.pclewis.mcpatcher.mod.CustomAnimation.tileSize I -> com/pclewis/mcpatcher/mod/CustomAnimation.j I <init>(IIILjava/lang/String;II)V@17
     PUTFIELD 0x00 0x06        PUTFIELD 0x00 0xb1
    field ref com.pclewis.mcpatcher.mod.CustomAnimation.imageData [B -> com/pclewis/mcpatcher/mod/CustomAnimation.f [B <init>(IIILjava/lang/String;II)V@103
     GETFIELD 0x00 0x13        GETFIELD 0x00 0xb4
    field ref com.pclewis.mcpatcher.mod.CustomAnimation.delegate Lcom/pclewis/mcpatcher/mod/CustomAnimation$Delegate; -> com/pclewis/mcpatcher/mod/CustomAnimation.delegate Lcom/pclewis/mcpatcher/mod/CustomAnimation$Delegate; <init>(IIILjava/lang/String;II)V@145
     PUTFIELD 0x00 0x18        PUTFIELD 0x00 0x18
    field ref com.pclewis.mcpatcher.mod.CustomAnimation.delegate Lcom/pclewis/mcpatcher/mod/CustomAnimation$Delegate; -> com/pclewis/mcpatcher/mod/CustomAnimation.delegate Lcom/pclewis/mcpatcher/mod/CustomAnimation$Delegate; <init>(IIILjava/lang/String;II)V@238
     PUTFIELD 0x00 0x18        PUTFIELD 0x00 0x18
    field ref com.pclewis.mcpatcher.mod.CustomAnimation.delegate Lcom/pclewis/mcpatcher/mod/CustomAnimation$Delegate; -> com/pclewis/mcpatcher/mod/CustomAnimation.delegate Lcom/pclewis/mcpatcher/mod/CustomAnimation$Delegate; a()V@1
     GETFIELD 0x00 0x18        GETFIELD 0x00 0x18
   string replace net/minecraft/src/TextureFX -> sr @58
  adding com/pclewis/mcpatcher/mod/CustomAnimation$Delegate.class for HD Textures
  adding com/pclewis/mcpatcher/mod/CustomAnimation$Tile.class for HD Textures
    field ref com.pclewis.mcpatcher.mod.CustomAnimation.imageData [B -> com/pclewis/mcpatcher/mod/CustomAnimation.f [B <init>(Lcom/pclewis/mcpatcher/mod/CustomAnimation;Ljava/lang/String;III)V@154
     GETFIELD 0x00 0x0f        GETFIELD 0x00 0x72
    field ref com.pclewis.mcpatcher.mod.CustomAnimation.imageData [B -> com/pclewis/mcpatcher/mod/CustomAnimation.f [B onTick()V@65
     GETFIELD 0x00 0x0f        GETFIELD 0x00 0x72
    field ref com.pclewis.mcpatcher.mod.CustomAnimation.imageData [B -> com/pclewis/mcpatcher/mod/CustomAnimation.f [B onTick()V@88
     GETFIELD 0x00 0x0f        GETFIELD 0x00 0x72
    field ref com.pclewis.mcpatcher.mod.CustomAnimation.imageData [B -> com/pclewis/mcpatcher/mod/CustomAnimation.f [B onTick()V@96
     GETFIELD 0x00 0x0f        GETFIELD 0x00 0x72
    field ref com.pclewis.mcpatcher.mod.CustomAnimation.imageData [B -> com/pclewis/mcpatcher/mod/CustomAnimation.f [B onTick()V@119
     GETFIELD 0x00 0x0f        GETFIELD 0x00 0x72
    method ref com.pclewis.mcpatcher.mod.CustomAnimation.access$000 ([I[B)V -> com/pclewis/mcpatcher/mod/CustomAnimation.access$000 ([I[B)V <init>(Lcom/pclewis/mcpatcher/mod/CustomAnimation;Ljava/lang/String;III)V@157
     INVOKESTATIC 0x00 0x10    INVOKESTATIC 0x00 0x10
    method ref com.pclewis.mcpatcher.mod.CustomAnimation.access$100 ()Ljava/util/Random; -> com/pclewis/mcpatcher/mod/CustomAnimation.access$100 ()Ljava/util/Random; onTick()V@36
     INVOKESTATIC 0x00 0x12    INVOKESTATIC 0x00 0x12
  adding com/pclewis/mcpatcher/mod/CustomAnimation$Strip.class for HD Textures
    method ref com.pclewis.mcpatcher.mod.CustomAnimation.access$000 ([I[B)V -> com/pclewis/mcpatcher/mod/CustomAnimation.access$000 ([I[B)V <init>(Lcom/pclewis/mcpatcher/mod/CustomAnimation;Ljava/awt/image/BufferedImage;Ljava/util/Properties;)V@91
     INVOKESTATIC 0x00 0x0b    INVOKESTATIC 0x00 0x0b
    field ref com.pclewis.mcpatcher.mod.CustomAnimation.imageData [B -> com/pclewis/mcpatcher/mod/CustomAnimation.f [B onTick()V@60
     GETFIELD 0x00 0x24        GETFIELD 0x00 0xad
  adding com/pclewis/mcpatcher/mod/FontUtils.class for HD Font
  adding com/pclewis/mcpatcher/mod/MobRandomizer.class for Random Mobs
   method signature (Lnet/minecraft/src/Entity;)Ljava/lang/String; -> (Lms;)Ljava/lang/String;
   method signature (Lnet/minecraft/src/Entity;Ljava/lang/String;)Ljava/lang/String; -> (Lms;Ljava/lang/String;)Ljava/lang/String;
   field signature Lnet/minecraft/src/TexturePackBase; -> Lh;
    method ref net.minecraft.src.Entity.getEntityTexture ()Ljava/lang/String; -> ms.M ()Ljava/lang/String; randomTexture(Lms;)Ljava/lang/String;@2
     INVOKEVIRTUAL 0x00 0x07   INVOKEVIRTUAL 0x00 0xc2
    method ref com.pclewis.mcpatcher.mod.MobRandomizer.randomTexture (Lnet/minecraft/src/Entity;Ljava/lang/String;)Ljava/lang/String; -> com.pclewis.mcpatcher.mod.MobRandomizer.randomTexture (Lms;Ljava/lang/String;)Ljava/lang/String; randomTexture(Lms;)Ljava/lang/String;@5
     INVOKESTATIC 0x00 0x08    INVOKESTATIC 0x00 0xc4
    field ref net.minecraft.client.Minecraft.texturePackList Lnet/minecraft/src/TexturePackList; -> net/minecraft/client/Minecraft.E Lfy; randomTexture(Lms;Ljava/lang/String;)Ljava/lang/String;@3
     GETFIELD 0x00 0x0a        GETFIELD 0x00 0xc8
    field ref net.minecraft.src.TexturePackList.selectedTexturePack Lnet/minecraft/src/TexturePackBase; -> fy.a Lh; randomTexture(Lms;Ljava/lang/String;)Ljava/lang/String;@6
     GETFIELD 0x00 0x0b        GETFIELD 0x00 0xcd
    field ref com.pclewis.mcpatcher.mod.MobRandomizer.lastTexturePack Lnet/minecraft/src/TexturePackBase; -> com.pclewis.mcpatcher.mod.MobRandomizer.lastTexturePack Lh; randomTexture(Lms;Ljava/lang/String;)Ljava/lang/String;@10
     GETSTATIC 0x00 0x0c       GETSTATIC 0x00 0xcf
    field ref com.pclewis.mcpatcher.mod.MobRandomizer.lastTexturePack Lnet/minecraft/src/TexturePackBase; -> com.pclewis.mcpatcher.mod.MobRandomizer.lastTexturePack Lh; randomTexture(Lms;Ljava/lang/String;)Ljava/lang/String;@18
     PUTSTATIC 0x00 0x0c       PUTSTATIC 0x00 0xcf
    field ref com.pclewis.mcpatcher.mod.MobRandomizer.lastTexturePack Lnet/minecraft/src/TexturePackBase; -> com.pclewis.mcpatcher.mod.MobRandomizer.lastTexturePack Lh; randomTexture(Lms;Ljava/lang/String;)Ljava/lang/String;@24
     GETSTATIC 0x00 0x0c       GETSTATIC 0x00 0xcf
    field ref com.pclewis.mcpatcher.mod.MobRandomizer.lastTexturePack Lnet/minecraft/src/TexturePackBase; -> com.pclewis.mcpatcher.mod.MobRandomizer.lastTexturePack Lh; randomTexture(Lms;Ljava/lang/String;)Ljava/lang/String;@121
     GETSTATIC 0x00 0x0c       GETSTATIC 0x00 0xcf
    method ref net.minecraft.src.TexturePackBase.getInputStream (Ljava/lang/String;)Ljava/io/InputStream; -> h.a (Ljava/lang/String;)Ljava/io/InputStream; randomTexture(Lms;Ljava/lang/String;)Ljava/lang/String;@126
     INVOKEVIRTUAL 0x00 0x1d   INVOKEVIRTUAL 0x00 0xd3
    field ref net.minecraft.src.Entity.randomMobsSkinSet Z -> ms.randomMobsSkinSet Z randomTexture(Lms;Ljava/lang/String;)Ljava/lang/String;@226
     GETFIELD 0x00 0x24        GETFIELD 0x00 0xd5
    field ref net.minecraft.src.Entity.randomMobsSkinSet Z -> ms.randomMobsSkinSet Z randomTexture(Lms;Ljava/lang/String;)Ljava/lang/String;@245
     PUTFIELD 0x00 0x24        PUTFIELD 0x00 0xd5
    field ref net.minecraft.src.Entity.entityId I -> ms.f I randomTexture(Lms;Ljava/lang/String;)Ljava/lang/String;@234
     GETFIELD 0x00 0x25        GETFIELD 0x00 0xd8
    field ref net.minecraft.src.Entity.randomMobsSkin J -> ms.randomMobsSkin J randomTexture(Lms;Ljava/lang/String;)Ljava/lang/String;@240
     PUTFIELD 0x00 0x27        PUTFIELD 0x00 0xda
    field ref net.minecraft.src.Entity.randomMobsSkin J -> ms.randomMobsSkin J randomTexture(Lms;Ljava/lang/String;)Ljava/lang/String;@249
     GETFIELD 0x00 0x27        GETFIELD 0x00 0xda
   string replace Lnet/minecraft/src/TexturePackBase; -> Lh; @781
   string replace Lnet/minecraft/src/Entity; -> Lms; @478
  adding com/pclewis/mcpatcher/mod/Colorizer.class for Custom Colors
   method signature (IILnet/minecraft/src/WorldChunkManager;III)I -> (IILqu;III)I
   method signature (Lnet/minecraft/src/WorldChunkManager;II)I -> (Lqu;II)I
   method signature (Lnet/minecraft/src/Block;Lnet/minecraft/src/WorldChunkManager;III)I -> (Loe;Lqu;III)I
   method signature (Lnet/minecraft/src/Block;)I -> (Loe;)I
   method signature (Lnet/minecraft/src/EntityRenderer;Lnet/minecraft/src/World;)Z -> (Lkz;Lvq;)Z
   method signature (Lnet/minecraft/src/WorldChunkManager;DDD)Z -> (Lqu;DDD)Z
   method signature (Lnet/minecraft/src/WorldChunkManager;Lnet/minecraft/src/Entity;)V -> (Lqu;Lms;)V
   method signature (Lnet/minecraft/src/World;)Z -> (Lvq;)Z
   method signature (Lnet/minecraft/src/BiomeGenBase;)V -> (Lzp;)V
   method signature (Lnet/minecraft/src/Potion;)V -> (Lyg;)V
   method signature (Ljava/lang/String;Lnet/minecraft/src/Potion;)V -> (Ljava/lang/String;Lyg;)V
   field signature Lnet/minecraft/src/TexturePackBase; -> Lh;
   field signature Lnet/minecraft/src/Entity; -> Lms;
   field signature Lnet/minecraft/src/WorldChunkManager; -> Lqu;
    method ref net.minecraft.src.WorldChunkManager.getTemperature (III)F -> qu.a (III)F colorizeBiome(IILqu;III)I@11
     INVOKEVIRTUAL 0x00 0x08   INVOKEVIRTUAL 0x03 0x31
    method ref net.minecraft.src.WorldChunkManager.getRainfall (II)F -> qu.b (II)F colorizeBiome(IILqu;III)I@19
     INVOKEVIRTUAL 0x00 0x09   INVOKEVIRTUAL 0x03 0x34
    method ref net.minecraft.src.WorldChunkManager.getBiomeGenAt (II)Lnet/minecraft/src/BiomeGenBase; -> qu.a (II)Lzp; colorizeWater(Lqu;II)I@3
     INVOKEVIRTUAL 0x00 0x0b   INVOKEVIRTUAL 0x03 0x37
    field ref net.minecraft.src.BiomeGenBase.waterColorMultiplier I -> zp.F I colorizeWater(Lqu;II)I@6
     GETFIELD 0x00 0x0c        GETFIELD 0x03 0x3b
    field ref net.minecraft.src.BiomeGenBase.waterColorMultiplier I -> zp.F I setupForFog(Lqu;Lms;)V@103
     GETFIELD 0x00 0x0c        GETFIELD 0x03 0x3b
    method ref com.pclewis.mcpatcher.mod.Colorizer.colorizeBiome (IILnet/minecraft/src/WorldChunkManager;III)I -> com.pclewis.mcpatcher.mod.Colorizer.colorizeBiome (IILqu;III)I colorizeWater(Lqu;II)I@15
     INVOKESTATIC 0x00 0x0d    INVOKESTATIC 0x03 0x3d
    method ref com.pclewis.mcpatcher.mod.Colorizer.colorizeBiome (IILnet/minecraft/src/WorldChunkManager;III)I -> com.pclewis.mcpatcher.mod.Colorizer.colorizeBiome (IILqu;III)I colorizeBlock(Loe;Lqu;III)I@16
     INVOKESTATIC 0x00 0x0d    INVOKESTATIC 0x03 0x3d
    method ref com.pclewis.mcpatcher.mod.Colorizer.colorizeBiome (IILnet/minecraft/src/WorldChunkManager;III)I -> com.pclewis.mcpatcher.mod.Colorizer.colorizeBiome (IILqu;III)I computeWaterColor(Lqu;DDD)Z@20
     INVOKESTATIC 0x00 0x0d    INVOKESTATIC 0x03 0x3d
    method ref com.pclewis.mcpatcher.mod.Colorizer.colorizeBiome (IILnet/minecraft/src/WorldChunkManager;III)I -> com.pclewis.mcpatcher.mod.Colorizer.colorizeBiome (IILqu;III)I computeFogColor(I)Z@115
     INVOKESTATIC 0x00 0x0d    INVOKESTATIC 0x03 0x3d
    field ref net.minecraft.src.Block.blockID I -> oe.bO I colorizeBlock(Loe;Lqu;III)I@7
     GETFIELD 0x00 0x11        GETFIELD 0x03 0x42
    field ref net.minecraft.src.Block.blockID I -> oe.bO I colorizeBlock(Loe;)I@7
     GETFIELD 0x00 0x11        GETFIELD 0x03 0x42
    field ref net.minecraft.src.World.worldProvider Lnet/minecraft/src/WorldProvider; -> vq.y Laip; computeLightmap(Lkz;Lvq;)Z@16
     GETFIELD 0x00 0x2a        GETFIELD 0x03 0x47
    field ref net.minecraft.src.World.worldProvider Lnet/minecraft/src/WorldProvider; -> vq.y Laip; computeSkyColor(Lvq;)Z@1
     GETFIELD 0x00 0x2a        GETFIELD 0x03 0x47
    field ref net.minecraft.src.WorldProvider.worldType I -> aip.h I computeLightmap(Lkz;Lvq;)Z@19
     GETFIELD 0x00 0x2b        GETFIELD 0x03 0x4c
    field ref net.minecraft.src.WorldProvider.worldType I -> aip.h I computeSkyColor(Lvq;)Z@4
     GETFIELD 0x00 0x2b        GETFIELD 0x03 0x4c
    field ref com.pclewis.mcpatcher.mod.Colorizer.lastTexturePack Lnet/minecraft/src/TexturePackBase; -> com.pclewis.mcpatcher.mod.Colorizer.lastTexturePack Lh; computeLightmap(Lkz;Lvq;)Z@71
     GETSTATIC 0x00 0x31       GETSTATIC 0x03 0x4e
    field ref com.pclewis.mcpatcher.mod.Colorizer.lastTexturePack Lnet/minecraft/src/TexturePackBase; -> com.pclewis.mcpatcher.mod.Colorizer.lastTexturePack Lh; checkUpdate()V@0
     GETSTATIC 0x00 0x31       GETSTATIC 0x03 0x4e
    field ref com.pclewis.mcpatcher.mod.Colorizer.lastTexturePack Lnet/minecraft/src/TexturePackBase; -> com.pclewis.mcpatcher.mod.Colorizer.lastTexturePack Lh; checkUpdate()V@25
     PUTSTATIC 0x00 0x31       PUTSTATIC 0x03 0x4e
    field ref com.pclewis.mcpatcher.mod.Colorizer.lastTexturePack Lnet/minecraft/src/TexturePackBase; -> com.pclewis.mcpatcher.mod.Colorizer.lastTexturePack Lh; checkUpdate()V@289
     GETSTATIC 0x00 0x31       GETSTATIC 0x03 0x4e
    field ref com.pclewis.mcpatcher.mod.Colorizer.lastTexturePack Lnet/minecraft/src/TexturePackBase; -> com.pclewis.mcpatcher.mod.Colorizer.lastTexturePack Lh; checkUpdate()V@780
     GETSTATIC 0x00 0x31       GETSTATIC 0x03 0x4e
    field ref com.pclewis.mcpatcher.mod.Colorizer.lastTexturePack Lnet/minecraft/src/TexturePackBase; -> com.pclewis.mcpatcher.mod.Colorizer.lastTexturePack Lh; checkUpdate()V@845
     GETSTATIC 0x00 0x31       GETSTATIC 0x03 0x4e
    field ref com.pclewis.mcpatcher.mod.Colorizer.lastTexturePack Lnet/minecraft/src/TexturePackBase; -> com.pclewis.mcpatcher.mod.Colorizer.lastTexturePack Lh; checkUpdate()V@921
     GETSTATIC 0x00 0x31       GETSTATIC 0x03 0x4e
    field ref com.pclewis.mcpatcher.mod.Colorizer.lastTexturePack Lnet/minecraft/src/TexturePackBase; -> com.pclewis.mcpatcher.mod.Colorizer.lastTexturePack Lh; loadColorMap(Ljava/lang/String;)[I@0
     GETSTATIC 0x00 0x31       GETSTATIC 0x03 0x4e
    method ref net.minecraft.src.TexturePackBase.getInputStream (Ljava/lang/String;)Ljava/io/InputStream; -> h.a (Ljava/lang/String;)Ljava/io/InputStream; computeLightmap(Lkz;Lvq;)Z@75
     INVOKEVIRTUAL 0x00 0x32   INVOKEVIRTUAL 0x03 0x51
    method ref net.minecraft.src.TexturePackBase.getInputStream (Ljava/lang/String;)Ljava/io/InputStream; -> h.a (Ljava/lang/String;)Ljava/io/InputStream; checkUpdate()V@294
     INVOKEVIRTUAL 0x00 0x32   INVOKEVIRTUAL 0x03 0x51
    method ref net.minecraft.src.TexturePackBase.getInputStream (Ljava/lang/String;)Ljava/io/InputStream; -> h.a (Ljava/lang/String;)Ljava/io/InputStream; checkUpdate()V@785
     INVOKEVIRTUAL 0x00 0x32   INVOKEVIRTUAL 0x03 0x51
    method ref net.minecraft.src.TexturePackBase.getInputStream (Ljava/lang/String;)Ljava/io/InputStream; -> h.a (Ljava/lang/String;)Ljava/io/InputStream; checkUpdate()V@850
     INVOKEVIRTUAL 0x00 0x32   INVOKEVIRTUAL 0x03 0x51
    method ref net.minecraft.src.TexturePackBase.getInputStream (Ljava/lang/String;)Ljava/io/InputStream; -> h.a (Ljava/lang/String;)Ljava/io/InputStream; checkUpdate()V@926
     INVOKEVIRTUAL 0x00 0x32   INVOKEVIRTUAL 0x03 0x51
    method ref net.minecraft.src.TexturePackBase.getInputStream (Ljava/lang/String;)Ljava/io/InputStream; -> h.a (Ljava/lang/String;)Ljava/io/InputStream; loadColorMap(Ljava/lang/String;)[I@4
     INVOKEVIRTUAL 0x00 0x32   INVOKEVIRTUAL 0x03 0x51
    field ref net.minecraft.src.World.lightningFlash I -> vq.s I computeLightmap(Lkz;Lvq;)Z@234
     GETFIELD 0x00 0x3d        GETFIELD 0x03 0x53
    method ref net.minecraft.src.World.getSunAngle (F)F -> vq.b (F)F computeLightmap(Lkz;Lvq;)Z@248
     INVOKEVIRTUAL 0x00 0x3f   INVOKEVIRTUAL 0x03 0x55
    field ref net.minecraft.src.EntityRenderer.torchFlickerX F -> kz.e F computeLightmap(Lkz;Lvq;)Z@267
     GETFIELD 0x00 0x42        GETFIELD 0x03 0x59
    field ref net.minecraft.client.Minecraft.gameSettings Lnet/minecraft/src/GameSettings; -> net/minecraft/client/Minecraft.A Lhh; computeLightmap(Lkz;Lvq;)Z@287
     GETFIELD 0x00 0x45        GETFIELD 0x03 0x5d
    field ref net.minecraft.src.GameSettings.gammaSetting F -> hh.N F computeLightmap(Lkz;Lvq;)Z@290
     GETFIELD 0x00 0x46        GETFIELD 0x03 0x62
    field ref net.minecraft.client.Minecraft.renderEngine Lnet/minecraft/src/RenderEngine; -> net/minecraft/client/Minecraft.p Lyz; computeLightmap(Lkz;Lvq;)Z@535
     GETFIELD 0x00 0x4a        GETFIELD 0x03 0x66
    field ref net.minecraft.src.EntityRenderer.lightmapTexture I -> kz.d I computeLightmap(Lkz;Lvq;)Z@545
     GETFIELD 0x00 0x4b        GETFIELD 0x03 0x69
    method ref net.minecraft.src.RenderEngine.createTextureFromBytes ([IIII)V -> yz.a ([IIII)V computeLightmap(Lkz;Lvq;)Z@548
     INVOKEVIRTUAL 0x00 0x4c   INVOKEVIRTUAL 0x03 0x6d
    field ref com.pclewis.mcpatcher.mod.Colorizer.fogChunkManager Lnet/minecraft/src/WorldChunkManager; -> com.pclewis.mcpatcher.mod.Colorizer.fogChunkManager Lqu; setupForFog(Lqu;Lms;)V@1
     PUTSTATIC 0x00 0x5c       PUTSTATIC 0x03 0x6f
    field ref com.pclewis.mcpatcher.mod.Colorizer.fogChunkManager Lnet/minecraft/src/WorldChunkManager; -> com.pclewis.mcpatcher.mod.Colorizer.fogChunkManager Lqu; computeFogColor(I)Z@10
     GETSTATIC 0x00 0x5c       GETSTATIC 0x03 0x6f
    field ref com.pclewis.mcpatcher.mod.Colorizer.fogChunkManager Lnet/minecraft/src/WorldChunkManager; -> com.pclewis.mcpatcher.mod.Colorizer.fogChunkManager Lqu; computeFogColor(I)Z@102
     GETSTATIC 0x00 0x5c       GETSTATIC 0x03 0x6f
    field ref com.pclewis.mcpatcher.mod.Colorizer.fogCamera Lnet/minecraft/src/Entity; -> com.pclewis.mcpatcher.mod.Colorizer.fogCamera Lms; setupForFog(Lqu;Lms;)V@5
     PUTSTATIC 0x00 0x5d       PUTSTATIC 0x03 0x71
    field ref com.pclewis.mcpatcher.mod.Colorizer.fogCamera Lnet/minecraft/src/Entity; -> com.pclewis.mcpatcher.mod.Colorizer.fogCamera Lms; computeFogColor(I)Z@16
     GETSTATIC 0x00 0x5d       GETSTATIC 0x03 0x71
    field ref com.pclewis.mcpatcher.mod.Colorizer.fogCamera Lnet/minecraft/src/Entity; -> com.pclewis.mcpatcher.mod.Colorizer.fogCamera Lms; computeFogColor(I)Z@28
     GETSTATIC 0x00 0x5d       GETSTATIC 0x03 0x71
    field ref com.pclewis.mcpatcher.mod.Colorizer.fogCamera Lnet/minecraft/src/Entity; -> com.pclewis.mcpatcher.mod.Colorizer.fogCamera Lms; computeFogColor(I)Z@36
     GETSTATIC 0x00 0x5d       GETSTATIC 0x03 0x71
    field ref com.pclewis.mcpatcher.mod.Colorizer.fogCamera Lnet/minecraft/src/Entity; -> com.pclewis.mcpatcher.mod.Colorizer.fogCamera Lms; computeFogColor(I)Z@44
     GETSTATIC 0x00 0x5d       GETSTATIC 0x03 0x71
    class ref net.minecraft.src.BiomeGenBase -> zp setupForFog(Lqu;Lms;)V@40
     CHECKCAST 0x00 0x63       CHECKCAST 0x03 0x39
    field ref net.minecraft.src.BiomeGenBase.temperature F -> zp.D F setupForFog(Lqu;Lms;)V@49
     GETFIELD 0x00 0x64        GETFIELD 0x03 0x73
    field ref net.minecraft.src.BiomeGenBase.temperature F -> zp.D F setupForFog(Lqu;Lms;)V@67
     GETFIELD 0x00 0x64        GETFIELD 0x03 0x73
    field ref net.minecraft.src.BiomeGenBase.rainfall F -> zp.E F setupForFog(Lqu;Lms;)V@63
     GETFIELD 0x00 0x65        GETFIELD 0x03 0x76
    field ref net.minecraft.src.BiomeGenBase.biomeID I -> zp.K I setupForFog(Lqu;Lms;)V@86
     GETFIELD 0x00 0x67        GETFIELD 0x03 0x79
    field ref net.minecraft.src.BiomeGenBase.biomeName Ljava/lang/String; -> zp.w Ljava/lang/String; setupForFog(Lqu;Lms;)V@96
     GETFIELD 0x00 0x68        GETFIELD 0x03 0x7c
    field ref net.minecraft.src.Entity.posX D -> ms.o D computeFogColor(I)Z@31
     GETFIELD 0x00 0x69        GETFIELD 0x03 0x81
    field ref net.minecraft.src.Entity.posY D -> ms.p D computeFogColor(I)Z@39
     GETFIELD 0x00 0x6a        GETFIELD 0x03 0x83
    field ref net.minecraft.src.Entity.posZ D -> ms.q D computeFogColor(I)Z@47
     GETFIELD 0x00 0x6b        GETFIELD 0x03 0x86
    field ref net.minecraft.src.Potion.id I -> yg.H I setupPotion(Lyg;)V@9
     GETFIELD 0x00 0x71        GETFIELD 0x03 0x8b
    field ref net.minecraft.src.Potion.name Ljava/lang/String; -> yg.I Ljava/lang/String; setupPotion(Lyg;)V@19
     GETFIELD 0x00 0x72        GETFIELD 0x03 0x8d
    field ref net.minecraft.src.Potion.name Ljava/lang/String; -> yg.I Ljava/lang/String; checkUpdate()V@428
     GETFIELD 0x00 0x72        GETFIELD 0x03 0x8d
    field ref net.minecraft.src.Potion.color I -> yg.N I setupPotion(Lyg;)V@26
     GETFIELD 0x00 0x73        GETFIELD 0x03 0x8f
    field ref net.minecraft.src.Potion.color I -> yg.N I setupPotion(Lyg;)V@38
     GETFIELD 0x00 0x73        GETFIELD 0x03 0x8f
    field ref net.minecraft.src.Potion.color I -> yg.N I checkUpdate()V@281
     PUTFIELD 0x00 0x73        PUTFIELD 0x03 0x8f
    field ref net.minecraft.src.Potion.color I -> yg.N I loadIntColor(Ljava/lang/String;Lyg;)V@26
     PUTFIELD 0x00 0x73        PUTFIELD 0x03 0x8f
    field ref net.minecraft.src.Potion.origColor I -> yg.origColor I setupPotion(Lyg;)V@41
     PUTFIELD 0x00 0x74        PUTFIELD 0x03 0x91
    field ref net.minecraft.src.Potion.origColor I -> yg.origColor I checkUpdate()V@278
     GETFIELD 0x00 0x74        GETFIELD 0x03 0x91
    field ref net.minecraft.client.Minecraft.texturePackList Lnet/minecraft/src/TexturePackList; -> net/minecraft/client/Minecraft.E Lfy; checkUpdate()V@6
     GETFIELD 0x00 0x78        GETFIELD 0x03 0x94
    field ref net.minecraft.client.Minecraft.texturePackList Lnet/minecraft/src/TexturePackList; -> net/minecraft/client/Minecraft.E Lfy; checkUpdate()V@19
     GETFIELD 0x00 0x78        GETFIELD 0x03 0x94
    field ref net.minecraft.src.TexturePackList.selectedTexturePack Lnet/minecraft/src/TexturePackBase; -> fy.a Lh; checkUpdate()V@9
     GETFIELD 0x00 0x79        GETFIELD 0x03 0x98
    field ref net.minecraft.src.TexturePackList.selectedTexturePack Lnet/minecraft/src/TexturePackBase; -> fy.a Lh; checkUpdate()V@22
     GETFIELD 0x00 0x79        GETFIELD 0x03 0x98
    field ref net.minecraft.src.Block.blocksList [Lnet/minecraft/src/Block; -> oe.m [Loe; checkUpdate()V@42
     GETSTATIC 0x00 0x7d       GETSTATIC 0x03 0x9c
    class ref net.minecraft.src.Potion -> yg checkUpdate()V@272
     CHECKCAST 0x00 0x8a       CHECKCAST 0x03 0x88
    class ref net.minecraft.src.Potion -> yg checkUpdate()V@423
     CHECKCAST 0x00 0x8a       CHECKCAST 0x03 0x88
    method ref com.pclewis.mcpatcher.mod.Colorizer.loadIntColor (Ljava/lang/String;Lnet/minecraft/src/Potion;)V -> com.pclewis.mcpatcher.mod.Colorizer.loadIntColor (Ljava/lang/String;Lyg;)V checkUpdate()V@432
     INVOKESTATIC 0x00 0x97    INVOKESTATIC 0x03 0x9e
   string replace Lnet/minecraft/src/Block; -> Loe; @765
   string replace Lnet/minecraft/src/EntityRenderer; -> Lkz; @2180
   string replace Lnet/minecraft/src/World; -> Lvq; @2195
   string replace Lnet/minecraft/src/Potion; -> Lyg; @5153
   string replace Lnet/minecraft/src/Entity; -> Lms; @4331
   string replace Lnet/minecraft/src/WorldChunkManager; -> Lqu; @464
   string replace Lnet/minecraft/src/BiomeGenBase; -> Lzp; @4226

Done!

#### Patch summary:
__Base
    added com/pclewis/mcpatcher/MCPatcherUtils.class
    added com/pclewis/mcpatcher/Config.class
    Minecraft (net/minecraft/client/Minecraft.class)
        [1] MCPatcherUtils.setMinecraft(this)

HD Textures
    added com/pclewis/mcpatcher/mod/TextureUtils.class
    added com/pclewis/mcpatcher/mod/CustomAnimation$Strip.class
    added com/pclewis/mcpatcher/mod/CustomAnimation$Tile.class
    added com/pclewis/mcpatcher/mod/CustomAnimation$Delegate.class
    added com/pclewis/mcpatcher/mod/TileSize.class
    added com/pclewis/mcpatcher/mod/CustomAnimation.class
    RenderEngine (yz.class)
        [1] (i % 16) * 16 + j * 16 -> (i % 16) * int_size + j * int_size
        [1] (i / 16) * 16 + j * 16 -> (i / 16) * int_size + j * int_size
        [0] 1048576 -> int_glBufferSize
        [1] call TextureUtils.registerTextureFX
        [1] getInputStream(...), readTextureImage -> getResourceAsBufferedImage(...)
        [1] glTexSubImage2D(...,16,16) -> glTexSubImage2D(...,int_size,int_size)
        [3] imageData.clear(), .put(), .limit() -> imageData = TextureUtils.getByteBuffer()
        [1] insert method setTileSize (Lnet/minecraft/client/Minecraft;)V
        [1] null check in getImageRGB
        [1] null check in setupTexture
        [16] readTextureImage(getInputStream(...)) -> getResourceAsBufferedImage(...)
    TextureFX (sr.class)
        [1] array size 1024 -> int_numBytes
    Compass (ss.class)
        [4] * 16 -> int_size
        [1] -4 -> int_compassCrossMin
        [1] -8 -> int_compassNeedleMin
        [2] 7.5D -> double_compassCenterMin
        [2] 8.5D -> double_compassCenterMax
        [1] array size 256 -> int_numPixels
        [1] getRGB(...16,16,...16) -> getRGB(...int_size,int_size,...int_size)
        [1] if i > 16 -> int_compassNeedleMax
        [1] if i > 4 -> int_compassCrossMax
        [1] while i < 256 -> int_numPixels
    Fire (mn.class)
        [1] % 20 -> int_flameHeight
        [4] * 16 -> int_size
        [1] 1.06F -> float_flameNudge
        [2] array size 320 -> int_flameArraySize
        [1] if i < 19 -> int_flameHeightMinus1
        [2] while i < 16 -> int_size
        [2] while i < 20 -> int_flameHeight
        [1] while i < 256 -> int_numPixels
    StillLava (bo.class)
        [10] & 15 -> int_sizeMinus1
        [0] & 255 -> int_numPixelsMinus1
        [12] * 16 -> int_size
        [4] array size 256 -> int_numPixels
        [2] while i < 16 -> int_size
        [1] while i < 256 -> int_numPixels
    FlowLava (fv.class)
        [10] & 15 -> int_sizeMinus1
        [1] & 255 -> int_numPixelsMinus1
        [13] * 16 -> int_size
        [4] array size 256 -> int_numPixels
        [2] while i < 16 -> int_size
        [1] while i < 256 -> int_numPixels
    StillWater (pd.class)
        [2] & 15 -> int_sizeMinus1
        [0] & 255 -> int_numPixelsMinus1
        [9] * 16 -> int_size
        [4] array size 256 -> int_numPixels
        [4] while i < 16 -> int_size
        [1] while i < 256 -> int_numPixels
    FlowWater (ack.class)
        [2] & 15 -> int_sizeMinus1
        [1] & 255 -> int_numPixelsMinus1
        [10] * 16 -> int_size
        [4] array size 256 -> int_numPixels
        [4] while i < 16 -> int_size
        [1] while i < 256 -> int_numPixels
    ItemRenderer (lv.class)
        [4] 0.001953125F -> float_texNudge
        [4] 16.0F -> float_size
        [2] tool pixel top
        [4] tool tex calculation
        [4] while i < 16 -> int_size
    Watch (hg.class)
        [1] % 16 -> int_size
        [2] & 15 -> int_sizeMinus1
        [3] * 16 -> int_size
        [1] / 16 -> int_size
        [2] 15.0D -> double_sizeMinus1
        [2] 16.0D -> double_size
        [2] array size 256 -> int_numPixels
        [2] getRGB(...16,16,...16) -> getRGB(...int_size,int_size,...int_size)
        [1] while i < 256 -> int_numPixels
    Portal (xs.class)
        [1] * 16 -> int_size
        [2] * 8 -> int_sizeHalf
        [2] 16.0F -> float_size
        [1] array size 32x1024 -> int_numBytes
        [0] if i < 256 -> int_numPixels
        [2] while i < 16 -> int_size
        [1] while i < 256 -> int_numPixels
    Minecraft (net/minecraft/client/Minecraft.class)
        [1] TextureUtils.setTileSize(), renderEngine.setTileSize() on startup
        [1] check for texture pack change on each tick
        [9] remove registerTextureFX call
    GLAllocation (ep.class)
    TexturePackList (fy.class)
        [1] TexturePackList.setTileSize(selectedTexturePack) on texture pack change
        [1] make field defaultTexturePack public
    TexturePackBase (h.class)
    TexturePackCustom (ahk.class)
        [1] closeTexturePackFile(this)
        [1] insert field lastModified J
        [1] insert field origZip Ljava/util/zip/ZipFile;
        [1] insert field tmpFile Ljava/io/File;
        [1] make field file public
        [1] make field zipFile public
        [1] openTexturePackFile(this)
    TexturePackDefault (kl.class)
    FontRenderer (mq.class)
        [1] insert method initialize ()V
        [1] make field isUnicode public
    GameSettings (hh.class)
    GetResource (multiple matches: agr ahk ei hg kl mq ss)
        [8] ImageIO.read(getResource(...)) -> getResourceAsBufferedImage(...)
    ColorizerWater (xw.class)
        [1] make field colorBuffer public
    ColorizerGrass (xy.class)
        [1] make field colorBuffer public
    ColorizerFoliage (gk.class)
        [1] make field colorBuffer public

HD Font
    added com/pclewis/mcpatcher/mod/FontUtils.class
    FontRenderer (mq.class)
        [2] FontUtils.computeCharWidths on init
        [1] getStringWidth int -> float
        [1] insert field charWidthf [F
        [1] use charWidthf in getStringWidth (init)
        [1] use charWidthf in getStringWidth (loop)
        [1] use charWidthf in getStringWidth (return value)
        [2] use charWidthf in glTranslatef call

Better Grass
    Material (aan.class)
    Block (oe.class)
    BlockGrass (qb.class)
        [1] check surrounding blocks in getBlockTexture
        [1] initialize grassMatrix
        [1] insert field grassMatrix [[I
    BlockMycelium (aje.class)
        [1] check surrounding blocks in getBlockTexture
        [1] initialize grassMatrix
        [1] insert field grassMatrix [[I
    IBlockAccess (aiw.class)
    RenderBlocks (uc.class)
        [2] if (getBlockTexture == 0) useBiomeColor = true (AO)
        [4] if (getBlockTexture == 0) useBiomeColor = true (non-AO post-1.8)
        [0] if (getBlockTexture == 0) useBiomeColor = true (non-AO pre-1.8)

Random Mobs
    added com/pclewis/mcpatcher/mod/MobRandomizer.class
    RenderLiving (ey.class)
        [1] replace mob textures
    RenderSpider (ajy.class)
        [1] override spider eye texture
    RenderEnderman (rv.class)
        [1] override enderman eye texture
    Entity (ms.class)
        [1] insert field randomMobsSkin J
        [1] insert field randomMobsSkinSet Z
        [1] read skin from nbt
        [1] write skin to nbt
    EntityLiving (aar.class)
    NBTTagCompound (abx.class)
    Minecraft (net/minecraft/client/Minecraft.class)
    TexturePackList (fy.class)
    TexturePackBase (h.class)

Custom Colors
    added com/pclewis/mcpatcher/mod/Colorizer.class
    Minecraft (net/minecraft/client/Minecraft.class)
    TexturePackList (fy.class)
    TexturePackBase (h.class)
    IBlockAccess (aiw.class)
    Block (oe.class)
        [1] override color multiplier for all blocks
        [1] override default color for all blocks
    BiomeGenBase (zp.class)
        [1] map biomes by name
    BiomeGenSwamp (afp.class)
        [1] override swamp foliage color
        [1] override swamp grass color
    BlockFluid (aes.class)
        [1] override water color
    BlockCauldron (vw.class)
    Item (ww.class)
    ItemBlock (tw.class)
        [1] insert method getColorFromDamage (II)I
    ItemRenderer (lv.class)
        [1] override water block color in third person
    Potion (yg.class)
        [1] insert field origColor I
        [1] make field color public
        [1] make field name public
        [1] map potions by name
    PotionHelper (hl.class)
        [1] override water bottle color
    ColorizerFoliage (gk.class)
        [1] override default basic foliage color
        [1] override default birch foliage color
        [1] override default pine foliage color
    BlockLeaves (tb.class)
        [1] override biome birch foliage color
        [1] override biome pine foliage color
    World (vq.class)
        [1] override sky color
    WorldProvider (aip.class)
        [1] override fog color
    WorldChunkManager (qu.class)
    Entity (ms.class)
    EntityFX (qv.class)
    EntityRainFX (qj.class)
        [1] override rain drop color
    EntityDropParticleFX (fs.class)
        [1] override lava drop color
        [1] override water drop color
        [1] remove water drop color update
    EntitySplashFX (nb.class)
        [1] override splash drop color
    EntityBubbleFX (tz.class)
        [1] override bubble drop color
    EntityLiving (aar.class)
    EntityRenderer (kz.class)
        [1] make field torchFlickerX public
        [1] override fog color
        [1] override lightmap
        [1] override underwater ambient color
    BlockLilyPad (wl.class)
        [3] override lily pad color
    BlockRedstoneWire (aff.class)
        [1] override redstone wire particle color
    RenderBlocks (uc.class)
        [1] colorize bottom of water block
        [1] colorize cauldron water color
        [6] colorize falling sand and gravel
        [1] override redstone wire color
    EntityReddustFX (ye.class)
        [1] override redstone particle color
    RenderGlobal (l.class)
        [1] override cloud type
    BlockStem (ach.class)
        [1] override pumpkin and melon stem color
    EntityList (yr.class)
        [1] set up mapping for spawnable entities
    ItemSpawnerEgg (aaw.class)
        [3] override spawner egg color

